Workbook
Name LISTA_OBJETIVOS: [13]apoio!$G$2:$G$13

Sheet CAPA
B2: PLANO DE MÍDIA
B4: CLIENTE | C4: : | D4: MINISTÉRIO DA EDUCAÇÃO
B6: CAMPANHA | C6: : | D6: FIES 2026
B8: PERÍODO | C8: : | D8: JULHO DE 2026
B10: AÇÃO MIDIAWEB | C10: :
B12: TIPO DE CAMPANHA | C12: : | D12: UTILIDADE PÚBLICA
B14: VERSÃO | C14: : | D14: V1
B16: TOTAL NEGOCIADO (100%) | C16: : | D16: =RESUMO!G65 -> 3972547.1
B18: TOTAL DESEMBOLSO (95%) | C18: : | D18: =RESUMO!H65 -> 3819999.8
B20: TOTAL PRODUÇÃO | C20: : | D20: =CRONO!AK18 -> 180000
B22: TOTAL MÍDIA (94,5%) + PRODUÇÃO | C22: : | D22: =D20+D18 -> 3999999.8
B24: DATA | C24: : | D24: 15/07/2026

Sheet CRONO
B2: CRONOGRAMA DE VEICULAÇÃO
B3: =RESUMO!C5 -> MINISTÉRIO DA EDUCAÇÃO
B4: =RESUMO!C6 -> FIES 2026
B6: MEIO | C6: MERCADO | D6: FORMATO | E6: PERÍODO DETALHADO DE VEICULAÇÃO | F6: JUNHO 2026 - 06/2026 | Q6: JULHO | AJ6: VALOR TOTAL NEGOCIADO 100% | AK6: VALOR DESEMBOLSO 95% | AM6: PART. MEIO %
F7: 1 | G7: =F7+1 -> 2 | H7: =G7+1 -> 3 | I7: =H7+1 -> 4 | J7: =I7+1 -> 5 | K7: =J7+1 -> 6 | L7: =K7+1 -> 7 | M7: =L7+1 -> 8 | N7: =M7+1 -> 9 | ... P7: =O7+1 -> 11 | Q7: 10 | R7: =Q7+1 -> 11 | S7: =R7+1 -> 12 | T7: =S7+1 -> 13 | U7: =T7+1 -> 14 | V7: =U7+1 -> 15 | W7: =V7+1 -> 16 | X7: =W7+1 -> 17 | Y7: =X7+1 -> 18 | ... AI7: =AH7+1 -> 28
F8: S | G8: T | H8: Q | I8: Q | J8: S | K8: S | L8: D | M8: S | N8: T | O8: Q | P8: Q | Q8: S | R8: S | S8: D | T8: S | U8: T | V8: Q | W8: Q | X8: S | Y8: S | Z8: D | AA8: S | AB8: T | AC8: Q | AD8: Q | AE8: S | AF8: S | AG8: D | AH8: S | AI8: T
B10: MÍDIA EXTERIOR | AJ10: =SUM(AJ11:AJ11) -> 2138848.9 | AK10: =SUM(AK11:AK11) -> 2031906.5 | AM10: =AK10/$AK$16 -> 0.53191272
B11: DOOH | C11: DF, SP, BA, RJ, CE, PR, PE, AM, MG, GO, PA, PI, MA | D11: 10" - 15" | E11: DE 16/07 A17/07 | AJ11: ='DOOH - METRÔ'!G33+'DOOH - MUB'!G28+'DOOH - ESTABELECIMENTOS'!F37+'DOOH - PAINEL'!F169+'DOOH - TERMINAL RODOVIÁRIO'!G36 -> 2138848.9 | AK11: =AJ11*0.95 -> 2031906.5 | AM11: =AK11/$AK$20 -> 0.50797665
B13: INTERNET | AJ13: =SUM(AJ14:AJ14) -> 1833698.2 | AK13: =SUM(AK14:AK14) -> 1788093.3 | AM13: =AK13/$AK$16 -> 0.46808728
B14: INTERNET | C14: NACIONAL | D14: DIVERSOS | E14: DE 16/07 A17/07 | AJ14: =INTERNET!AH32 -> 1833698.2 | AK14: =INTERNET!AJ32 -> 1788093.3 | AM14: =AK14/$AK$20 -> 0.44702335
B16: TOTAL MÍDIA | AJ16: =AJ10+AJ13 -> 3972547.1 | AK16: =AK10+AK13 -> 3819999.8 | AM16: =AK16/AK20 -> 0.955
B18: TOTAL PREVISTO PARA PRODUÇÃO DE MÍDIA | AK18: 180000 | AM18: =AK18/AK20 -> 0.045000003
B20: TOTAL GERAL | AK20: =AK18+AK16 -> 3999999.8 | AM20: =AM16+AM18 -> 1

Sheet RESUMO
C1: #EXTERNO.CONFIDENCIAL
C3: RESUMO DE VERBA
C5: =CAPA!D4 -> MINISTÉRIO DA EDUCAÇÃO
C6: =CAPA!D6 -> FIES 2026
C7: =CAPA!D8 -> JULHO DE 2026
C9: MEIO | D9: TIPO | E9: PRAÇA | G9: VALOR 100% | H9: VALOR TOTAL 95% | I9: % MEIO | J9: % CAMPANHA | L9: REPRESENTANTE
C12: MIDIA EXTERIOR DIGITAL
C13: URBAN + | D13: METRÔ | E13: DF | G13: ='DOOH - METRÔ'!G28 -> 37273.6 | H13: =G13*0.95 -> 35409.92 | I13: =H13/$H$47 -> 0.017426944 | J13: =H13/$H$65 -> 0.0092696132 | L13: MIDIA MAIS
C14: MOBTV | D14: METRÔ | E14: DF | G14: ='DOOH - METRÔ'!G29 -> 44626.4 | H14: =G14*0.95 -> 42395.08 | I14: =H14/$H$47 -> 0.020864681 | J14: =H14/$H$65 -> 0.011098189 | L14: DS MIDIA
C15: MEDIA MEGAS | D15: METRÔ | E15: SP | G15: ='DOOH - METRÔ'!G30 -> 209000 | H15: =G15*0.95 -> 198550 | I15: =H15/$H$47 -> 0.097716112 | J15: =H15/$H$65 -> 0.051976443 | L15: MEDIA MEGAS
C16: ELETROMÍDIA - TV MINUTO | D16: METRÔ | E16: SP | G16: ='DOOH - METRÔ'!G31 -> 56262.246 | H16: =G16*0.95 -> 53449.134 | I16: =H16/$H$47 -> 0.026304918 | J16: =H16/$H$65 -> 0.013991921 | L16: STREET
C17: ELETROMIDIA | D17: METRÔ | E17: RJ | G17: ='DOOH - METRÔ'!G32 -> 0 | H17: =G17*0.95 -> 0 | I17: =H17/$H$47 -> 0 | J17: =H17/$H$65 -> 0 | L17: STREET
C18: VISUPLAC | D18: MUB | E18: DF | G18: ='DOOH - MUB'!G24 -> 67961.143 | H18: ='DOOH - MUB'!H24 -> 64563.086 | I18: =H18/$H$47 -> 0.031774635 | J18: =H18/$H$65 -> 0.016901332 | L18: MOSAICO
C19: PLUREX | D19: MUB | E19: RJ | G19: ='DOOH - MUB'!G25 -> 24624 | H19: ='DOOH - MUB'!H25 -> 23392.8 | I19: =H19/$H$47 -> 0.011512735 | J19: =H19/$H$65 -> 0.00612377 | L19: BO GROUP
C20: DESTAKE | D20: MUB | E20: MG | G20: ='DOOH - MUB'!G26 -> 129846 | H20: ='DOOH - MUB'!H26 -> 123353.7 | I20: =H20/$H$47 -> 0.060708355 | J20: =H20/$H$65 -> 0.032291547 | L20: MIDIA MAIS
C21: ELETROMIDIA | D21: MUB | E21: SP | G21: ='DOOH - MUB'!G27 -> 128280.71 | H21: ='DOOH - MUB'!H27 -> 121866.68 | I21: =H21/$H$47 -> 0.059976519 | J21: =H21/$H$65 -> 0.031902274 | L21: STREET
C22: INSIGHT MIDIA | D22: ESTABELECIMENTOS | E22: PE, CE, DF, SP, BA, PR | G22: ='DOOH - ESTABELECIMENTOS'!F35 -> 243456 | H22: ='DOOH - ESTABELECIMENTOS'!G35 -> 231283.2 | I22: =H22/$H$47 -> 0.11382571 | J22: =H22/$H$65 -> 0.060545344 | L22: INSIGHT
C23: BEEP MIDIA | D23: ESTABELECIMENTOS | E23: PA, RJ, MA | G23: ='DOOH - ESTABELECIMENTOS'!F36 -> 117924 | H23: ='DOOH - ESTABELECIMENTOS'!G36 -> 112027.8 | I23: =H23/$H$47 -> 0.055134329 | J23: =H23/$H$65 -> 0.029326651 | L23: BEEP MIDIA
C24: WE SUPER OOH | D24: PAINEL DE LED | E24: PE, CE, GO | G24: ='DOOH - PAINEL'!F150 -> 54847.605 | H24: ='DOOH - PAINEL'!H150 -> 52105.225 | I24: =H24/$H$47 -> 0.025643515 | J24: =H24/$H$65 -> 0.013640112 | L24: MOSAICO
C25: MLA MIDIA | D25: PAINEL DE LED | E25: PE, DF | G25: ='DOOH - PAINEL'!F151 -> 40759.2 | H25: ='DOOH - PAINEL'!H151 -> 38721.24 | I25: =H25/$H$47 -> 0.019056605 | J25: =H25/$H$65 -> 0.010136451 | L25: MLA MIDIA
C26: LED MAIS | D26: PAINEL DE LED | E26: PR, BA, CE, DF, GO | G26: ='DOOH - PAINEL'!F152 -> 66960 | H26: ='DOOH - PAINEL'!H152 -> 63612 | I26: =H26/$H$47 -> 0.031306559 | J26: =H26/$H$65 -> 0.016652357 | L26: G2
C27: PLAN PAINÉIS | D27: PAINEL DE LED | E27: PR, CE, AM | G27: ='DOOH - PAINEL'!F153 -> 22403.571 | H27: ='DOOH - PAINEL'!H153 -> 21283.393 | I27: =H27/$H$47 -> 0.010474593 | J27: =H27/$H$65 -> 0.0055715692 | L27: PLAN PAINEIS
C28: 55 MÍDIA | D28: PAINEL DE LED | E28: CE | G28: ='DOOH - PAINEL'!F154 -> 115347.9 | H28: ='DOOH - PAINEL'!H154 -> 109580.5 | I28: =H28/$H$47 -> 0.053929896 | J28: =H28/$H$65 -> 0.028685998 | L28: MIDIA MAIS
C29: NORDESTE MIDIA EXTERIOR DIGITAL | D29: PAINEL DE LED | E29: CE | G29: ='DOOH - PAINEL'!F155 -> 22400 | H29: ='DOOH - PAINEL'!H155 -> 21280 | I29: =H29/$H$47 -> 0.010472923 | J29: =H29/$H$65 -> 0.005570681
C30: URB | D30: PAINEL DE LED | E30: AM, PI, PA | G30: ='DOOH - PAINEL'!F156 -> 66047 | H30: ='DOOH - PAINEL'!H156 -> 62744.65 | I30: =H30/$H$47 -> 0.030879694 | J30: =H30/$H$65 -> 0.016425302
C31: ALTERNAMIDIA | D31: PAINEL DE LED | E31: AM, MG, GO | G31: ='DOOH - PAINEL'!F157 -> 56729.991 | H31: ='DOOH - PAINEL'!H157 -> 53893.491 | I31: =H31/$H$47 -> 0.026523608 | J31: =H31/$H$65 -> 0.014108245
C32: DMIDIA | D32: PAINEL DE LED | E32: MG | G32: ='DOOH - PAINEL'!F158 -> 34644.998 | H32: ='DOOH - PAINEL'!H158 -> 32912.748 | I32: =H32/$H$47 -> 0.016197964 | J32: =H32/$H$65 -> 0.0086159032
C33: DOORS | D33: PAINEL DE LED | E33: MG, GO | G33: ='DOOH - PAINEL'!F159 -> 63104 | H33: ='DOOH - PAINEL'!H159 -> 59948.8 | I33: =H33/$H$47 -> 0.02950372 | J33: =H33/$H$65 -> 0.015693404
C34: TRAFFIC LED | D34: PAINEL DE LED | E34: DF | G34: ='DOOH - PAINEL'!F160 -> 11995.62 | H34: ='DOOH - PAINEL'!H160 -> 11395.839 | I34: =H34/$H$47 -> 0.0056084466 | J34: =H34/$H$65 -> 0.0029832041
C35: LEDME | D35: PAINEL DE LED | E35: DF | G35: ='DOOH - PAINEL'!F161 -> 50656.32 | H35: ='DOOH - PAINEL'!H161 -> 48123.504 | I35: =H35/$H$47 -> 0.023683917 | J35: =H35/$H$65 -> 0.012597777
C36: UNIVERSO BR DOOH | D36: PAINEL DE LED | E36: DF, SP | G36: ='DOOH - PAINEL'!F162 -> 22205.714 | H36: ='DOOH - PAINEL'!H162 -> 21095.429 | I36: =H36/$H$47 -> 0.010382086 | J36: =H36/$H$65 -> 0.0055223639
C37: ANUNCIART | D37: PAINEL DE LED | E37: DF | G37: ='DOOH - PAINEL'!F163 -> 26058.24 | H37: ='DOOH - PAINEL'!H163 -> 24755.328 | I37: =H37/$H$47 -> 0.012183301 | J37: =H37/$H$65 -> 0.0064804528
C38: EAGLE PUBLICITY | D38: PAINEL DE LED | E38: DF | G38: ='DOOH - PAINEL'!F164 -> 81884.4 | H38: ='DOOH - PAINEL'!H164 -> 77790.18 | I38: =H38/$H$47 -> 0.038284331 | J38: =H38/$H$65 -> 0.020363923
C39: AGENCIA MAJESTIC DOOH | D39: PAINEL DE LED | E39: DF | G39: ='DOOH - PAINEL'!F165 -> 63000 | H39: ='DOOH - PAINEL'!H165 -> 59850 | I39: =H39/$H$47 -> 0.029455096 | J39: =H39/$H$65 -> 0.01566754
C40: ALTO IMPACTO | D40: PAINEL DE LED | E40: RJ | G40: ='DOOH - PAINEL'!F166 -> 31146.667 | H40: ='DOOH - PAINEL'!H166 -> 29589.333 | I40: =H40/$H$47 -> 0.01456235 | J40: =H40/$H$65 -> 0.0077458993
... C42: INTELICOM | D42: PAINEL DE LED | E42: PE | G42: ='DOOH - PAINEL'!F168 -> 55478.6 | H42: ='DOOH - PAINEL'!H168 -> 52704.67 | I42: =H42/$H$47 -> 0.025938531 | J42: =H42/$H$65 -> 0.013797035
C43: MOBILAPA | D43: TERM. RODOVIÁRIO | E43: BA | G43: ='DOOH - TERMINAL RODOVIÁRIO'!G32 -> 29281.714 | H43: ='DOOH - TERMINAL RODOVIÁRIO'!H32 -> 27817.629 | I43: =H43/$H$47 -> 0.013690408 | J43: =H43/$H$65 -> 0.0072821022 | L43: PLAN PAINÉIS
C44: ALL 7 MIDIA | D44: TERM. RODOVIÁRIO | E44: BA | G44: ='DOOH - TERMINAL RODOVIÁRIO'!G33 -> 19511.28 | H44: ='DOOH - TERMINAL RODOVIÁRIO'!H33 -> 18535.716 | I44: =H44/$H$47 -> 0.0091223273 | J44: =H44/$H$65 -> 0.004852282 | L44: ALTERNAMIDIA
C45: MIDI | D45: TERM. RODOVIÁRIO | E45: BA | G45: ='DOOH - TERMINAL RODOVIÁRIO'!G34 -> 70761.6 | H45: ='DOOH - TERMINAL RODOVIÁRIO'!H34 -> 67223.52 | I45: =H45/$H$47 -> 0.033083964 | J45: =H45/$H$65 -> 0.017597781 | L45: G2
C46: ONBUS | D46: TERM. RODOVIÁRIO | E46: RJ | G46: ='DOOH - TERMINAL RODOVIÁRIO'!G35 -> 16070.4 | H46: ='DOOH - TERMINAL RODOVIÁRIO'!H35 -> 15266.88 | I46: =H46/$H$47 -> 0.0075135742 | J46: =H46/$H$65 -> 0.0039965657 | L46: MIDIALAND
C47: TOTAL MIDIA EXTERIOR DIGITAL | G47: =SUBTOTAL(9,G13:G46) -> 2138848.9 | H47: =SUBTOTAL(9,H13:H46) -> 2031906.5 | I47: =SUBTOTAL(9,I13:I46) -> 1 | J47: =H47/$H$65 -> 0.53191272
C49: INTERNET
C50: META | D50: REDE SOCIAL | E50: NACIONAL | G50: =INTERNET!D36 -> 256000 | H50: =INTERNET!E36 -> 289280 | I50: =H50/$H$62 -> 0.16178127 | J50: =H50/$H$65 -> 0.075727754 | L50: =C50 -> META
C51: TIK TOK | D51: REDE SOCIAL | E51: NACIONAL | G51: =INTERNET!D37 -> 206250 | H51: =INTERNET!E37 -> 195937.5 | I51: =H51/$H$62 -> 0.10957901 | J51: =H51/$H$65 -> 0.051292543 | L51: =C51 -> TIK TOK
C52: NEWCOM | D52: REDE DE CONTEÚDO | E52: NACIONAL | G52: =INTERNET!D38 -> 176225.37 | H52: =INTERNET!E38 -> 167414.1 | I52: =H52/$H$62 -> 0.093627162 | J52: =H52/$H$65 -> 0.043825683 | L52: STREET
C53: BAIHIVE | D53: REDE DE CONTEÚDO | E53: NACIONAL | G53: =INTERNET!D39 -> 145104.18 | H53: =INTERNET!E39 -> 137848.97 | I53: =H53/$H$62 -> 0.077092716 | J53: =H53/$H$65 -> 0.036086119 | L53: DUE MIDIA
C54: MÍDIA MINDS | D54: REDE DE CONTEÚDO | E54: NACIONAL | G54: =INTERNET!AH17 -> 145103.96 | H54: =INTERNET!AJ17 -> 137848.76 | I54: =H54/$H$62 -> 0.077092601 | J54: =H54/$H$65 -> 0.036086065 | L54: DUE MIDIA
C55: ADZEP | D55: REDE DE CONTEÚDO | E55: NACIONAL | G55: =INTERNET!D41 -> 176225.43 | H55: =INTERNET!E41 -> 167414.16 | I55: =H55/$H$62 -> 0.093627196 | J55: =H55/$H$65 -> 0.043825699 | L55: MOB
C56: RANGE | D56: REDE DE VÍDEO | E56: NACIONAL | G56: =INTERNET!D42 -> 108000 | H56: =INTERNET!E42 -> 102600 | I56: =H56/$H$62 -> 0.057379557 | J56: =H56/$H$65 -> 0.02685864 | L56: DIRETO
C57: CITTAMOBI | D57: APP DE MOBILIDADE | E57: NACIONAL | G57: =INTERNET!D44 -> 121684.77 | H57: =INTERNET!E44 -> 115600.53 | I57: =H57/$H$62 -> 0.064650166 | J57: =H57/$H$65 -> 0.03026192 | L57: =C57 -> CITTAMOBI
C58: YOU TARGET | D58: WI-FI | E58: NACIONAL | G58: =INTERNET!D46 -> 149021.96 | H58: =INTERNET!E46 -> 141570.87 | I58: =H58/$H$62 -> 0.079174206 | J58: =H58/$H$65 -> 0.037060438 | L58: THE VOICE
C59: CONECTA BRASIL | D59: WI-FI | E59: NACIONAL | G59: =INTERNET!D48 -> 96390 | H59: =INTERNET!E48 -> 91570.5 | I59: =H59/$H$62 -> 0.051211255 | J59: =H59/$H$65 -> 0.023971337 | L59: =C59 -> CONECTA BRASIL
C60: MFAY WI-FI | D60: WI-FI | E60: NACIONAL | G60: =INTERNET!D49 -> 149024 | H60: =INTERNET!E49 -> 141572.8 | I60: =H60/$H$62 -> 0.079175288 | J60: =H60/$H$65 -> 0.037060945 | L60: MOSAICO
C61: TRIPLE A GAMES | D61: GAMES | E61: NACIONAL | G61: =INTERNET!D50 -> 104668.52 | H61: =INTERNET!E50 -> 99435.098 | I61: =H61/$H$62 -> 0.05560957 | J61: =H61/$H$65 -> 0.026030132 | L61: BAIHIVE
C62: TOTAL INTERNET | G62: =SUBTOTAL(9,G50:G61) -> 1833698.2 | H62: =SUBTOTAL(9,H50:H61) -> 1788093.3 | I62: =SUM(I50:I61) -> 1 | J62: =H62/$H$65 -> 0.46808728
C64: MEIO | G64: VALOR TOTAL 100% | H64: VALOR TOTAL 95%
C65: TOTAL GERAL DE MÍDIA | G65: =G47+G62 -> 3972547.1 | H65: =H47+H62 -> 3819999.8
C66: TOTAL GERAL DE PRODUÇÃO | G66: 180000 | H66: 180000
C67: TOTAL GERAL | G67: =G65 -> 3972547.1 | H67: =H65+H66 -> 3999999.8 | J67: =J66+J65 -> 0
C72: AGÊNCIA | D72: VALOR TOTAL 100% | E72: VALOR 95% | G72: RATEIO % | H72: META RATEIO % | I72: META RATEIO
C73: CALIA | D73: =SUMIF($B$12:$B$66,C73,$G$12:$G$66) -> 0 | E73: =SUMIF($B$12:$B$66,C73,$H$12:$H$66) -> 0 | G73: 0.46666666 | H73: =$H$69*G73 -> 0 | I73: =H73-E73 -> 0
C74: SA PROPAGANDA | D74: =SUMIF($B$12:$B$61,C74,$G$12:$G$61) -> 0 | E74: =SUMIF($B$12:$B$61,C74,$H$12:$H$61) -> 0 | G74: 0.46666666 | H74: =$H$69*G74 -> 0 | I74: =H74-E74 -> 0
C75: DE BRITO | D75: =SUMIF($B$12:$B$61,C75,$G$12:$G$61) -> 0 | E75: =SUMIF($B$12:$B$61,C75,$H$12:$H$61) -> 0 | G75: 0.06666668 | H75: =$H$69*G75 -> 0 | I75: =H75-E75 -> 0
C76: TOTAL GERAL | D76: =SUM(D73:D75) -> 0 | E76: =SUM(E73:E75) -> 0 | G76: =SUM(G73:G75) -> 1 | H76: =SUM(H73:H75) -> 0

Sheet RESUMO -ME
B2: RESUMO DE VERBA - MÍDIA EXTERIOR
B4: =CAPA!D4 -> MINISTÉRIO DA EDUCAÇÃO
B5: =CAPA!D6 -> FIES 2026
B6: =CAPA!D8 -> JULHO DE 2026
B8: PRAÇA / MEIO | D8: DOOH | J8: TOTAL POR PRAÇA | K8: VALOR DESEMBOLSO 95% | L8: POPULAÇÃO | M8: SHARE POPULAÇÃO | N8: PARTICIPAÇÃO
D9: METRÔ | E9: PAINEL | F9: TERM. ROD. | G9: MUB | H9: ESTABELECIMENTOS
B10: REGIÃO SUDESTE
B11: #VALUE! | C11: RJ | D11: =SUMIF('DOOH - METRÔ'!$C$8:$C$22,C11,'DOOH - METRÔ'!$W$8:$W$22) -> 0 | E11: =SUMIF('DOOH - PAINEL'!$C:$C,'RESUMO -ME'!C11,'DOOH - PAINEL'!$X:$X) -> 89446.667 | F11: =SUMIF('DOOH - TERMINAL RODOVIÁRIO'!$C$11:$C$26,'RESUMO -ME'!C11,'DOOH - TERMINAL RODOVIÁRIO'!$X$11:$X$26) -> 16070.4 | G11: =SUMIF('DOOH - MUB'!$C$11:$C$17,'RESUMO -ME'!C11,'DOOH - MUB'!$X$11:$X$17) -> 24624 | H11: =SUMIF('DOOH - ESTABELECIMENTOS'!$C$11:$C$28,'RESUMO -ME'!C11,'DOOH - ESTABELECIMENTOS'!$W$11:$W$28) -> 47988 | I11: {=_FV(B11,"População")} -> 6730729 | J11: =SUM(D11:H11) -> 178129.07 | K11: =J11*0.95 -> 169222.61 | L11: {=_FV(B11,"População")} -> 6730729 | M11: =L11/$L$28 -> 0.16907331 | N11: =K11/$K$28 -> 0.083282678
B12: #VALUE! | C12: SP | D12: =SUMIF('DOOH - METRÔ'!$C$8:$C$22,C12,'DOOH - METRÔ'!$W$8:$W$22) -> 265262.25 | E12: =SUMIF('DOOH - PAINEL'!$C:$C,'RESUMO -ME'!C12,'DOOH - PAINEL'!$X:$X) -> 15314.286 | F12: =SUMIF('DOOH - TERMINAL RODOVIÁRIO'!$C$11:$C$26,'RESUMO -ME'!C12,'DOOH - TERMINAL RODOVIÁRIO'!$X$11:$X$26) -> 0 | G12: =SUMIF('DOOH - MUB'!$C$11:$C$17,'RESUMO -ME'!C12,'DOOH - MUB'!$X$11:$X$17) -> 128280.71 | H12: =SUMIF('DOOH - ESTABELECIMENTOS'!$C$11:$C$28,'RESUMO -ME'!C12,'DOOH - ESTABELECIMENTOS'!$W$11:$W$28) -> 76416 | J12: =SUM(D12:H12) -> 485273.25 | K12: =J12*0.95 -> 461009.58 | L12: {=_FV(B12,"População")} -> 11904961 | M12: =L12/$L$28 -> 0.29904802 | N12: =K12/$K$28 -> 0.22688524
B13: #VALUE! | C13: MG | D13: =SUMIF('DOOH - METRÔ'!$C$8:$C$22,C13,'DOOH - METRÔ'!$W$8:$W$22) -> 0 | E13: =SUMIF('DOOH - PAINEL'!$C:$C,'RESUMO -ME'!C13,'DOOH - PAINEL'!$X:$X) -> 85051.849 | F13: =SUMIF('DOOH - TERMINAL RODOVIÁRIO'!$C$11:$C$26,'RESUMO -ME'!C13,'DOOH - TERMINAL RODOVIÁRIO'!$X$11:$X$26) -> 0 | G13: =SUMIF('DOOH - MUB'!$C$11:$C$17,'RESUMO -ME'!C13,'DOOH - MUB'!$X$11:$X$17) -> 129846 | H13: =SUMIF('DOOH - ESTABELECIMENTOS'!$C$11:$C$28,'RESUMO -ME'!C13,'DOOH - ESTABELECIMENTOS'!$W$11:$W$28) -> 0 | J13: =SUM(D13:H13) -> 214897.85 | K13: =J13*0.95 -> 204152.96 | L13: {=_FV(B13,"População")} -> 2415872 | M13: =L13/$L$28 -> 0.060685772 | N13: =K13/$K$28 -> 0.1004736
B14: REGIÃO CENTRO OESTE | E14: =SUMIF('DOOH - PAINEL'!$C:$C,'RESUMO -ME'!C14,'DOOH - PAINEL'!$X:$X) -> 0
B15: #VALUE! | C15: GO | D15: =SUMIF('DOOH - METRÔ'!$C$8:$C$22,C15,'DOOH - METRÔ'!$W$8:$W$22) -> 0 | E15: =SUMIF('DOOH - PAINEL'!$C:$C,'RESUMO -ME'!C15,'DOOH - PAINEL'!$X:$X) -> 62678.821 | F15: =SUMIF('DOOH - TERMINAL RODOVIÁRIO'!$C$11:$C$26,'RESUMO -ME'!C15,'DOOH - TERMINAL RODOVIÁRIO'!$X$11:$X$26) -> 0 | G15: =SUMIF('DOOH - MUB'!$C$11:$C$17,'RESUMO -ME'!C15,'DOOH - MUB'!$X$11:$X$17) -> 0 | H15: =SUMIF('DOOH - ESTABELECIMENTOS'!$C$11:$C$28,'RESUMO -ME'!C15,'DOOH - ESTABELECIMENTOS'!$W$11:$W$28) -> 0 | J15: =SUM(D15:H15) -> 62678.821 | K15: =J15*0.95 -> 59544.88 | L15: {=_FV(B15,"População")} -> 1503256 | M15: =L15/$L$28 -> 0.03776121 | N15: =K15/$K$28 -> 0.029304931
B16: #VALUE! | C16: DF | D16: =SUMIF('DOOH - METRÔ'!$C$8:$C$22,C16,'DOOH - METRÔ'!$W$8:$W$22) -> 81900 | E16: =SUMIF('DOOH - PAINEL'!$C:$C,'RESUMO -ME'!C16,'DOOH - PAINEL'!$X:$X) -> 264278.41 | F16: =SUMIF('DOOH - TERMINAL RODOVIÁRIO'!$C$11:$C$26,'RESUMO -ME'!C16,'DOOH - TERMINAL RODOVIÁRIO'!$X$11:$X$26) -> 0 | G16: =SUMIF('DOOH - MUB'!$C$11:$C$17,'RESUMO -ME'!C16,'DOOH - MUB'!$X$11:$X$17) -> 67961.143 | H16: =SUMIF('DOOH - ESTABELECIMENTOS'!$C$11:$C$28,'RESUMO -ME'!C16,'DOOH - ESTABELECIMENTOS'!$W$11:$W$28) -> 57600 | J16: =SUM(D16:H16) -> 471739.55 | K16: =J16*0.95 -> 448152.57 | L16: {=_FV(B16,"População")} -> 2996899 | M16: =L16/$L$28 -> 0.075280946 | N16: =K16/$K$28 -> 0.22055768
B17: REGIÃO NORTE | E17: =SUMIF('DOOH - PAINEL'!$C:$C,'RESUMO -ME'!C17,'DOOH - PAINEL'!$X:$X) -> 0
B18: #VALUE! | C18: PA | D18: =SUMIF('DOOH - METRÔ'!$C$8:$C$22,C18,'DOOH - METRÔ'!$W$8:$W$22) -> 0 | E18: =SUMIF('DOOH - PAINEL'!$C:$C,'RESUMO -ME'!C18,'DOOH - PAINEL'!$X:$X) -> 17617.6 | F18: =SUMIF('DOOH - TERMINAL RODOVIÁRIO'!$C$11:$C$26,'RESUMO -ME'!C18,'DOOH - TERMINAL RODOVIÁRIO'!$X$11:$X$26) -> 0 | G18: =SUMIF('DOOH - MUB'!$C$11:$C$17,'RESUMO -ME'!C18,'DOOH - MUB'!$X$11:$X$17) -> 0 | H18: =SUMIF('DOOH - ESTABELECIMENTOS'!$C$11:$C$28,'RESUMO -ME'!C18,'DOOH - ESTABELECIMENTOS'!$W$11:$W$28) -> 40548 | J18: =SUM(D18:H18) -> 58165.6 | K18: =J18*0.95 -> 55257.32 | L18: {=_FV(B18,"População")} -> 1397315 | M18: =L18/$L$28 -> 0.035100013 | N18: =K18/$K$28 -> 0.027194815
B19: #VALUE! | C19: AM | D19: =SUMIF('DOOH - METRÔ'!$C$8:$C$22,C19,'DOOH - METRÔ'!$W$8:$W$22) -> 0 | E19: =SUMIF('DOOH - PAINEL'!$C:$C,'RESUMO -ME'!C19,'DOOH - PAINEL'!$X:$X) -> 46990.505 | F19: =SUMIF('DOOH - TERMINAL RODOVIÁRIO'!$C$11:$C$26,'RESUMO -ME'!C19,'DOOH - TERMINAL RODOVIÁRIO'!$X$11:$X$26) -> 0 | G19: =SUMIF('DOOH - MUB'!$C$11:$C$17,'RESUMO -ME'!C19,'DOOH - MUB'!$X$11:$X$17) -> 0 | H19: =SUMIF('DOOH - ESTABELECIMENTOS'!$C$11:$C$28,'RESUMO -ME'!C19,'DOOH - ESTABELECIMENTOS'!$W$11:$W$28) -> 0 | J19: =SUM(D19:H19) -> 46990.505 | K19: =J19*0.95 -> 44640.98 | L19: {=_FV(B19,"População")} -> 2303732 | M19: =L19/$L$28 -> 0.057868858 | N19: =K19/$K$28 -> 0.021969997
B20: REGIÃO SUL | E20: =SUMIF('DOOH - PAINEL'!$C:$C,'RESUMO -ME'!C20,'DOOH - PAINEL'!$X:$X) -> 0
B21: #VALUE! | C21: PR | D21: =SUMIF('DOOH - METRÔ'!$C$8:$C$22,C21,'DOOH - METRÔ'!$W$8:$W$22) -> 0 | E21: =SUMIF('DOOH - PAINEL'!$C:$C,'RESUMO -ME'!C21,'DOOH - PAINEL'!$X:$X) -> 18636.429 | F21: =SUMIF('DOOH - TERMINAL RODOVIÁRIO'!$C$11:$C$26,'RESUMO -ME'!C21,'DOOH - TERMINAL RODOVIÁRIO'!$X$11:$X$26) -> 0 | G21: =SUMIF('DOOH - MUB'!$C$11:$C$17,'RESUMO -ME'!C21,'DOOH - MUB'!$X$11:$X$17) -> 0 | H21: =SUMIF('DOOH - ESTABELECIMENTOS'!$C$11:$C$28,'RESUMO -ME'!C21,'DOOH - ESTABELECIMENTOS'!$W$11:$W$28) -> 26880 | J21: =SUM(D21:H21) -> 45516.429 | K21: =J21*0.95 -> 43240.607 | L21: {=_FV(B21,"População")} -> 1830795 | M21: =L21/$L$28 -> 0.045988864 | N21: =K21/$K$28 -> 0.021280806
B22: REGIÃO NORDESTE | E22: =SUMIF('DOOH - PAINEL'!$C:$C,'RESUMO -ME'!C22,'DOOH - PAINEL'!$X:$X) -> 0 | H22: =SUMIF('DOOH - ESTABELECIMENTOS'!$C$11:$C$28,'RESUMO -ME'!C22,'DOOH - ESTABELECIMENTOS'!$W$11:$W$28) -> 0
B23: #VALUE! | C23: BA | D23: =SUMIF('DOOH - METRÔ'!$C$8:$C$22,C23,'DOOH - METRÔ'!$W$8:$W$22) -> 0 | E23: =SUMIF('DOOH - PAINEL'!$C:$C,'RESUMO -ME'!C23,'DOOH - PAINEL'!$X:$X) -> 16740 | F23: =SUMIF('DOOH - TERMINAL RODOVIÁRIO'!$C$11:$C$26,'RESUMO -ME'!C23,'DOOH - TERMINAL RODOVIÁRIO'!$X$11:$X$26) -> 119554.59 | G23: =SUMIF('DOOH - MUB'!$C$11:$C$17,'RESUMO -ME'!C23,'DOOH - MUB'!$X$11:$X$17) -> 0 | H23: =SUMIF('DOOH - ESTABELECIMENTOS'!$C$11:$C$28,'RESUMO -ME'!C23,'DOOH - ESTABELECIMENTOS'!$W$11:$W$28) -> 24960 | J23: =SUM(D23:H23) -> 161254.59 | K23: =J23*0.95 -> 153191.86 | L23: {=_FV(B23,"População")} -> 2564204 | M23: =L23/$L$28 -> 0.064411815 | N23: =K23/$K$28 -> 0.075393167
B24: #VALUE! | C24: CE | D24: =SUMIF('DOOH - METRÔ'!$C$8:$C$22,C24,'DOOH - METRÔ'!$W$8:$W$22) -> 0 | E24: =SUMIF('DOOH - PAINEL'!$C:$C,'RESUMO -ME'!C24,'DOOH - PAINEL'!$X:$X) -> 231530.38 | F24: =SUMIF('DOOH - TERMINAL RODOVIÁRIO'!$C$11:$C$26,'RESUMO -ME'!C24,'DOOH - TERMINAL RODOVIÁRIO'!$X$11:$X$26) -> 0 | G24: =SUMIF('DOOH - MUB'!$C$11:$C$17,'RESUMO -ME'!C24,'DOOH - MUB'!$X$11:$X$17) -> 0 | H24: =SUMIF('DOOH - ESTABELECIMENTOS'!$C$11:$C$28,'RESUMO -ME'!C24,'DOOH - ESTABELECIMENTOS'!$W$11:$W$28) -> 26880 | J24: =SUM(D24:H24) -> 258410.38 | K24: =J24*0.95 -> 245489.86 | L24: {=_FV(B24,"População")} -> 2578483 | M24: =L24/$L$28 -> 0.064770498 | N24: =K24/$K$28 -> 0.1208175
B25: #VALUE! | C25: MA | D25: =SUMIF('DOOH - METRÔ'!$C$8:$C$22,C25,'DOOH - METRÔ'!$W$8:$W$22) -> 0 | E25: =SUMIF('DOOH - PAINEL'!$C:$C,'RESUMO -ME'!C25,'DOOH - PAINEL'!$X:$X) -> 0 | F25: =SUMIF('DOOH - TERMINAL RODOVIÁRIO'!$C$11:$C$26,'RESUMO -ME'!C25,'DOOH - TERMINAL RODOVIÁRIO'!$X$11:$X$26) -> 0 | G25: =SUMIF('DOOH - MUB'!$C$11:$C$17,'RESUMO -ME'!C25,'DOOH - MUB'!$X$11:$X$17) -> 0 | H25: =SUMIF('DOOH - ESTABELECIMENTOS'!$C$11:$C$28,'RESUMO -ME'!C25,'DOOH - ESTABELECIMENTOS'!$W$11:$W$28) -> 29388 | J25: =SUM(D25:H25) -> 29388 | K25: =J25*0.95 -> 27918.6 | L25: {=_FV(B25,"População")} -> 1089215 | M25: =L25/$L$28 -> 0.02736066 | N25: =K25/$K$28 -> 0.013740101
B26: #VALUE! | C26: pi | D26: =SUMIF('DOOH - METRÔ'!$C$8:$C$22,C26,'DOOH - METRÔ'!$W$8:$W$22) -> 0 | E26: =SUMIF('DOOH - PAINEL'!$C:$C,'RESUMO -ME'!C26,'DOOH - PAINEL'!$X:$X) -> 1355.2 | F26: =SUMIF('DOOH - TERMINAL RODOVIÁRIO'!$C$11:$C$26,'RESUMO -ME'!C26,'DOOH - TERMINAL RODOVIÁRIO'!$X$11:$X$26) -> 0 | G26: =SUMIF('DOOH - MUB'!$C$11:$C$17,'RESUMO -ME'!C26,'DOOH - MUB'!$X$11:$X$17) -> 0 | H26: =SUMIF('DOOH - ESTABELECIMENTOS'!$C$11:$C$28,'RESUMO -ME'!C26,'DOOH - ESTABELECIMENTOS'!$W$11:$W$28) -> 0 | J26: =SUM(D26:H26) -> 1355.2 | K26: =J26*0.95 -> 1287.44 | L26: {=_FV(B26,"População")} -> 905692 | M26: =L26/$L$28 -> 0.022750633 | N26: =K26/$K$28 -> 0.00063361184
B27: #VALUE! | C27: PE | D27: =SUMIF('DOOH - METRÔ'!$C$8:$C$22,C27,'DOOH - METRÔ'!$W$8:$W$22) -> 0 | E27: =SUMIF('DOOH - PAINEL'!$C:$C,'RESUMO -ME'!C27,'DOOH - PAINEL'!$X:$X) -> 94329.686 | F27: =SUMIF('DOOH - TERMINAL RODOVIÁRIO'!$C$11:$C$26,'RESUMO -ME'!C27,'DOOH - TERMINAL RODOVIÁRIO'!$X$11:$X$26) -> 0 | G27: =SUMIF('DOOH - MUB'!$C$11:$C$17,'RESUMO -ME'!C27,'DOOH - MUB'!$X$11:$X$17) -> 0 | H27: =SUMIF('DOOH - ESTABELECIMENTOS'!$C$11:$C$28,'RESUMO -ME'!C27,'DOOH - ESTABELECIMENTOS'!$W$11:$W$28) -> 30720 | J27: =SUM(D27:H27) -> 125049.69 | K27: =J27*0.95 -> 118797.2 | L27: {=_FV(B27,"População")} -> 1588376 | M27: =L27/$L$28 -> 0.039899392 | N27: =K27/$K$28 -> 0.058465881
B28: TOTAL | D28: =SUM(D10:D27) -> 347162.25 | E28: =SUM(E10:E27) -> 943969.83 | F28: =SUM(F10:F27) -> 135624.99 | G28: =SUM(G10:G27) -> 350711.86 | H28: =SUM(H10:H27) -> 361380 | J28: =SUM(J11:J27) -> 2138848.9 | K28: =SUM(K11:K27) -> 2031906.5 | L28: =SUM(L11:L27) -> 39809529 | M28: =SUM(M11:M27) -> 1 | N28: =SUM(N11:N27) -> 1

Sheet DOOH - METRÔ
B2: PROGRAMAÇÃO - DOOH METRÔ
B4: =CAPA!D4 -> MINISTÉRIO DA EDUCAÇÃO
B5: =CAPA!D6 -> FIES 2026
B6: =CAPA!D8 -> JULHO DE 2026
B8: IDENTIFICADOR SISTEMA | C8: UF | D8: PRAÇA | E8: CÓD MUNICÍPIO | F8: VEÍCULO | G8: CNPJ | H8: LOCAL | I8: FORMATO | M8: PERÍODO DE VEICULAÇÃO | P8: QUANT. DE FACES | Q8: QTD. INS DIA | R8: TT. INS.PERÍODO | S8: VALOR TABELA | U8: DESC. % | V8: VALOR NEGOCIADO | X8: VALOR DESEMBOLSO 95% | Y8: COBERTURA PERÍODO(FLUXO) | Z8: IMPACTO PERÍODO | AA8: FONTE | AB8: CPM | AC8: CPI | AD8: REPRESENTANTE
I9: TIPO | J9: TIPO DE COMPRA | K9: AMBIENTE | L9: MATERIAL | M9: INICIAL | N9: FINAL | O9: TOTAL DE DIAS | S9: UNITÁRIO | T9: TOTAL | V9: UNITÁRIO | W9: TOTAL 100%
B11: 97390 | C11: DF | D11: BRASÍLIA | E11: 5300108 | F11: URBAN + | G11: 44.472.500/0001-00 | H11: Embarque, sentido Plano Piloto | I11: METRÔ | J11: CIRCUITO | K11: METRO/TREM | L11: 15" | M11: 46219 | N11: =M11+O11-1 -> 46220 | O11: 2 | P11: 1 | Q11: 4160 | R11: =Q11*O11*P11 -> 8320 | S11: 3.2 | T11: =S11*R11 -> 26624 | U11: 0.3 | V11: =S11-S11*U11 -> 2.24 | W11: =T11*(1-U11) -> 18636.8 | X11: =W11*0.95 -> 17704.96 | Y11: 7283 | Z11: =R11 -> 8320 | AA11: PRÓPRIA | AB11: =W11/(Z11)*1000 -> 2240 | AC11: =W11/(Z11) -> 2.24 | AD11: DIRETO
B12: 97390 | C12: DF | D12: BRASÍLIA | E12: 5300108 | F12: URBAN + | G12: 44.472.500/0001-00 | H12: Embarque, sentido Plano Piloto/Taguatinga/Ceilândia/Samambaia | I12: METRÔ | J12: CIRCUITO | K12: METRO/TREM | L12: 15" | M12: 46219 | N12: =M12+O12-1 -> 46220 | O12: 2 | P12: 1 | Q12: 4160 | R12: =Q12*O12*P12 -> 8320 | S12: 3.2 | T12: =S12*R12 -> 26624 | U12: 0.3 | V12: =S12-S12*U12 -> 2.24 | W12: =T12*(1-U12) -> 18636.8 | X12: =W12*0.95 -> 17704.96 | Y12: 9454 | Z12: =R12 -> 8320 | AA12: PRÓPRIA | AB12: =W12/(Z12)*1000 -> 2240 | AC12: =W12/(Z12) -> 2.24 | AD12: DIRETO
B13: 12237 | C13: DF | D13: BRASÍLIA | E13: 5300108 | F13: MOBTV | G13: 05.806.588/0001-99 | H13: ESTAÇÃO PRAÇA DO RELÓGIO | I13: METRÔ | J13: CIRCUITO | K13: METRO/TREM | L13: 15" | M13: 46219 | N13: =M13+O13-1 -> 46220 | O13: 2 | P13: 1 | Q13: 1000 | R13: =Q13*O13*P13 -> 2000 | S13: 3.2 | T13: =S13*R13 -> 6400 | U13: 0.3 | V13: =S13-S13*U13 -> 2.24 | W13: =T13*(1-U13) -> 4480 | X13: =W13*0.95 -> 4256 | Y13: 7283 | Z13: =R13 -> 2000 | AA13: PRÓPRIA | AB13: =W13/(Z13)*1000 -> 2240 | AC13: =W13/(Z13) -> 2.24 | AD13: DS MIDIA
B14: 12237 | C14: DF | D14: BRASÍLIA | E14: 5300108 | F14: MOBTV | G14: 05.806.588/0001-99 | H14: ESTAÇÃO BRT GAMA | I14: METRÔ | J14: CIRCUITO | K14: METRO/TREM | L14: 15" | M14: 46219 | N14: =M14+O14-1 -> 46220 | O14: 2 | P14: 2 | Q14: 1000 | R14: =Q14*O14*P14 -> 4000 | S14: 3.2 | T14: =S14*R14 -> 12800 | U14: 0.3 | V14: =S14-S14*U14 -> 2.24 | W14: =T14*(1-U14) -> 8960 | X14: =W14*0.95 -> 8512 | Y14: 9454 | Z14: =R14 -> 4000 | AA14: PRÓPRIA | AB14: =W14/(Z14)*1000 -> 2240 | AC14: =W14/(Z14) -> 2.24 | AD14: DS MIDIA
B15: 12237 | C15: DF | D15: BRASÍLIA | E15: 5300108 | F15: MOBTV | G15: 05.806.588/0001-99 | H15: ESTAÇÃO BRT SANTA MARIA | I15: METRÔ | J15: CIRCUITO | K15: METRO/TREM | L15: 15" | M15: 46219 | N15: =M15+O15-1 -> 46220 | O15: 2 | P15: 2 | Q15: 1000 | R15: =Q15*O15*P15 -> 4000 | S15: 3.2 | T15: =S15*R15 -> 12800 | U15: 0.3 | V15: =S15-S15*U15 -> 2.24 | W15: =T15*(1-U15) -> 8960 | X15: =W15*0.95 -> 8512 | Y15: 9454 | Z15: =R15 -> 4000 | AA15: PRÓPRIA | AB15: =W15/(Z15)*1000 -> 2240 | AC15: =W15/(Z15) -> 2.24 | AD15: DS MIDIA
B16: 12237 | C16: DF | D16: BRASÍLIA | E16: 5300108 | F16: MOBTV | G16: 05.806.588/0001-99 | H16: LED ESTAÇÃO CENTRAL DESEMBARQUE | I16: METRÔ | J16: CIRCUITO | K16: METRO/TREM | L16: 15" | M16: 46219 | N16: =M16+O16-1 -> 46220 | O16: 2 | P16: 2 | Q16: 820 | R16: =Q16*O16*P16 -> 3280 | S16: 4.9 | T16: =S16*R16 -> 16072 | U16: 0.3 | V16: =S16-S16*U16 -> 3.43 | W16: =T16*(1-U16) -> 11250.4 | X16: =W16*0.95 -> 10687.88 | Y16: 9454 | Z16: =R16 -> 3280 | AA16: PRÓPRIA | AB16: =W16/(Z16)*1000 -> 3430 | AC16: =W16/(Z16) -> 3.43 | AD16: DS MIDIA
B17: 12237 | C17: DF | D17: BRASÍLIA | E17: 5300108 | F17: MOBTV | G17: 05.806.588/0001-99 | H17: LED ESTAÇÃO CENTRAL EMBARQUE | I17: METRÔ | J17: CIRCUITO | K17: METRO/TREM | L17: 15" | M17: 46219 | N17: =M17+O17-1 -> 46220 | O17: 2 | P17: 2 | Q17: 800 | R17: =Q17*O17*P17 -> 3200 | S17: 4.9 | T17: =S17*R17 -> 15680 | U17: 0.3 | V17: =S17-S17*U17 -> 3.43 | W17: =T17*(1-U17) -> 10976 | X17: =W17*0.95 -> 10427.2 | Y17: 9454 | Z17: =R17 -> 3200 | AA17: PRÓPRIA | AB17: =W17/(Z17)*1000 -> 3430 | AC17: =W17/(Z17) -> 3.43 | AD17: DS MIDIA
B18: TOTAL - BRASÍLIA | Q18: =SUBTOTAL(9,Q11:Q17) -> 12940 | R18: =SUBTOTAL(9,R11:R17) -> 33120 | T18: =SUBTOTAL(9,T11:T17) -> 117000 | W18: =SUBTOTAL(9,W11:W17) -> 81900 | X18: =SUBTOTAL(9,X11:X17) -> 77805 | Z18: =SUBTOTAL(9,Z11:Z17) -> 33120 | AB18: =SUBTOTAL(9,AB11:AB17) -> 18060
B19: 27461 | C19: SP | D19: SÃO PAULO | E19: 3550308 | F19: MEDIA MEGAS | G19: 10.929.279/0001-46 | H19: Circuito 11 Estações | I19: METRÔ | J19: CIRCUITO | K19: METRO/TREM | L19: 15" | M19: 46219 | N19: =M19+O19-1 -> 46220 | O19: 2 | P19: 200 | Q19: 812 | R19: =Q19*O19*P19 -> 324800 | S19: 275000 | T19: =S19 -> 275000 | U19: 0.24 | V19: =S19-S19*U19 -> 209000 | W19: =T19*(1-U19) -> 209000 | X19: =W19*0.95 -> 198550 | Y19: 7283 | Z19: =R19 -> 324800 | AA19: PRÓPRIA | AB19: =V19/(Z19)*1000 -> 643.47291 | AC19: =V19/(Z19) -> 0.64347291 | AD19: DIRETO
B20: 86035 | C20: SP | D20: SÃO PAULO | E20: 3550308 | F20: ELETROMÍDIA - TV MINUTO | G20: 27.865.757/0091-50 | H20: Metrô SP - Circuito Interno De Trem Completo | I20: METRÔ | J20: CIRCUITO | K20: METRO/TREM | L20: 10" | M20: 46219 | N20: =M20+O20-1 -> 46220 | O20: 2 | P20: 3792 | Q20: 192 | R20: =Q20*O20*P20 -> 1456128 | S20: 93770.41 | T20: =S20 -> 93770.41 | U20: 0.4 | V20: =S20-S20*U20 -> 56262.246 | W20: =T20*(1-U20) -> 56262.246 | X20: =W20*0.95 -> 53449.134 | Y20: 2450000 | Z20: =R20 -> 1456128 | AA20: PRÓPRIA | AB20: =V20/(Z20)*1000 -> 38.638256 | AC20: =V20/(Z20) -> 0.038638256 | AD20: DIRETO
B21: TOTAL - SÃO PAULO | Q21: =SUBTOTAL(9,Q19:Q20) -> 1004 | R21: =SUBTOTAL(9,R19:R20) -> 1780928 | T21: =SUBTOTAL(9,T19:T20) -> 368770.41 | W21: =SUBTOTAL(9,W19:W20) -> 265262.25 | X21: =SUBTOTAL(9,X19:X20) -> 251999.13 | Z21: =SUBTOTAL(9,Z19:Z20) -> 1780928 | AB21: =SUBTOTAL(9,AB19:AB20) -> 682.11116
B22: 86035 | C22: RJ | D22: RIO DE JANEIRO | E22: 3304557 | F22: ELETROMIDIA | G22: 27.865.757/0091-50 | H22: Metrô Rio - Circuito Completo | I22: METRÔ | J22: CIRCUITO | K22: METRO/TREM | L22: 10" | M22: 46219 | N22: =M22+O22-1 -> 46220 | O22: 2 | P22: 273 | U22: 0.4 | X22: =W22*0.95 -> 0 | Y22: 12314061 | Z22: =R22 -> 0 | AA22: PRÓPRIA | AB22: =V22/(Z22)*1000 -> #DIV/0! | AC22: =V22/(Z22) -> #DIV/0! | AD22: DIRETO
B23: TOTAL - RIO DE JANEIRO | Q23: =SUBTOTAL(9,Q22:Q22) -> 0 | R23: =SUBTOTAL(9,R22:R22) -> 0 | T23: =SUBTOTAL(9,T22:T22) -> 0 | W23: =SUBTOTAL(9,W22:W22) -> 0 | X23: =SUBTOTAL(9,X22:X22) -> 0 | Z23: =SUBTOTAL(9,Z22:Z22) -> 0 | AB23: =SUBTOTAL(9,AB22:AB22) -> #DIV/0!
B24: TOTAL GERAL | Q24: =SUBTOTAL(9,Q11:Q23) -> 13944 | R24: =SUBTOTAL(9,R11:R23) -> 1814048 | T24: =SUBTOTAL(9,T11:T23) -> 485770.41 | W24: =SUBTOTAL(9,W11:W23) -> 347162.25 | X24: =SUBTOTAL(9,X11:X23) -> 329804.13 | Z24: =SUBTOTAL(9,Z18:Z23) -> 1780928 | AB24: =SUBTOTAL(9,AB18:AB23) -> #DIV/0!
B25: OBSERVAÇÃO:
B27: VEÍCULO | D27: QTD DE INSERÇÕES | E27: DADOS DE IMPACTO | F27: VALOR TABELA | G27: VALOR NEGOCIADO 100% | H27: VALOR DESEMBOLSO 95% | I27: RENTABILIDADE %
B28: URBAN + | D28: =SUMIF(F:F,B28,R:R) -> 16640 | E28: =SUMIF(F:F,B28,Z:Z) -> 16640 | F28: =SUMIF($F$11:$F$22,B28,$T$11:$T$23) -> 53248 | G28: =SUMIF($F$11:$F$22,B28,$W$11:$W$23) -> 37273.6 | H28: =G28*0.95 -> 35409.92 | I28: =1-H28/F28 -> 0.335
B29: MOBTV | D29: =SUMIF(F:F,B29,R:R) -> 16480 | E29: =SUMIF(F:F,B29,Z:Z) -> 16480 | F29: =SUMIF($F$11:$F$22,B29,$T$11:$T$23) -> 63752 | G29: =SUMIF($F$11:$F$22,B29,$W$11:$W$23) -> 44626.4 | H29: =G29*0.95 -> 42395.08 | I29: =1-H29/F29 -> 0.335
B30: MEDIA MEGAS | D30: =SUMIF(F:F,B30,R:R) -> 324800 | E30: =SUMIF(F:F,B30,Z:Z) -> 324800 | F30: =SUMIF($F$11:$F$22,B30,$T$11:$T$23) -> 275000 | G30: =SUMIF($F$11:$F$22,B30,$W$11:$W$23) -> 209000 | H30: =G30*0.95 -> 198550 | I30: =1-H30/F30 -> 0.278
B31: ELETROMÍDIA - TV MINUTO | D31: =SUMIF(F:F,B31,R:R) -> 1456128 | E31: =SUMIF(F:F,B31,Z:Z) -> 1456128 | F31: =SUMIF($F$11:$F$22,B31,$T$11:$T$23) -> 93770.41 | G31: =SUMIF($F$11:$F$22,B31,$W$11:$W$23) -> 56262.246 | H31: =G31*0.95 -> 53449.134 | I31: =1-H31/F31 -> 0.43
B32: ELETROMIDIA | D32: =SUMIF(F:F,B32,R:R) -> 0 | E32: =SUMIF(F:F,B32,Z:Z) -> 0 | F32: =SUMIF($F$11:$F$22,B32,$T$11:$T$23) -> 0 | G32: =SUMIF($F$11:$F$22,B32,$W$11:$W$23) -> 0 | H32: =G32*0.95 -> 0 | I32: =1-H32/F32 -> #DIV/0!
D33: =SUM(D28:D32) -> 1814048 | E33: =SUM(E28:E32) -> 1814048 | F33: =SUM(F28:F32) -> 485770.41 | G33: =SUM(G28:G32) -> 347162.25 | H33: =SUM(H28:H32) -> 329804.13
B36: AGENCIA | C36: VALOR 100% | D36: VALOR 95%
B37: CALIA | C37: =SUMIF($A$18:$A$23,B37,$W$18:$W$24) -> 0 | D37: =C37*0.95 -> 0
B38: SA | C38: =SUMIF($A$18:$A$23,B38,$W$18:$W$24) -> 0 | D38: =C38*0.95 -> 0
B39: DE BRITO | C39: =SUMIF($A$18:$A$23,B39,$W$18:$W$24) -> 0 | D39: =C39*0.95 -> 0

Sheet DOOH - MUB
B2: PROGRAMAÇÃO - DOOH MOBILIÁRIO URBANO
AH3: ,
B4: =RESUMO!C5 -> MINISTÉRIO DA EDUCAÇÃO
B5: =RESUMO!C6 -> FIES 2026
B6: =RESUMO!C7 -> JULHO DE 2026
B8: IDENTIFICADOR SISTEMA | C8: UF | D8: PRAÇA | E8: CÓD MUNICÍPIO | F8: VEÍCULO | G8: CNPJ | H8: LOCAL | I8: FORMATO | M8: PERÍODO DE VEICULAÇÃO | P8: QUANT. DE FACES | Q8: QTD. INS DIA | R8: TT. INS.PERÍODO | S8: QTD DE COTAS CONTRATADAS | T8: VALOR TABELA | V8: DESC. % | W8: VALOR NEGOCIADO | Y8: VALOR DESEMBOLSO 95% | Z8: COBERTURA PERÍODO(FLUXO) | AA8: IMPACTO PERÍODO | AB8: FONTE | AC8: CPM | AD8: CPI | AE8: REPRESENTANTE
I9: TIPO | J9: TIPO DE COMPRA | K9: AMBIENTE | L9: MATERIAL | M9: INICIAL | N9: FINAL | O9: TOTAL DE DIAS | T9: UNITÁRIO | U9: TOTAL | W9: UNITÁRIO | X9: TOTAL 100%
B11: 12323 | C11: DF | D11: BRASÍLIA | E11: 5300108 | F11: VISUPLAC | G11: 02.306.218/0001-02 | H11: CIRCUITO EMPIRE STATE | I11: MUB DIGITAL | J11: CIRCUITO | K11: VIAS DE ALTO FLUXO | L11: 10" | M11: 46219 | N11: =M11+O11-1 -> 46220 | O11: 2 | P11: 132 | Q11: 360 | R11: =Q11*P11*O11 -> 95040 | S11: 1 | T11: =279840/7*O11 -> 79954.286 | U11: =T11 -> 79954.286 | V11: 0.15 | W11: =T11-T11*V11 -> 67961.143 | X11: =U11*(1-V11) -> 67961.143 | Y11: =X11*0.95 -> 64563.086 | Z11: - | AA11: =R11 -> 95040 | AB11: PRÓPRIA | AC11: =X11/(AA11+AA12)*1000 -> 715.07937 | AD11: =X11/(AA11+AA12) -> 0.71507937 | AE11: MOSAICO
B12: TOTAL - DISTRITO FEDERAL | R12: =SUBTOTAL(9,R11:R11) -> 95040 | X12: =SUBTOTAL(9,X11:X11) -> 67961.143 | Y12: =X12*0.95 -> 64563.086
B13: 100158 | C13: RJ | D13: RIO DE JANEIRO | E13: 3304557 | F13: PLUREX | G13: 30.307.086/0001-60 | H13: diversos (verificar endereços abaixo) | I13: BANCA DIGITAL | J13: PERÍODO | K13: VIAS DE ALTO FLUXO | L13: 10" | M13: 46219 | N13: =M13+O13-1 -> 46220 | O13: 2 | P13: 10 | Q13: 855 | R13: =O13*P13*Q13 -> 17100 | S13: 1 | T13: 3.2 | U13: =T13*R13 -> 54720 | V13: 0.55 | W13: =T13-(T13*V13) -> 1.44 | X13: =U13-(U13*V13) -> 24624 | Y13: =X13*0.95 -> 23392.8 | Z13: 336119 | AA13: =R13 -> 17100 | AB13: NÃO INFORMADO | AC13: =X13/(AA13+AA14)*1000 -> 1440 | AD13: =X13/(AA13+AA14) -> 1.44 | AE13: BI GROUP
B14: TOTAL - RIO DE JANEIRO | R14: =SUBTOTAL(9,R13:R13) -> 17100 | X14: =SUBTOTAL(9,X13:X13) -> 24624 | Y14: =X14*0.95 -> 23392.8
B15: 70547 | C15: MG | D15: BELO HORIZONTE | E15: 3106200 | F15: DESTAKE | G15: 07.923.942/0001-90 | H15: diversos (verificar endereços abaixo) | I15: MUB DIGITAL | J15: POR FACE | K15: VIAS DE ALTO FLUXO | L15: 10" | M15: 46219 | N15: =M15+O15-1 -> 46220 | O15: 2 | P15: 25 | Q15: 4800 | R15: =Q15*P15*O15 -> 240000 | S15: 4 | T15: 7752 | U15: =T15*P15 -> 193800 | V15: 0.33 | W15: =T15-T15*V15 -> 5193.84 | X15: =U15*(1-V15) -> 129846 | Y15: =X15*0.95 -> 123353.7 | Z15: 115140.29 | AA15: =Z15*O15 -> 230280.57 | AB15: PRÓPRIA | AC15: =X15/(AA15+AA16)*1000 -> 563.85999 | AD15: =X15/(AA15+AA16) -> 0.56385999 | AE15: MIDIA MAIS
B16: TOTAL - MINAS GERAIS | R16: =SUBTOTAL(9,R15:R15) -> 240000 | X16: =SUBTOTAL(9,X15:X15) -> 129846 | Y16: =X16*0.95 -> 123353.7
B17: 41033 | C17: SP | D17: SÃO PAULO | E17: 3550308 | F17: ELETROMIDIA | G17: 17.104.815/0001-13 | H17: Abrigos São Paulo | I17: MUB DIGITAL | J17: POR FACE | K17: VIAS DE ALTO FLUXO | L17: 10" | M17: 46219 | N17: 46217 | O17: 2 | P17: 100 | Q17: 732 | R17: =Q17*P17*O17 -> 146400 | S17: 1 | T17: 213801.19 | U17: =T17 -> 213801.19 | V17: 0.4 | W17: =T17-T17*V17 -> 128280.71 | X17: =U17*(1-V17) -> 128280.71 | Y17: =X17*0.95 -> 121866.68 | Z17: 602818.97 | AA17: =Z17*P17 -> 60281897 | AB17: PRÓPRIA | AC17: =X17/(AA17+AA18)*1000 -> 2.1280139 | AD17: =X17/(AA17+AA18) -> 0.0021280139 | AE17: STREET MÍDIA
B18: TOTAL - SÃO PAULO | R18: =R17 -> 146400 | X18: =SUBTOTAL(9,X17) -> 128280.71 | Y18: =X18*0.95 -> 121866.68
B20: TOTAL GERAL | R20: =SUBTOTAL(9,R11:R18) -> 644940 | U20: =SUM(U11:U18) -> 542275.48 | X20: =SUBTOTAL(9,X11:X18) -> 350711.86 | Y20: =X20*0.95 -> 333176.26 | AA20: =SUM(AA11:AA17) -> 60624317
B21: OBSERVAÇÃO:
B23: VEÍCULO | D23: QTD DE INSERÇÕES | E23: DADOS DE IMPACTO | F23: VALOR TABELA | G23: VALOR NEGOCIADO 100% | H23: VALOR DESEMBOLSO 95% | I23: RENTABILIDADE %
B24: VISUPLAC | D24: =SUMIF($F$11:$F$17,B24,$R$11:$R$17) -> 95040 | E24: =SUMIF($F$11:$F$17,B24,$AA$11:$AA$17) -> 95040 | F24: =SUMIF($F$11:$F$17,B24,$U$11:$U$17) -> 79954.286 | G24: =SUMIF($F$11:$F$17,B24,$X$11:$X$17) -> 67961.143 | H24: =G24*0.95 -> 64563.086 | I24: =1-H24/F24 -> 0.1925
B25: PLUREX | D25: =SUMIF($F$11:$F$17,B25,$R$11:$R$17) -> 17100 | E25: =SUMIF($F$11:$F$17,B25,$AA$11:$AA$17) -> 17100 | F25: =SUMIF($F$11:$F$17,B25,$U$11:$U$17) -> 54720 | G25: =SUMIF($F$11:$F$17,B25,$X$11:$X$17) -> 24624 | H25: =G25*0.95 -> 23392.8 | I25: =1-H25/F25 -> 0.5725
B26: DESTAKE | D26: =SUMIF($F$11:$F$17,B26,$R$11:$R$17) -> 240000 | E26: =SUMIF($F$11:$F$17,B26,$AA$11:$AA$17) -> 230280.57 | F26: =SUMIF($F$11:$F$17,B26,$U$11:$U$17) -> 193800 | G26: =SUMIF($F$11:$F$17,B26,$X$11:$X$17) -> 129846 | H26: =G26*0.95 -> 123353.7 | I26: =1-H26/F26 -> 0.3635
B27: ELETROMIDIA | D27: =SUMIF($F$11:$F$17,B27,$R$11:$R$17) -> 146400 | E27: =SUMIF($F$11:$F$17,B27,$AA$11:$AA$17) -> 60281897 | F27: =SUMIF($F$11:$F$17,B27,$U$11:$U$17) -> 213801.19 | G27: =SUMIF($F$11:$F$17,B27,$X$11:$X$17) -> 128280.71 | H27: =G27*0.95 -> 121866.68 | I27: =1-H27/F27 -> 0.43
D28: =SUM(D24:D27) -> 498540 | E28: =SUM(E24:E27) -> 60624317 | F28: =SUM(F24:F27) -> 542275.48 | G28: =SUM(G24:G27) -> 350711.86 | H28: =SUM(H24:H27) -> 333176.26
B31: AGENCIA | C31: VALOR 100% | D31: VALOR 95%
B32: CALIA | C32: =SUMIF($A$11:$A$17,B32,$X$11:$X$19) -> 0 | D32: =C32*0.95 -> 0
B33: SA | C33: =SUMIF($A$11:$A$17,B33,$X$11:$X$19) -> 0 | D33: =C33*0.95 -> 0
B34: DE BRITO | C34: =SUMIF($A$11:$A$17,B34,$X$11:$X$19) -> 0 | D34: =C34*0.95 -> 0
B37: LSITA DE BANCAS
B38: AV AFONSO PENA, 1005 - CENTRO
B39: AV. AFONSO PENA, 1709 - FUNCIONÁRIOS
B40: ALVARES CABRAL, 17 - CENTRO
B41: AV. AMAZONAS, 1837 - SANTO AGOSTINHO
B42: AV CRISTIANO MACHADO, 11936 - JULIANA
B43: AV CRISTIANO MACHADO.2320 - CIDADE NOVA
B44: AV CRISTÁVÃO COLOMBO, 277 - SAVASSI
B45: AV DO CONTORNO, 1343 - FLORESTA
B46: AV DO CONTORNO, 3946 - SANTA EFIGÊNIA
B47: AV DO CONTORNO, 6846 - LOURDES
B48: AV DOS BANDEIRANTES, 60, SION
... B69: RUA RIO GRANDE DO SUL, 758 - BARRO PRETO

Sheet DOOH - ESTABELECIMENTOS
B2: PROGRAMAÇÃO - DOOH ESTABELECIMENTOS
B4: =RESUMO!C5 -> MINISTÉRIO DA EDUCAÇÃO
B5: =RESUMO!C6 -> FIES 2026
B6: =RESUMO!C7 -> JULHO DE 2026
B8: IDENTIFICADOR SISTEMA | C8: UF | D8: PRAÇA | E8: CÓD MUNICÍPIO | F8: VEÍCULO | G8: CNPJ | H8: LOCAL | I8: FORMATO | M8: PERÍODO DE VEICULAÇÃO | P8: MATERIAL | Q8: QTD. INS DIA | R8: TT. INS. | S8: VALOR TABELA | U8: DESC. % | V8: VALOR NEGOCIADO | X8: VALOR DESEMBOLSO 95% | Y8: COBERTURA PERÍODO (FLUXO) | Z8: IMPACTO PERÍODO | AA8: CPI | AB8: CPM | AC8: RENTABILIDADE | AD8: REPRESENTANTE
I9: TIPO | J9: TIPO DE COMPRA | K9: AMBIENTE | L9: QUANT. | M9: INICIAL | N9: FINAL | O9: TOTAL DE DIAS | S9: UNITÁRIO | T9: TOTAL | V9: UNITÁRIO | W9: TOTAL 100%
B11: 57519 | C11: PE | D11: RECIFE | F11: INSIGHT MIDIA | G11: 18.619.705/0001-57 | H11: LOTÉRICAS | I11: MIDIA EM LOTERICA | J11: INSERÇÕES | K11: LOTÉRICAS | L11: 70 | M11: 46219 | N11: =M11+O11-1 -> 46220 | O11: 2 | P11: 15" | Q11: 300 | R11: =Q11*O11 -> 600 | S11: 80 | T11: =S11*R11 -> 48000 | U11: 0.36 | V11: =S11-S11*U11 -> 51.2 | W11: =T11*(1-U11) -> 30720 | X11: =W11*0.95 -> 29184 | Y11: 80888.889 | Z11: =Y11*O11 -> 161777.78 | AA11: =W11/(Z11+#REF!) -> #REF! | AB11: =W11/(Z11+#REF!)*1000 -> #REF! | AC11: =1-(W11/((T11+#REF!))) -> #REF! | AD11: INSIGHT
B12: TOTAL - PERNAMBUCO | L12: =SUBTOTAL(9,L11:L11) -> 70 | R12: =SUBTOTAL(9,R11:R11) -> 600 | W12: =SUBTOTAL(9,W11:W11) -> 30720 | X12: =W12*0.95 -> 29184 | AB12: =SUBTOTAL(9,AB11:AB11) -> #REF!
B13: 57519 | C13: CE | D13: FORTALEZA | F13: INSIGHT MIDIA | G13: 18.619.705/0001-57 | H13: LOTÉRICAS | I13: MIDIA EM LOTERICA | J13: INSERÇÕES | K13: LOTÉRICAS | L13: 70 | M13: 46219 | N13: =M13+O13-1 -> 46220 | O13: 2 | P13: 15" | Q13: 300 | R13: =Q13*O13 -> 600 | S13: 70 | T13: =S13*R13 -> 42000 | U13: 0.36 | V13: =S13-S13*U13 -> 44.8 | W13: =T13*(1-U13) -> 26880 | X13: =W13*0.95 -> 25536 | Y13: 80888.889 | Z13: =Y13*O13 -> 161777.78 | AA13: =W13/(Z13+#REF!) -> #REF! | AB13: =W13/(Z13+#REF!)*1000 -> #REF! | AC13: =1-(W13/((T13+#REF!))) -> #REF! | AD13: INSIGHT
B14: TOTAL - CEARA | L14: =SUBTOTAL(9,L13:L13) -> 70 | R14: =SUBTOTAL(9,R13:R13) -> 600 | W14: =SUBTOTAL(9,W13:W13) -> 26880 | X14: =W14*0.95 -> 25536 | AB14: =SUBTOTAL(9,AB13:AB13) -> #REF!
B15: 57519 | C15: DF | D15: BRASÍLIA | F15: INSIGHT MIDIA | G15: 18.619.705/0001-57 | H15: LOTÉRICAS | I15: MIDIA EM LOTERICA | J15: INSERÇÕES | K15: LOTÉRICAS | L15: 70 | M15: 46219 | N15: =M15+O15-1 -> 46220 | O15: 2 | P15: 15" | Q15: 300 | R15: =Q15*O15 -> 600 | S15: 150 | T15: =S15*R15 -> 90000 | U15: 0.36 | V15: =S15-S15*U15 -> 96 | W15: =T15*(1-U15) -> 57600 | X15: =W15*0.95 -> 54720 | Y15: 80888.889 | Z15: =Y15*O15 -> 161777.78 | AA15: =W15/(Z15+#REF!) -> #REF! | AB15: =W15/(Z15+#REF!)*1000 -> #REF! | AC15: =1-(W15/((T15+#REF!))) -> #REF! | AD15: INSIGHT
B16: TOTAL - DISTRITO FEDERAL | L16: =SUBTOTAL(9,L15:L15) -> 70 | R16: =SUBTOTAL(9,R15:R15) -> 600 | W16: =SUBTOTAL(9,W15:W15) -> 57600 | X16: =W16*0.95 -> 54720 | AB16: =SUBTOTAL(9,AB15:AB15) -> #REF!
B17: 57519 | C17: SP | D17: SÃO PAULO | E17: 3550308 | F17: INSIGHT MIDIA | G17: 18.619.705/0001-57 | H17: LOTÉRICAS | I17: MIDIA EM LOTERICA | J17: INSERÇÕES | K17: LOTÉRICAS | L17: 70 | M17: 46219 | N17: =M17+O17-1 -> 46220 | O17: 2 | P17: 15" | Q17: 300 | R17: =Q17*O17 -> 600 | S17: 199 | T17: =S17*R17 -> 119400 | U17: 0.36 | V17: =S17-S17*U17 -> 127.36 | W17: =T17*(1-U17) -> 76416 | X17: =W17*0.95 -> 72595.2 | Y17: 80888.889 | Z17: =Y17*O17 -> 161777.78 | AA17: =W17/(Z17+#REF!) -> #REF! | AB17: =W17/(Z17+#REF!)*1000 -> #REF! | AC17: =1-(W17/((T17+#REF!))) -> #REF! | AD17: INSIGHT
B18: TOTAL - SÃO PAULO | L18: =SUBTOTAL(9,L17:L17) -> 70 | R18: =SUBTOTAL(9,R17:R17) -> 600 | W18: =SUBTOTAL(9,W17:W17) -> 76416 | X18: =W18*0.95 -> 72595.2 | AB18: =SUBTOTAL(9,AB17:AB17) -> #REF!
B19: 57519 | C19: BA | D19: SALVADOR | F19: INSIGHT MIDIA | G19: 18.619.705/0001-57 | H19: LOTÉRICAS | I19: MIDIA EM LOTERICA | J19: INSERÇÕES | K19: LOTÉRICAS | L19: 70 | M19: 46219 | N19: =M19+O19-1 -> 46220 | O19: 2 | P19: 15" | Q19: 300 | R19: =Q19*O19 -> 600 | S19: 65 | T19: =S19*R19 -> 39000 | U19: 0.36 | V19: =S19-S19*U19 -> 41.6 | W19: =T19*(1-U19) -> 24960 | X19: =W19*0.95 -> 23712 | Y19: 80888.889 | Z19: =Y19*O19 -> 161777.78 | AA19: =W19/(Z19+#REF!) -> #REF! | AB19: =W19/(Z19+#REF!)*1000 -> #REF! | AC19: =1-(W19/((T19+#REF!))) -> #REF! | AD19: INSIGHT
B20: TOTAL - BAHIA | L20: =SUBTOTAL(9,L19:L19) -> 70 | R20: =SUBTOTAL(9,R19:R19) -> 600 | W20: =SUBTOTAL(9,W19:W19) -> 24960 | X20: =W20*0.95 -> 23712 | AB20: =SUBTOTAL(9,AB19:AB19) -> #REF!
B21: 57519 | C21: PR | D21: CURITIBA | F21: INSIGHT MIDIA | G21: 18.619.705/0001-57 | H21: LOTÉRICAS | I21: MIDIA EM LOTERICA | J21: INSERÇÕES | K21: LOTÉRICAS | L21: 70 | M21: 46219 | N21: =M21+O21-1 -> 46220 | O21: 2 | P21: 15" | Q21: 300 | R21: =Q21*O21 -> 600 | S21: 70 | T21: =S21*R21 -> 42000 | U21: 0.36 | V21: =S21-S21*U21 -> 44.8 | W21: =T21*(1-U21) -> 26880 | X21: =W21*0.95 -> 25536 | Y21: 80888.889 | Z21: =Y21*O21 -> 161777.78 | AA21: =W21/(Z21+#REF!) -> #REF! | AB21: =W21/(Z21+#REF!)*1000 -> #REF! | AC21: =1-(W21/((T21+#REF!))) -> #REF! | AD21: INSIGHT
B22: TOTAL - PARANA | L22: =SUBTOTAL(9,L21:L21) -> 70 | R22: =SUBTOTAL(9,R21:R21) -> 600 | W22: =SUBTOTAL(9,W21:W21) -> 26880 | X22: =W22*0.95 -> 25536 | AB22: =SUBTOTAL(9,AB21:AB21) -> #REF!
B23: 83840 | C23: PA | D23: BELEM | F23: BEEP MIDIA | G23: 42.448.723/0001-06 | H23: LOTÉRICAS | I23: MIDIA EM LOTERICA | J23: INSERÇÕES | K23: LOTÉRICAS | L23: 30 | M23: 46219 | N23: =M23+O23-1 -> 46220 | O23: 2 | P23: 15" | Q23: 300 | R23: =Q23*O23 -> 600 | S23: 109 | T23: =S23*R23 -> 65400 | U23: 0.38 | V23: =S23-S23*U23 -> 67.58 | W23: =T23*(1-U23) -> 40548 | X23: =W23*0.95 -> 38520.6 | Y23: 80888.889 | Z23: =Y23*O23 -> 161777.78 | AA23: =W23/(Z23+#REF!) -> #REF! | AB23: =W23/(Z23+#REF!)*1000 -> #REF! | AC23: =1-(W23/((T23+#REF!))) -> #REF! | AD23: INSIGHT
B24: TOTAL - PARA | L24: =SUBTOTAL(9,L23:L23) -> 30 | R24: =SUBTOTAL(9,R23:R23) -> 600 | W24: =SUBTOTAL(9,W23:W23) -> 40548 | X24: =W24*0.95 -> 38520.6 | AB24: =SUBTOTAL(9,AB23:AB23) -> #REF!
B25: 83840 | C25: RJ | D25: RIO DE JANEIRO | F25: BEEP MIDIA | G25: 42.448.723/0001-06 | H25: LOTÉRICAS | I25: MIDIA EM LOTERICA | J25: INSERÇÕES | K25: LOTÉRICAS | L25: 51 | M25: 46219 | N25: =M25+O25-1 -> 46220 | O25: 2 | P25: 15" | Q25: 300 | R25: =Q25*O25 -> 600 | S25: 129 | T25: =S25*R25 -> 77400 | U25: 0.38 | V25: =S25-S25*U25 -> 79.98 | W25: =T25*(1-U25) -> 47988 | X25: =W25*0.95 -> 45588.6 | Y25: 80888.889 | Z25: =Y25*O25 -> 161777.78 | AA25: =W25/(Z25+#REF!) -> #REF! | AB25: =W25/(Z25+#REF!)*1000 -> #REF! | AC25: =1-(W25/((T25+#REF!))) -> #REF! | AD25: INSIGHT
B26: TOTAL - RIO DE JANEIRO | L26: =SUBTOTAL(9,L25:L25) -> 51 | R26: =SUBTOTAL(9,R25:R25) -> 600 | W26: =SUBTOTAL(9,W25:W25) -> 47988 | X26: =W26*0.95 -> 45588.6 | AB26: =SUBTOTAL(9,AB25:AB25) -> #REF!
B27: 83840 | C27: MA | D27: SÃO LUIS | F27: BEEP MIDIA | G27: 42.448.723/0001-06 | H27: LOTÉRICAS | I27: MIDIA EM LOTERICA | J27: INSERÇÕES | K27: LOTÉRICAS | L27: 26 | M27: 46219 | N27: =M27+O27-1 -> 46220 | O27: 2 | P27: 15" | Q27: 300 | R27: =Q27*O27 -> 600 | S27: 79 | T27: =S27*R27 -> 47400 | U27: 0.38 | V27: =S27-S27*U27 -> 48.98 | W27: =T27*(1-U27) -> 29388 | X27: =W27*0.95 -> 27918.6 | Y27: 80888.889 | Z27: =Y27*O27 -> 161777.78 | AA27: =W27/(Z27+#REF!) -> #REF! | AB27: =W27/(Z27+#REF!)*1000 -> #REF! | AC27: =1-(W27/((T27+#REF!))) -> #REF! | AD27: INSIGHT
B28: TOTAL - MARANHAO | L28: =SUBTOTAL(9,L27:L27) -> 26 | R28: =SUBTOTAL(9,R27:R27) -> 600 | W28: =SUBTOTAL(9,W27:W27) -> 29388 | X28: =W28*0.95 -> 27918.6 | AB28: =SUBTOTAL(9,AB27:AB27) -> #REF!
B29: TOTAL GERAL | L29: =SUBTOTAL(9,L11:L28) -> 527 | R29: =SUBTOTAL(9,R11:R28) -> 5400 | T29: =SUBTOTAL(9,T11:T28) -> 570600 | W29: =SUBTOTAL(9,W11:W28) -> 361380 | X29: =W29*0.95 -> 343311 | Z29: =SUM(Z11:Z12) -> 161777.78
B31: OBSERVAÇÕES: NÃO HÁ VEICULAÇÃO AOS DOMINGOS
B34: VEICULO | D34: INS | E34: VALOR 100% | F34: TOTAL 100% | G34: DESEMBOLSO 95%
B35: INSIGHT MIDIA | D35: =SUMIF(F$11:$F28,B35,R$11:$R28) -> 3600 | E35: =SUMIF($F$11:$AD$29,B35,$W$11:$W$12) -> 243456 | F35: =SUMIF($F$11:$F$28,B35,$W$11:$W$28) -> 243456 | G35: =SUMIF($F$11:$F$27,B35,$X$11:$X$28) -> 231283.2
B36: BEEP MIDIA | D36: =SUMIF(F$11:$F29,B36,R$11:$R29) -> 1800 | E36: =SUMIF($F$11:$AD$29,B36,$W$11:$W$12) -> 117924 | F36: =SUMIF($F$11:$F$28,B36,$W$11:$W$28) -> 117924 | G36: =SUMIF($F$11:$F$27,B36,$X$11:$X$28) -> 112027.8
B37: TOTAL | D37: =D36 -> 1800 | E37: =SUM(E36:E36) -> 117924 | F37: =F35+F36 -> 361380 | G37: =G35+G36 -> 343311
B40: AGENCIA | D40: VALOR 100% | E40: VALOR 95%
B41: CALIA | D41: =SUMIF($A$11:$A$12,B41,$W$11:$W$12) -> 0 | E41: =D41*0.95 -> 0
B42: SA | D42: =SUMIF($A$11:$A$12,B42,$W$11:$W$12) -> 0 | E42: =D42*0.95 -> 0
B43: DE BRITO | D43: =SUMIF($A$11:$A$12,B43,$W$11:$W$12) -> 0 | E43: =D43*0.95 -> 0

Sheet DOOH - PAINEL
B2: PROGRAMAÇÃO - DOOH PAINEL ELETRÔNICO
B4: =CAPA!D4 -> MINISTÉRIO DA EDUCAÇÃO
B5: =CAPA!D6 -> FIES 2026
B6: =CAPA!D8 -> JULHO DE 2026
B8: IDENTIFICADOR SISTEMA | C8: UF | D8: PRAÇA | E8: CÓD MUNICÍPIO | F8: VEÍCULO | G8: CNPJ | H8: LOCAL | I8: FORMATO | M8: PERÍODO DE VEICULAÇÃO | P8: QUANT. DE FACES | Q8: QTD. INS DIA | R8: TT. INS.PERÍODO | S8: QTD DE COTAS CONTRATADAS | T8: VALOR TABELA | V8: DESC. % | W8: VALOR NEGOCIADO | Y8: VALOR DESEMBOLSO 95% | Z8: COBERTURA PERÍODO (FLUXO) | AA8: IMPACTO PERÍODO | AB8: CPI | AC8: CPM | AD8: REPRESENTANTE
I9: TIPO | J9: TIPO DE COMPRA | K9: AMBIENTE | L9: MATERIAL | M9: INICIAL | N9: FINAL | O9: TOTAL DE DIAS | T9: UNITÁRIO | U9: TOTAL | W9: UNITÁRIO | X9: TOTAL 100%
B11: 12084 | C11: PE | D11: RECIFE | E11: 2611606 | F11: WE SUPER OOH | G11: 13.045.189/0005-70 | H11: Av. Conselheiro Rosa e Silva, 212 | I11: PAINEL ELETRÔNICO | J11: MENSAL PROPORCIONAL | K11: VIAS DE ALTO FLUXO | L11: 10" | M11: 46219 | N11: =M11+O11-1 -> 46220 | O11: 2 | P11: 1 | Q11: =360*2 -> 720 | R11: =Q11*P11*O11 -> 1440 | S11: 2 | T11: 2649.86 | U11: =T11*S11 -> 5299.72 | V11: 0.15 | W11: =T11-T11*V11 -> 2252.381 | X11: =U11*(1-V11) -> 4504.762 | Y11: =X11*0.95 -> 4279.5239 | Z11: 252578 | AA11: =R11 -> 1440 | AB11: =X11/(AA11) -> 3.1283069 | AC11: =X11/(AA11)*1000 -> 3128.3069 | AD11: MOSAICO
B12: 12084 | C12: PE | D12: RECIFE | E12: 2611606 | F12: WE SUPER OOH | G12: 13.045.189/0005-70 | H12: Av. 17 de Agosto, 823 | I12: PAINEL ELETRÔNICO | J12: MENSAL PROPORCIONAL | K12: VIAS DE ALTO FLUXO | L12: 10" | M12: 46219 | N12: =M12+O12-1 -> 46220 | O12: 2 | P12: 1 | Q12: =360*2 -> 720 | R12: =Q12*P12*O12 -> 1440 | S12: 2 | T12: 2649.86 | U12: 5299.72 | V12: 0.15 | W12: =T12-T12*V12 -> 2252.381 | X12: =U12*(1-V12) -> 4504.762 | Y12: =X12*0.95 -> 4279.5239 | Z12: 209499 | AA12: =R12 -> 1440 | AB12: =X12/(AA12) -> 3.1283069 | AC12: =X12/(AA12)*1000 -> 3128.3069 | AD12: MOSAICO
B13: 12084 | C13: PE | D13: RECIFE | E13: 2611606 | F13: WE SUPER OOH | G13: 13.045.189/0005-70 | H13: Rua Ernesto de Paula Santos esquina com a Av. Engenheiro Domingos Ferreira, 4140 | I13: PAINEL ELETRÔNICO | J13: MENSAL PROPORCIONAL | K13: VIAS DE ALTO FLUXO | L13: 10" | M13: 46219 | N13: =M13+O13-1 -> 46220 | O13: 2 | P13: 1 | Q13: =360*2 -> 720 | R13: =Q13*P13*O13 -> 1440 | S13: 2 | T13: 2649.86 | U13: 5299.72 | V13: 0.15 | W13: =T13-T13*V13 -> 2252.381 | X13: =U13*(1-V13) -> 4504.762 | Y13: =X13*0.95 -> 4279.5239 | Z13: 70000 | AA13: =R13 -> 1440 | AB13: =X13/(AA13) -> 3.1283069 | AC13: =X13/(AA13)*1000 -> 3128.3069 | AD13: MOSAICO
B14: 82219 | C14: PE | D14: RECIFE | E14: 2611606 | F14: INTELICOM | H14: Av. Conselheiro Aguiar acesso Shopping -Pina | I14: PAINEL ELETRÔNICO | J14: MENSAL PROPORCIONAL | K14: VIAS DE ALTO FLUXO | L14: 10" | M14: 46219 | N14: =M14+O14-1 -> 46220 | O14: 2 | P14: 1 | Q14: 945 | R14: =Q14*P14*O14 -> 1890 | S14: 1 | T14: =27001*0.7/7*O14 -> 5400.2 | U14: =T14 -> 5400.2 | V14: 0 | W14: =T14-T14*V14 -> 5400.2 | X14: =U14*(1-V14) -> 5400.2 | Y14: =X14*0.95 -> 5130.19 | Z14: 70000 | AA14: =R14 -> 1890 | AB14: =X14/(AA14+AA16) -> 1.8557388 | AC14: =X14/(AA14+AA16)*1000 -> 1855.7388 | AD14: DIRETO
B15: 82219 | C15: PE | D15: RECIFE | E15: 2611606 | F15: INTELICOM | H15: Av. Conselheiro Rosa e Silva - Aflitos | I15: PAINEL ELETRÔNICO | J15: MENSAL PROPORCIONAL | K15: VIAS DE ALTO FLUXO | L15: 10" | M15: 46219 | N15: =M15+O15-1 -> 46220 | O15: 2 | P15: 1 | Q15: 945 | R15: =Q15*P15*O15 -> 1890 | S15: 1 | T15: =27001*0.7/7*O15 -> 5400.2 | U15: =T15 -> 5400.2 | V15: 0 | W15: =T15-T15*V15 -> 5400.2 | X15: =U15*(1-V15) -> 5400.2 | Y15: =X15*0.95 -> 5130.19 | Z15: 70000 | AA15: =R15 -> 1890 | AB15: =X15/(AA15+AA23) -> 0.83208012 | AC15: =X15/(AA15+AA23)*1000 -> 832.08012 | AD15: DIRETO
B16: 82219 | C16: PE | D16: RECIFE | E16: 2611606 | F16: INTELICOM | H16: Av. Abdias de Carvalho - Madalena | I16: PAINEL ELETRÔNICO | J16: MENSAL PROPORCIONAL | K16: VIAS DE ALTO FLUXO | L16: 10" | M16: 46219 | N16: =M16+O16-1 -> 46220 | O16: 2 | P16: 1 | Q16: 510 | R16: =Q16*P16*O16 -> 1020 | S16: 1 | T16: =31913*0.7/7*O16 -> 6382.6 | U16: =T16 -> 6382.6 | V16: 0 | W16: =T16-T16*V16 -> 6382.6 | X16: =U16*(1-V16) -> 6382.6 | Y16: =X16*0.95 -> 6063.47 | Z16: =Z14 -> 70000 | AA16: =R16 -> 1020 | AB16: =X16/(AA16+AA24) -> 1.135694 | AC16: =X16/(AA16+AA24)*1000 -> 1135.694 | AD16: DIRETO
B17: 82219 | C17: PE | D17: RECIFE | E17: 2611606 | F17: INTELICOM | H17: Av. Conselheiro Rosa e Silva - Tamarineira | I17: PAINEL ELETRÔNICO | J17: MENSAL PROPORCIONAL | K17: VIAS DE ALTO FLUXO | L17: 10" | M17: 46219 | N17: =M17+O17-1 -> 46220 | O17: 2 | P17: 1 | Q17: 510 | R17: =Q17*P17*O17 -> 1020 | S17: 1 | T17: =31913*0.7/7*O17 -> 6382.6 | U17: =T17 -> 6382.6 | V17: 0 | W17: =T17-T17*V17 -> 6382.6 | X17: =U17*(1-V17) -> 6382.6 | Y17: =X17*0.95 -> 6063.47 | Z17: 70000 | AA17: =R17 -> 1020 | AB17: =X17/(AA17+AA19) -> 3.1287255 | AC17: =X17/(AA17+AA19)*1000 -> 3128.7255 | AD17: DIRETO
B18: 82219 | C18: PE | D18: RECIFE | E18: 2611606 | F18: INTELICOM | H18: Av. 17 de Agosto - Casa Forte | I18: PAINEL ELETRÔNICO | J18: MENSAL PROPORCIONAL | K18: VIAS DE ALTO FLUXO | L18: 10" | M18: 46219 | N18: =M18+O18-1 -> 46220 | O18: 2 | P18: 1 | Q18: 510 | R18: =Q18*P18*O18 -> 1020 | S18: 1 | T18: =31913*0.7/7*O18 -> 6382.6 | U18: =T18 -> 6382.6 | V18: 0 | W18: =T18-T18*V18 -> 6382.6 | X18: =U18*(1-V18) -> 6382.6 | Y18: =X18*0.95 -> 6063.47 | Z18: 70000 | AA18: =R18 -> 1020 | AB18: =X18/(AA18+AA26) -> 6.257451 | AC18: =X18/(AA18+AA26)*1000 -> 6257.451 | AD18: DIRETO
B19: 82219 | C19: PE | D19: RECIFE | E19: 2611606 | F19: INTELICOM | H19: Av. Conselheiro Aguiar - Avenida | I19: PAINEL ELETRÔNICO | J19: MENSAL PROPORCIONAL | K19: VIAS DE ALTO FLUXO | L19: 10" | M19: 46219 | N19: =M19+O19-1 -> 46220 | O19: 2 | P19: 1 | Q19: 510 | R19: =Q19*P19*O19 -> 1020 | S19: 1 | T19: =31913*0.7/7*O19 -> 6382.6 | U19: =T19 -> 6382.6 | V19: 0 | W19: =T19-T19*V19 -> 6382.6 | X19: =U19*(1-V19) -> 6382.6 | Y19: =X19*0.95 -> 6063.47 | Z19: =Z17 -> 70000 | AA19: =R19 -> 1020 | AB19: =X19/(AA19+AA27) -> 1.8662573 | AC19: =X19/(AA19+AA27)*1000 -> 1866.2573 | AD19: DIRETO
B20: 82219 | C20: PE | D20: RECIFE | E20: 2611606 | F20: INTELICOM | H20: Av. Engenheiro Domingos - Avenida | I20: PAINEL ELETRÔNICO | J20: MENSAL PROPORCIONAL | K20: VIAS DE ALTO FLUXO | L20: 10" | M20: 46219 | N20: =M20+O20-1 -> 46220 | O20: 2 | P20: 1 | Q20: 510 | R20: =Q20*P20*O20 -> 1020 | S20: 1 | T20: =31913*0.7/7*O20 -> 6382.6 | U20: =T20 -> 6382.6 | V20: 0 | W20: =T20-T20*V20 -> 6382.6 | X20: =U20*(1-V20) -> 6382.6 | Y20: =X20*0.95 -> 6063.47 | Z20: 70000 | AA20: =R20 -> 1020 | AB20: =X20/(AA20+AA22) -> 3.1287255 | AC20: =X20/(AA20+AA22)*1000 -> 3128.7255 | AD20: DIRETO
B21: 82219 | C21: PE | D21: RECIFE | E21: 2611606 | F21: INTELICOM | H21: Av. Gov. Agamenon - Ilha do \leite | I21: PAINEL ELETRÔNICO | J21: MENSAL PROPORCIONAL | K21: VIAS DE ALTO FLUXO | L21: 10" | M21: 46219 | N21: =M21+O21-1 -> 46220 | O21: 2 | P21: 1 | Q21: 510 | R21: =Q21*P21*O21 -> 1020 | S21: 1 | T21: =31913*0.7/7*O21 -> 6382.6 | U21: =T21 -> 6382.6 | V21: 0 | W21: =T21-T21*V21 -> 6382.6 | X21: =U21*(1-V21) -> 6382.6 | Y21: =X21*0.95 -> 6063.47 | Z21: 70000 | AA21: =R21 -> 1020 | AB21: =X21/(AA21+AA29) -> 2.5945528 | AC21: =X21/(AA21+AA29)*1000 -> 2594.5528 | AD21: DIRETO
B22: 82219 | C22: PE | D22: RECIFE | E22: 2611606 | F22: INTELICOM | H22: Av. Eng. Abdias de Carvalho - Avenida | I22: PAINEL ELETRÔNICO | J22: MENSAL PROPORCIONAL | K22: VIAS DE ALTO FLUXO | L22: 10" | M22: 46219 | N22: =M22+O22-1 -> 46220 | O22: 2 | P22: 1 | Q22: 510 | R22: =Q22*P22*O22 -> 1020 | S22: 1 | T22: =31913*0.7/7*O22 -> 6382.6 | U22: =T22 -> 6382.6 | V22: 0 | W22: =T22-T22*V22 -> 6382.6 | X22: =U22*(1-V22) -> 6382.6 | Y22: =X22*0.95 -> 6063.47 | Z22: =Z20 -> 70000 | AA22: =R22 -> 1020 | AB22: =X22/(AA22+AA30) -> 6.257451 | AC22: =X22/(AA22+AA30)*1000 -> 6257.451 | AD22: DIRETO
B23: 107541 | C23: PE | D23: RECIFE | E23: 2611606 | F23: MLA MIDIA | G23: 52.008.394/0001-28 | H23: ERNESTO PAULA SANTOS Nº 867 - RECIFE | I23: PAINEL ELETRÔNICO | J23: MENSAL PROPORCIONAL | K23: VIAS DE ALTO FLUXO | L23: 10" | M23: 46219 | N23: =M23+O23-1 -> 46220 | O23: 2 | P23: 1 | Q23: 2300 | R23: =Q23*P23*O23 -> 4600 | S23: 1 | T23: 5.4 | U23: =T23*R23 -> 24840 | V23: 0.66 | W23: =T23-T23*V23 -> 1.836 | X23: =U23*(1-V23) -> 8445.6 | Y23: =X23*0.95 -> 8023.32 | Z23: 70000 | AA23: =R23 -> 4600 | AB23: =X23/(AA23+AA25) -> 0.918 | AC23: =X23/(AA23+AA25)*1000 -> 918 | AD23: DIRETO
B24: 107541 | C24: PE | D24: RECIFE | E24: 2611606 | F24: MLA MIDIA | G24: 52.008.394/0001-28 | H24: AV. GOV. AGAMENON MAGALHÃES Nº2656 - RECIFE | I24: PAINEL ELETRÔNICO | J24: MENSAL PROPORCIONAL | K24: VIAS DE ALTO FLUXO | L24: 10" | M24: 46219 | N24: =M24+O24-1 -> 46220 | O24: 2 | P24: 1 | Q24: 2300 | R24: =Q24*P24*O24 -> 4600 | S24: 1 | T24: 5.4 | U24: =T24*R24 -> 24840 | V24: 0.66 | W24: =T24-T24*V24 -> 1.836 | X24: =U24*(1-V24) -> 8445.6 | Y24: =X24*0.95 -> 8023.32 | Z24: 70000 | AA24: =R24 -> 4600 | AB24: =X24/(AA24+AA26) -> 1.836 | AC24: =X24/(AA24+AA26)*1000 -> 1836 | AD24: DIRETO
B25: 107541 | C25: PE | D25: RECIFE | E25: 2611606 | F25: MLA MIDIA | G25: 52.008.394/0001-28 | H25: AV. DOMINGOS FERREIRA Nº1537 - RECIFE | I25: PAINEL ELETRÔNICO | J25: MENSAL PROPORCIONAL | K25: VIAS DE ALTO FLUXO | L25: 10" | M25: 46219 | N25: =M25+O25-1 -> 46220 | O25: 2 | P25: 1 | Q25: 2300 | R25: =Q25*P25*O25 -> 4600 | S25: 1 | T25: 5.4 | U25: =T25*R25 -> 24840 | V25: 0.66 | W25: =T25-T25*V25 -> 1.836 | X25: =U25*(1-V25) -> 8445.6 | Y25: =X25*0.95 -> 8023.32 | Z25: =Z23 -> 70000 | AA25: =R25 -> 4600 | AB25: =X25/(AA25+AA27) -> 1.2065143 | AC25: =X25/(AA25+AA27)*1000 -> 1206.5143 | AD25: DIRETO
B26: TOTAL - PERNAMBUCO | P26: =SUBTOTAL(9,P11:P25) -> 15 | R26: =SUBTOTAL(9,R11:R25) -> 29040 | X26: =SUBTOTAL(9,X11:X25) -> 94329.686 | Y26: =SUBTOTAL(9,Y11:Y25) -> 89613.202 | AC26: =AVERAGE(AC11:AC25)*1.5 -> 4040.2111
B27: 87254 | C27: PR | D27: CURITIBA | E27: 4106902 | F27: LED MAIS | G27: 28.507.808/0001-89 | H27: AV. IGUAÇU 4399, ESQ. COM RUA ARTHUR BERNARDES - TERRENO DA SOUQ | I27: PAINEL ELETRÔNICO | J27: POR INSERÇÃO | K27: VIAS DE ALTO FLUXO | L27: 10" | M27: 46219 | N27: =M27+O27-1 -> 46220 | O27: 2 | P27: 1 | Q27: 1200 | R27: =Q27*P27*O27 -> 2400 | S27: 1 | T27: 4.65 | U27: =T27*R27 -> 11160 | V27: 0.25 | W27: =T27-T27*V27 -> 3.4875 | X27: =U27*(1-V27) -> 8370 | Y27: =X27*0.95 -> 7951.5 | Z27: - | AA27: =R27 -> 2400 | AB27: - | AC27: - | AD27: G2
B28: 87254 | C28: PR | D28: CURITIBA | E28: 4106902 | F28: LED MAIS | G28: 28.507.808/0001-89 | H28: RODOVIA JOÃO LEOPOLDO JACOMEL 12627 RETENÇÃO DE SINALEIRO - ESQ. COM AV. MARINGÁ SENT. PINHAIS | I28: PAINEL ELETRÔNICO | J28: POR INSERÇÃO | K28: VIAS DE ALTO FLUXO | L28: 10" | M28: 46219 | N28: =M28+O28-1 -> 46220 | O28: 2 | P28: 1 | Q28: 1200 | R28: =Q28*P28*O28 -> 2400 | S28: 1 | T28: 4.65 | U28: =T28*R28 -> 11160 | V28: 0.25 | W28: =T28-T28*V28 -> 3.4875 | X28: =U28*(1-V28) -> 8370 | Y28: =X28*0.95 -> 7951.5 | Z28: - | AA28: =R28 -> 2400 | AB28: - | AC28: - | AD28: G2
B29: 67263 | C29: PR | D29: CURITIBA | E29: 4106902 | F29: PLAN PAINÉIS | G29: 13.517.365/0001-30 | H29: RUA MAUA, 452, ANEXO AO ESTADIO MAJOR ANTONIO COUTO PEREIRA | I29: PAINEL ELETRÔNICO | J29: PERÍODO | K29: VIAS DE ALTO FLUXO | L29: 10" | M29: 46219 | N29: =M29+O29-1 -> 46220 | O29: 2 | P29: 1 | Q29: =360*2 -> 720 | R29: =Q29*P29*O29 -> 1440 | S29: 1 | T29: =7375/7*O29 -> 2107.1429 | U29: =T29*S29 -> 2107.1429 | V29: 0.1 | W29: =T29-T29*V29 -> 1896.4286 | X29: =U29*(1-V29) -> 1896.4286 | Y29: =X29*0.95 -> 1801.6071 | Z29: - | AA29: =R29 -> 1440 | AB29: - | AC29: - | AD29: DIRETO
B30: TOTAL - PARANÁ | P30: =SUBTOTAL(9,P27:P29) -> 3 | R30: =SUBTOTAL(9,R27:R29) -> 6240 | X30: =SUBTOTAL(9,X27:X29) -> 18636.429 | Y30: =SUBTOTAL(9,Y27:Y29) -> 17704.607 | AC30: =AVERAGE(AC27:AC29)*1.5 -> #DIV/0!
B31: 87254 | C31: BA | D31: SALVADOR | E31: 2927408 | F31: LED MAIS | G31: 28.507.808/0001-89 | H31: AV. SANTOS DUMONT (PROXIMO AO ASSAI ATACADISTA) | I31: PAINEL ELETRÔNICO | J31: MENSAL PROPORCIONAL | K31: VIAS DE ALTO FLUXO | L31: 10" | M31: 46219 | N31: =M31+O31-1 -> 46220 | O31: 2 | P31: 1 | Q31: 1200 | R31: =Q31*P31*O31 -> 2400 | S31: 1 | T31: 4.65 | U31: =T31*R31 -> 11160 | V31: 0.25 | W31: =T31-T31*V31 -> 3.4875 | X31: =U31*(1-V31) -> 8370 | Y31: =X31*0.95 -> 7951.5 | Z31: - | AA31: =R31 -> 2400 | AB31: - | AC31: - | AD31: G2
B32: 87254 | C32: BA | D32: SALVADOR | E32: 2927408 | F32: LED MAIS | G32: 28.507.808/0001-89 | H32: AV. PRINCESA ISABEL (PROXIMO A PIZZA HUT) | I32: PAINEL ELETRÔNICO | J32: MENSAL PROPORCIONAL | K32: VIAS DE ALTO FLUXO | L32: 10" | M32: 46219 | N32: =M32+O32-1 -> 46220 | O32: 2 | P32: 1 | Q32: 1200 | R32: =Q32*P32*O32 -> 2400 | S32: 1 | T32: 4.65 | U32: =T32*R32 -> 11160 | V32: 0.25 | W32: =T32-T32*V32 -> 3.4875 | X32: =U32*(1-V32) -> 8370 | Y32: =X32*0.95 -> 7951.5 | Z32: - | AA32: =R32 -> 2400 | AB32: - | AC32: - | AD32: G2
B33: TOTAL - BAHIA | P33: =SUBTOTAL(9,P31:P32) -> 2 | R33: =SUBTOTAL(9,R31:R32) -> 4800 | X33: =SUBTOTAL(9,X31:X32) -> 16740 | Y33: =SUBTOTAL(9,Y31:Y32) -> 15903 | AC33: =AVERAGE(AC31:AC32)*1.5 -> #DIV/0!
B34: 84398 | C34: CE | D34: FORTALEZA | E34: 2304400 | F34: 55 MÍDIA | G34: 42.317.692/0001-46 | H34: AV BARÃO DE STUDART, 81- MEIRELES | I34: MEGA PAINEL DE LED 3D | J34: POR INSERÇÃO | K34: VIAS DE ALTO FLUXO | L34: 15" | M34: 46219 | N34: =M34+O34-1 -> 46220 | O34: 2 | P34: 1 | Q34: 1500 | R34: =Q34*P34*O34 -> 3000 | S34: 1 | T34: 15.69 | U34: =T34*R34 -> 47070 | V34: 0.21 | W34: =T34-T34*V34 -> 12.3951 | X34: =U34*(1-V34) -> 37185.3 | Y34: =X34*0.95 -> 35326.035 | Z34: 63535.857 | AA34: 444751 | AB34: =X34/(AA34+AA35) -> 0.052108204 | AC34: =X34/(AA34+AA35)*1000 -> 52.108204 | AD34: MIDIA MAIS
B35: 84398 | C35: CE | D35: FORTALEZA | E35: 2304400 | F35: 55 MÍDIA | G35: 42.317.692/0001-46 | H35: AV JULIO ABREU, 291, MEIRELES | I35: PAINEL DE LED | J35: POR INSERÇÃO | K35: VIAS DE ALTO FLUXO | L35: 15" | M35: 46219 | N35: =M35+O35-1 -> 46220 | O35: 2 | P35: 1 | Q35: 1500 | R35: =Q35*P35*O35 -> 3000 | S35: 1 | T35: 3.66 | U35: =T35*R35 -> 10980 | V35: 0.21 | W35: =T35-T35*V35 -> 2.8914 | X35: =U35*(1-V35) -> 8674.2 | Y35: =X35*0.95 -> 8240.49 | Z35: 38409 | AA35: 268866 | AB35: =X35/(AA35+AA36) -> 0.020079167 | AC35: =X35/(AA35+AA36)*1000 -> 20.079167 | AD35: MIDIA MAIS
B36: 84398 | C36: CE | D36: FORTALEZA | E36: 2304400 | F36: 55 MÍDIA | G36: 42.317.692/0001-46 | H36: RUA ILDEFONSO ALBANO, 2260 - ALDEOTA | I36: PAINEL DE LED | J36: POR INSERÇÃO | K36: VIAS DE ALTO FLUXO | L36: 15" | M36: 46219 | N36: =M36+O36-1 -> 46220 | O36: 2 | P36: 1 | Q36: 1500 | R36: =Q36*P36*O36 -> 3000 | S36: 1 | T36: 3.66 | U36: =T36*R36 -> 10980 | V36: 0.21 | W36: =T36-T36*V36 -> 2.8914 | X36: =U36*(1-V36) -> 8674.2 | Y36: =X36*0.95 -> 8240.49 | Z36: 23305 | AA36: 163134 | AB36: =X36/(AA36+AA37) -> 0.027369451 | AC36: =X36/(AA36+AA37)*1000 -> 27.369451 | AD36: MIDIA MAIS
B37: 84398 | C37: CE | D37: FORTALEZA | E37: 2304400 | F37: 55 MÍDIA | G37: 42.317.692/0001-46 | H37: AV BARÃO DE STUDART, 100 - MEIRELES | I37: PAINEL DE LED | J37: POR INSERÇÃO | K37: VIAS DE ALTO FLUXO | L37: 15" | M37: 46219 | N37: =M37+O37-1 -> 46220 | O37: 2 | P37: 1 | Q37: 1500 | R37: =Q37*P37*O37 -> 3000 | S37: 1 | T37: 3.66 | U37: =T37*R37 -> 10980 | V37: 0.21 | W37: =T37-T37*V37 -> 2.8914 | X37: =U37*(1-V37) -> 8674.2 | Y37: =X37*0.95 -> 8240.49 | Z37: 21971 | AA37: 153796 | AB37: =X37/(AA37+AA38) -> 0.024196828 | AC37: =X37/(AA37+AA38)*1000 -> 24.196828 | AD37: MIDIA MAIS
B38: 84398 | C38: CE | D38: FORTALEZA | E38: 2304400 | F38: 55 MÍDIA | G38: 42.317.692/0001-46 | H38: AV DOM MANUEL, 1110 - CENTRO | I38: PAINEL DE LED | J38: POR INSERÇÃO | K38: VIAS DE ALTO FLUXO | L38: 15" | M38: 46219 | N38: =M38+O38-1 -> 46220 | O38: 2 | P38: 1 | Q38: 1500 | R38: =Q38*P38*O38 -> 3000 | S38: 1 | T38: 3.66 | U38: =T38*R38 -> 10980 | V38: 0.21 | W38: =T38-T38*V38 -> 2.8914 | X38: =U38*(1-V38) -> 8674.2 | Y38: =X38*0.95 -> 8240.49 | Z38: 63535.857 | AA38: 204689 | AB38: =X38/(AA38+AA39) -> 0.025279411 | AC38: =X38/(AA38+AA39)*1000 -> 25.279411 | AD38: MIDIA MAIS
B39: 84398 | C39: CE | D39: FORTALEZA | E39: 2304400 | F39: 55 MÍDIA | G39: 42.317.692/0001-46 | H39: AV SARGENTO HERMÍNIO SAMPAIO, 1176 - MONTE CASTELO | I39: PAINEL DE LED | J39: POR INSERÇÃO | K39: VIAS DE ALTO FLUXO | L39: 15" | M39: 46219 | N39: =M39+O39-1 -> 46220 | O39: 2 | P39: 1 | Q39: 1500 | R39: =Q39*P39*O39 -> 3000 | S39: 1 | T39: 2.62 | U39: =T39*R39 -> 7860 | V39: 0.21 | W39: =T39-T39*V39 -> 2.0698 | X39: =U39*(1-V39) -> 6209.4 | Y39: =X39*0.95 -> 5898.93 | Z39: 38409 | AA39: 138444 | AB39: =X39/(AA39+AA40) -> 0.007356281 | AC39: =X39/(AA39+AA40)*1000 -> 7.356281 | AD39: MIDIA MAIS
B40: 84398 | C40: CE | D40: FORTALEZA | E40: 2304400 | F40: 55 MÍDIA | G40: 42.317.692/0001-46 | H40: AV WASHINGTON SOARES,4370B - EDSON QUEIROZ | I40: PAINEL DE LED | J40: POR INSERÇÃO | K40: VIAS DE ALTO FLUXO | L40: 15" | M40: 46219 | N40: =M40+O40-1 -> 46220 | O40: 2 | P40: 1 | Q40: 1500 | R40: =Q40*P40*O40 -> 3000 | S40: 1 | T40: 2.62 | U40: =T40*R40 -> 7860 | V40: 0.21 | W40: =T40-T40*V40 -> 2.0698 | X40: =U40*(1-V40) -> 6209.4 | Y40: =X40*0.95 -> 5898.93 | Z40: 23305 | AA40: 705651 | AB40: =X40/(AA40+AA41) -> 0.0053975915 | AC40: =X40/(AA40+AA41)*1000 -> 5.3975915 | AD40: MIDIA MAIS
B41: 84398 | C41: CE | D41: FORTALEZA | E41: 2304400 | F41: 55 MÍDIA | G41: 42.317.692/0001-46 | H41: AV BEZERRA DE MENEZES, 2113 - PARUQELÂNDIA | I41: PAINEL DE LED | J41: POR INSERÇÃO | K41: VIAS DE ALTO FLUXO | L41: 15" | M41: 46219 | N41: =M41+O41-1 -> 46220 | O41: 2 | P41: 1 | Q41: 1500 | R41: =Q41*P41*O41 -> 3000 | S41: 1 | T41: 2.62 | U41: =T41*R41 -> 7860 | V41: 0.21 | W41: =T41-T41*V41 -> 2.0698 | X41: =U41*(1-V41) -> 6209.4 | Y41: =X41*0.95 -> 5898.93 | Z41: 21971 | AA41: 444751 | AB41: =X41/(AA41+AA42) -> 0.010374123 | AC41: =X41/(AA41+AA42)*1000 -> 10.374123 | AD41: MIDIA MAIS
B42: 84398 | C42: CE | D42: FORTALEZA | E42: 2304400 | F42: 55 MÍDIA | G42: 42.317.692/0001-46 | H42: AV ANTONIO SALES, 3202 - DIONÍSIO TORRES | I42: PAINEL DE LED | J42: POR INSERÇÃO | K42: VIAS DE ALTO FLUXO | L42: 15" | M42: 46219 | N42: =M42+O42-1 -> 46220 | O42: 2 | P42: 1 | Q42: 1500 | R42: =Q42*P42*O42 -> 3000 | S42: 1 | T42: 2.62 | U42: =T42*R42 -> 7860 | V42: 0.21 | W42: =T42-T42*V42 -> 2.0698 | X42: =U42*(1-V42) -> 6209.4 | Y42: =X42*0.95 -> 5898.93 | Z42: 63535.857 | AA42: 153796 | AB42: =X42/(AA42+AA43) -> 0.017321227 | AC42: =X42/(AA42+AA43)*1000 -> 17.321227 | AD42: MIDIA MAIS
B43: 84398 | C43: CE | D43: FORTALEZA | E43: 2304400 | F43: 55 MÍDIA | G43: 42.317.692/0001-46 | H43: AV. VIRGÍLIO TÁVORA, 1090 - ALDEOTA | I43: PAINEL DE LED | J43: POR INSERÇÃO | K43: VIAS DE ALTO FLUXO | L43: 15" | M43: 46219 | N43: =M43+O43-1 -> 46220 | O43: 2 | P43: 1 | Q43: 1500 | R43: =Q43*P43*O43 -> 3000 | S43: 1 | T43: 2.62 | U43: =T43*R43 -> 7860 | V43: 0.21 | W43: =T43-T43*V43 -> 2.0698 | X43: =U43*(1-V43) -> 6209.4 | Y43: =X43*0.95 -> 5898.93 | Z43: 63535.857 | AA43: 204689 | AB43: =X43/(AA43+AA44) -> 0.012099565 | AC43: =X43/(AA43+AA44)*1000 -> 12.099565 | AD43: MIDIA MAIS
B44: 84398 | C44: CE | D44: FORTALEZA | E44: 2304400 | F44: 55 MÍDIA | G44: 42.317.692/0001-46 | H44: AV. EUSÉBIO DE QUEIROZ, 4985 - PRAÇA EUSÉBIO | I44: PAINEL DE LED | J44: POR INSERÇÃO | K44: VIAS DE ALTO FLUXO | L44: 15" | M44: 46219 | N44: =M44+O44-1 -> 46220 | O44: 2 | P44: 1 | Q44: 1500 | R44: =Q44*P44*O44 -> 3000 | S44: 1 | T44: 2.62 | U44: =T44*R44 -> 7860 | V44: 0.21 | W44: =T44-T44*V44 -> 2.0698 | X44: =U44*(1-V44) -> 6209.4 | Y44: =X44*0.95 -> 5898.93 | Z44: 38409 | AA44: 308503 | AB44: =X44/(AA44+AA45) -> 0.0082434345 | AC44: =X44/(AA44+AA45)*1000 -> 8.2434345 | AD44: MIDIA MAIS
B45: 84398 | C45: CE | D45: FORTALEZA | E45: 2304400 | F45: 55 MÍDIA | G45: 42.317.692/0001-46 | H45: AV. DOUTOR SILAS MUNGUBA, 450 - PARANGABA | I45: PAINEL DE LED | J45: POR INSERÇÃO | K45: VIAS DE ALTO FLUXO | L45: 15" | M45: 46219 | N45: =M45+O45-1 -> 46220 | O45: 2 | P45: 1 | Q45: 1500 | R45: =Q45*P45*O45 -> 3000 | S45: 1 | T45: 2.62 | U45: =T45*R45 -> 7860 | V45: 0.21 | W45: =T45-T45*V45 -> 2.0698 | X45: =U45*(1-V45) -> 6209.4 | Y45: =X45*0.95 -> 5898.93 | Z45: 23305 | AA45: 444751 | AB45: =X45/(AA45) -> 0.01396152 | AC45: =X45/(AA45)*1000 -> 13.96152 | AD45: MIDIA MAIS
B46: 59425 | C46: CE | D46: FORTALEZA | E46: 2304400 | F46: NORDESTE MIDIA EXTERIOR DIGITAL | G46: 08.755.659/0001-60 | H46: AV. WASHINGTON SOARES 2380 - ENGENHEIRO LUCIANO CAVALCANTE | I46: PAINEL ELETRÔNICO | J46: POR INSERÇÃO | K46: VIAS DE ALTO FLUXO | L46: 10" | M46: 46219 | N46: =M46+O46-1 -> 46220 | O46: 2 | P46: 1 | Q46: 2000 | R46: =Q46*P46*O46 -> 4000 | S46: 1 | T46: 4 | U46: =T46*R46 -> 16000 | V46: 0.3 | W46: =T46-T46*V46 -> 2.8 | X46: =U46*(1-V46) -> 11200 | Y46: =X46*0.95 -> 10640 | Z46: - | AA46: - | AB46: - | AC46: - | AD46: FERNANDO KERN
B47: 59425 | C47: CE | D47: FORTALEZA | E47: 2304400 | F47: NORDESTE MIDIA EXTERIOR DIGITAL | G47: 08.755.659/0001-60 | H47: AV. RUI BARBOSA 2212 - JOAQUIM TÁVORA | I47: PAINEL ELETRÔNICO | J47: POR INSERÇÃO | K47: VIAS DE ALTO FLUXO | L47: 10" | M47: 46219 | N47: =M47+O47-1 -> 46220 | O47: 2 | P47: 1 | Q47: 2000 | R47: =Q47*P47*O47 -> 4000 | S47: 1 | T47: 4 | U47: =T47*R47 -> 16000 | V47: 0.3 | W47: =T47-T47*V47 -> 2.8 | X47: =U47*(1-V47) -> 11200 | Y47: =X47*0.95 -> 10640 | Z47: - | AA47: - | AB47: - | AC47: - | AD47: FERNANDO KERN
B48: 12084 | C48: CE | D48: FORTALEZA | E48: 2304400 | F48: WE SUPER OOH | G48: 13.045.189/0005-70 | H48: Av. Bezerra de Menezes, 2576 | I48: PAINEL ELETRÔNICO | J48: MENSAL PROPORCIONAL | K48: VIAS DE ALTO FLUXO | L48: 10" | M48: 46219 | N48: =M48+O48-1 -> 46220 | O48: 2 | P48: 1 | Q48: =360*S48 -> 720 | R48: =Q48*P48*O48 -> 1440 | S48: 2 | T48: 2649.86 | U48: =T48*S48 -> 5299.72 | V48: 0.15 | W48: =T48-T48*V48 -> 2252.381 | X48: =U48*(1-V48) -> 4504.762 | Y48: =X48*0.95 -> 4279.5239 | Z48: 252578 | AA48: =R48 -> 1440 | AB48: =X48/(AA48+AA49) -> 0.85317462 | AC48: =X48/(AA48+AA49)*1000 -> 853.17462 | AD48: MOSAICO
B49: 12084 | C49: CE | D49: FORTALEZA | E49: 2304400 | F49: WE SUPER OOH | G49: 13.045.189/0005-70 | H49: MEDIA WALL FORTALEZA - COTA PREMIUM | I49: PAINEL ELETRÔNICO | J49: MENSAL PROPORCIONAL | K49: VIAS DE ALTO FLUXO | L49: 10" | M49: 46219 | N49: =M49+O49-1 -> 46220 | O49: 2 | P49: 1 | Q49: =960*S49 -> 1920 | R49: =Q49*P49*O49 -> 3840 | S49: 2 | T49: 15558 | U49: =T49*S49 -> 31116 | V49: 0.15 | W49: =T49-T49*V49 -> 13224.3 | X49: =U49*(1-V49) -> 26448.6 | Y49: =X49*0.95 -> 25126.17 | Z49: 252578 | AA49: =R49 -> 3840 | AB49: =X49/(AA49+AA50) -> 4.2385577 | AC49: =X49/(AA49+AA50)*1000 -> 4238.5577 | AD49: MOSAICO
B50: 87254 | C50: CE | D50: FORTALEZA | E50: 2304400 | F50: LED MAIS | G50: 28.507.808/0001-89 | H50: AV. DOM LUÍS ESQ. R. BARBOSA DE FREITAS PROX. SHOPPING ALDEOTA | I50: PAINEL ELETRÔNICO | J50: MENSAL PROPORCIONAL | K50: VIAS DE ALTO FLUXO | L50: 10" | M50: 46219 | N50: =M50+O50-1 -> 46220 | O50: 2 | P50: 1 | Q50: 1200 | R50: =Q50*P50*O50 -> 2400 | S50: 1 | T50: 4.65 | U50: =T50*R50 -> 11160 | V50: 0.25 | W50: =T50-T50*V50 -> 3.4875 | X50: =U50*(1-V50) -> 8370 | Y50: =X50*0.95 -> 7951.5 | Z50: - | AA50: =R50 -> 2400 | AB50: - | AC50: - | AD50: G2
B51: 87254 | C51: CE | D51: FORTALEZA | E51: 2304400 | F51: LED MAIS | G51: 28.507.808/0001-89 | H51: AV. SANTOS DUMONT ESQ. COM A AV. VIRGÍLIO TÁVORA | I51: PAINEL ELETRÔNICO | J51: MENSAL PROPORCIONAL | K51: VIAS DE ALTO FLUXO | L51: 10" | M51: 46219 | N51: =M51+O51-1 -> 46220 | O51: 2 | P51: 1 | Q51: 1200 | R51: =Q51*P51*O51 -> 2400 | S51: 1 | T51: 4.65 | U51: =T51*R51 -> 11160 | V51: 0.25 | W51: =T51-T51*V51 -> 3.4875 | X51: =U51*(1-V51) -> 8370 | Y51: =X51*0.95 -> 7951.5 | Z51: - | AA51: =R51 -> 2400 | AB51: - | AC51: - | AD51: G2
B52: 104346 | C52: CE | D52: FORTALEZA | E52: 2304400 | F52: URB | G52: 13.517.365/0001-30 | H52: PAINEIS DE LEDS FORTALEZA | I52: PAINEL ELETRÔNICO | J52: MENSAL PROPORCIONAL | K52: VIAS DE ALTO FLUXO | L52: 10" | M52: 46219 | N52: =M52+O52-1 -> 46220 | O52: 2 | P52: 26 | Q52: 230 | R52: =Q52*P52*O52 -> 11960 | S52: 1 | T52: 1466.67 | U52: =T52*P52 -> 38133.42 | V52: 0.2 | W52: =T52-T52*V52 -> 1173.336 | X52: =U52*(1-V52) -> 30506.736 | Y52: =X52*0.95 -> 28981.399 | Z52: - | AA52: =R52 -> 11960 | AB52: - | AC52: - | AD52: DIRETO
B53: 104346 | C53: CE | D53: FORTALEZA | E53: 2304400 | F53: URB | G53: 13.517.365/0001-30 | H53: PAINEL DE FORTALEZA - Av. Washington Soares - Empena Iguatemi Bosque | I53: PAINEL ELETRÔNICO | J53: MENSAL PROPORCIONAL | K53: VIAS DE ALTO FLUXO | L53: 10" | M53: 46219 | N53: =M53+O53-1 -> 46220 | O53: 2 | P53: 1 | Q53: 230 | R53: =Q53*P53*O53 -> 460 | S53: 1 | T53: 13933.33 | U53: =T53*P53 -> 13933.33 | V53: 0.2 | W53: =T53-T53*V53 -> 11146.664 | X53: =U53*(1-V53) -> 11146.664 | Y53: =X53*0.95 -> 10589.331 | Z53: - | AA53: =R53 -> 460 | AB53: - | AC53: - | AD53: DIRETO
B54: 67263 | C54: CE | D54: FORTALEZA | E54: 2304400 | F54: PLAN PAINÉIS | G54: 13.517.365/0001-30 | H54: Av. Virgílio Távora próximo a esquina da Av. Dom Luiz Face voltada para a Av. Dom Luiz | I54: PAINEL ELETRÔNICO | J54: PERÍODO | K54: VIAS DE ALTO FLUXO | L54: 10" | M54: 46219 | N54: =M54+O54-1 -> 46220 | O54: 2 | P54: 1 | Q54: 360 | R54: =Q54*P54*O54 -> 720 | S54: 1 | T54: =8125/7*O54 -> 2321.4286 | U54: =T54*S54 -> 2321.4286 | V54: 0.1 | W54: =T54-T54*V54 -> 2089.2857 | X54: =U54*(1-V54) -> 2089.2857 | Y54: =X54*0.95 -> 1984.8214 | Z54: - | AA54: =R54 -> 720 | AB54: - | AC54: - | AD54: DIRETO
B55: 67263 | C55: CE | D55: FORTALEZA | E55: 2304400 | F55: PLAN PAINÉIS | G55: 13.517.365/0001-30 | H55: Av. Santos Dumont com Av. Rui Barbosa (Mc Donalds) | I55: PAINEL ELETRÔNICO | J55: PERÍODO | K55: VIAS DE ALTO FLUXO | L55: 10" | M55: 46219 | N55: =M55+O55-1 -> 46220 | O55: 2 | P55: 1 | Q55: 360 | R55: =Q55*P55*O55 -> 720 | S55: 1 | T55: =9125/7*O55 -> 2607.1429 | U55: =T55*S55 -> 2607.1429 | V55: 0.1 | W55: =T55-T55*V55 -> 2346.4286 | X55: =U55*(1-V55) -> 2346.4286 | Y55: =X55*0.95 -> 2229.1071 | Z55: - | AA55: =R55 -> 720 | AB55: - | AC55: - | AD55: DIRETO
B56: TOTAL - CEARÁ | P56: =SUBTOTAL(9,P34:P55) -> 47 | R56: =SUBTOTAL(9,R34:R55) -> 67940 | X56: =SUBTOTAL(9,X34:X55) -> 231530.38 | Y56: =SUBTOTAL(9,Y34:Y55) -> 219953.86 | AC56: =AVERAGE(AC34:AC55)*1.5 -> 569.51991
B57: 104346 | C57: AM | D57: MANAUS | E57: 1302603 | F57: URB | G57: 50.608.858/0001-01 | H57: PAINEIS DE LEDS MANAUS | I57: PAINEL ELETRÔNICO | J57: MENSAL PROPORCIONAL | K57: VIAS DE ALTO FLUXO | L57: 10" | M57: 46219 | N57: =M57+O57-1 -> 46220 | O57: 2 | P57: 4 | Q57: 486 | R57: =Q57*P57*O57 -> 3888 | S57: 1 | T57: 1694 | U57: =T57*P57 -> 6776 | V57: 0.2 | W57: =T57-T57*V57 -> 1355.2 | X57: =U57*(1-V57) -> 5420.8 | Y57: =X57*0.95 -> 5149.76 | Z57: 120000 | AA57: =Z57*O57 -> 240000 | AB57: =X57/(AA57+AA59) -> 0.022519109 | AC57: =X57/(AA57+AA59)*1000 -> 22.519109 | AD57: DIRETO
B58: 67263 | C58: AM | D58: MANAUS | E58: 1302603 | F58: PLAN PAINÉIS | G58: 13.517.365/0001-30 | H58: Av. André Araújo - Pátio da TV Band | I58: PAINEL ELETRÔNICO | J58: PERÍODO | K58: VIAS DE ALTO FLUXO | L58: 10" | M58: 46219 | N58: =M58+O58-1 -> 46220 | O58: 2 | P58: 1 | Q58: 360 | R58: =Q58*P58*O58 -> 720 | S58: 1 | T58: =15625/7*O58 -> 4464.2857 | U58: =T58*S58 -> 4464.2857 | V58: 0.1 | W58: =T58-T58*V58 -> 4017.8571 | X58: =U58*(1-V58) -> 4017.8571 | Y58: =X58*0.95 -> 3816.9643 | Z58: - | AA58: =R58 -> 720 | AB58: - | AC58: - | AD58: DIRETO
B59: 67263 | C59: AM | D59: MANAUS | E59: 1302603 | F59: PLAN PAINÉIS | G59: 13.517.365/0001-30 | H59: Av. Djalma Batista - Próximo ao amazonas Shopping e Arena da Amazônia | I59: PAINEL ELETRÔNICO | J59: PERÍODO | K59: VIAS DE ALTO FLUXO | L59: 10" | M59: 46219 | N59: =M59+O59-1 -> 46220 | O59: 2 | P59: 1 | Q59: 360 | R59: =Q59*P59*O59 -> 720 | S59: 1 | T59: =15625/7*O59 -> 4464.2857 | U59: =T59*S59 -> 4464.2857 | V59: 0.1 | W59: =T59-T59*V59 -> 4017.8571 | X59: =U59*(1-V59) -> 4017.8571 | Y59: =X59*0.95 -> 3816.9643 | Z59: - | AA59: =R59 -> 720 | AB59: - | AC59: - | AD59: DIRETO
B60: 67263 | C60: AM | D60: MANAUS | E60: 1302603 | F60: PLAN PAINÉIS | G60: 13.517.365/0001-30 | H60: Av. Efigênio Salles - No Clube da AOB | I60: PAINEL ELETRÔNICO | J60: PERÍODO | K60: VIAS DE ALTO FLUXO | L60: 10" | M60: 46219 | N60: =M60+O60-1 -> 46220 | O60: 2 | P60: 1 | Q60: 360 | R60: =Q60*P60*O60 -> 720 | S60: 1 | T60: =15625/7*O60 -> 4464.2857 | U60: =T60*S60 -> 4464.2857 | V60: 0.1 | W60: =T60-T60*V60 -> 4017.8571 | X60: =U60*(1-V60) -> 4017.8571 | Y60: =X60*0.95 -> 3816.9643 | Z60: - | AA60: =R60 -> 720 | AB60: - | AC60: - | AD60: DIRETO
B61: 67263 | C61: AM | D61: MANAUS | E61: 1302603 | F61: PLAN PAINÉIS | G61: 13.517.365/0001-30 | H61: Rua Maceió - Pátio da Comemore | I61: PAINEL ELETRÔNICO | J61: PERÍODO | K61: VIAS DE ALTO FLUXO | L61: 10" | M61: 46219 | N61: =M61+O61-1 -> 46220 | O61: 2 | P61: 1 | Q61: 360 | R61: =Q61*P61*O61 -> 720 | S61: 1 | T61: =15625/7*O61 -> 4464.2857 | U61: =T61*S61 -> 4464.2857 | V61: 0.1 | W61: =T61-T61*V61 -> 4017.8571 | X61: =U61*(1-V61) -> 4017.8571 | Y61: =X61*0.95 -> 3816.9643 | Z61: - | AA61: =R61 -> 720 | AB61: - | AC61: - | AD61: DIRETO
B62: 92163 | C62: AM | D62: MANAUS | E62: 1302603 | F62: ALTERNAMIDIA | G62: 06.154.881/0001-81 | H62: AVENIDA MAXTEIXEIRA,EMFRENTE ACAA-HOME CENTER | I62: PAINEL ELETRÔNICO | J62: MENSAL PROPORCIONAL | K62: VIAS DE ALTO FLUXO | L62: 10" | M62: 46219 | N62: =M62+O62-1 -> 46220 | O62: 2 | P62: 1 | Q62: 600 | R62: =Q62*P62*O62 -> 1200 | S62: 1 | T62: 11485.71 | U62: =T62*S62 -> 11485.71 | V62: 0.26 | W62: =T62-T62*V62 -> 8499.4254 | X62: =U62*(1-V62) -> 8499.4254 | Y62: =X62*0.95 -> 8074.4541 | Z62: - | AA62: =R62 -> 1200 | AB62: - | AC62: - | AD62: DIRETO
B63: 92163 | C63: AM | D63: MANAUS | E63: 1302603 | F63: ALTERNAMIDIA | G63: 06.154.881/0001-81 | H63: AVENIDAAUTAZMIRIM,EM FRENTEANORTEAUTOPEÇAS-AUTAZ MIRIM | I63: PAINEL ELETRÔNICO | J63: MENSAL PROPORCIONAL | K63: VIAS DE ALTO FLUXO | L63: 10" | M63: 46219 | N63: =M63+O63-1 -> 46220 | O63: 2 | P63: 1 | Q63: 600 | R63: =Q63*P63*O63 -> 1200 | S63: 1 | T63: 11485.71 | U63: =T63*S63 -> 11485.71 | V63: 0.26 | W63: =T63-T63*V63 -> 8499.4254 | X63: =U63*(1-V63) -> 8499.4254 | Y63: =X63*0.95 -> 8074.4541 | Z63: - | AA63: =R63 -> 1200 | AB63: - | AC63: - | AD63: DIRETO
B64: 92163 | C64: AM | D64: MANAUS | E64: 1302603 | F64: ALTERNAMIDIA | G64: 06.154.881/0001-81 | H64: AVENIDATANCREDONEVES, EMFRENTEAOLIFE PARQUE 10 | I64: PAINEL ELETRÔNICO | J64: MENSAL PROPORCIONAL | K64: VIAS DE ALTO FLUXO | L64: 10" | M64: 46219 | N64: =M64+O64-1 -> 46220 | O64: 2 | P64: 1 | Q64: 600 | R64: =Q64*P64*O64 -> 1200 | S64: 1 | T64: 11485.71 | U64: =T64*S64 -> 11485.71 | V64: 0.26 | W64: =T64-T64*V64 -> 8499.4254 | X64: =U64*(1-V64) -> 8499.4254 | Y64: =X64*0.95 -> 8074.4541 | Z64: - | AA64: =R64 -> 1200 | AB64: - | AC64: - | AD64: DIRETO
B65: TOTAL - AMAZONAS | P65: =SUBTOTAL(9,P57:P64) -> 11 | R65: =SUBTOTAL(9,R57:R64) -> 10368 | X65: =SUBTOTAL(9,X57:X64) -> 46990.505 | Y65: =SUBTOTAL(9,Y57:Y64) -> 44640.98 | AC65: =AVERAGE(AC57:AC64)*1.5 -> 33.778664
B66: 24874 | C66: MG | D66: BELO HORIZONTE | E66: 3106200 | F66: DMIDIA | G66: 12.291.445/0001-57 | H66: Av. Raja Gabaglia, 4697 - Santa Lúcia | I66: PAINEL ELETRÔNICO | J66: MENSAL PROPORCIONAL | K66: VIAS DE ALTO FLUXO | L66: 10" | M66: 46219 | N66: =M66+O66-1 -> 46220 | O66: 2 | P66: 1 | Q66: =540*4 -> 2160 | R66: =Q66*P66*O66 -> 4320 | S66: 1 | T66: 2.794312 | U66: =T66*R66 -> 12071.428 | V66: 0.59 | W66: =T66-T66*V66 -> 1.1456679 | X66: =U66*(1-V66) -> 4949.2854 | Y66: =X66*0.95 -> 4701.8211 | Z66: 74000 | AA66: =R66 -> 4320 | AB66: =X66/(AA66) -> 1.1456679 | AC66: =X66/(AA66)*1000 -> 1145.6679 | AD66: BI GROUP
B67: 24874 | C67: MG | D67: BELO HORIZONTE | E67: 3106200 | F67: DMIDIA | G67: 12.291.445/0001-57 | H67: Av. Raja Gabaglia, 1595 - Luxemburgo | I67: PAINEL ELETRÔNICO | J67: MENSAL PROPORCIONAL | K67: VIAS DE ALTO FLUXO | L67: 10" | M67: 46219 | N67: =M67+O67-1 -> 46220 | O67: 2 | P67: 1 | Q67: =540*4 -> 2160 | R67: =Q67*P67*O67 -> 4320 | S67: 1 | T67: 2.794312 | U67: =T67*R67 -> 12071.428 | V67: 0.59 | W67: =T67-T67*V67 -> 1.1456679 | X67: =U67*(1-V67) -> 4949.2854 | Y67: =X67*0.95 -> 4701.8211 | Z67: 73000 | AA67: =R67 -> 4320 | AB67: =X67/(AA67) -> 1.1456679 | AC67: =X67/(AA67)*1000 -> 1145.6679 | AD67: BI GROUP
B68: 24874 | C68: MG | D68: BELO HORIZONTE | E68: 3106200 | F68: DMIDIA | G68: 12.291.445/0001-57 | H68: Av. Barão Homem de Melo, 2184 - Estóril | I68: PAINEL ELETRÔNICO | J68: MENSAL PROPORCIONAL | K68: VIAS DE ALTO FLUXO | L68: 10" | M68: 46219 | N68: =M68+O68-1 -> 46220 | O68: 2 | P68: 1 | Q68: =540*4 -> 2160 | R68: =Q68*P68*O68 -> 4320 | S68: 1 | T68: 2.794312 | U68: =T68*R68 -> 12071.428 | V68: 0.59 | W68: =T68-T68*V68 -> 1.1456679 | X68: =U68*(1-V68) -> 4949.2854 | Y68: =X68*0.95 -> 4701.8211 | Z68: 68500 | AA68: =R68 -> 4320 | AB68: =X68/(AA68) -> 1.1456679 | AC68: =X68/(AA68)*1000 -> 1145.6679 | AD68: BI GROUP
B69: 24874 | C69: MG | D69: BELO HORIZONTE | E69: 3106200 | F69: DMIDIA | G69: 12.291.445/0001-57 | H69: Via Expressa/Tereza Cristina, 3535 - Calafate | I69: PAINEL ELETRÔNICO | J69: MENSAL PROPORCIONAL | K69: VIAS DE ALTO FLUXO | L69: 10" | M69: 46219 | N69: =M69+O69-1 -> 46220 | O69: 2 | P69: 1 | Q69: =540*4 -> 2160 | R69: =Q69*P69*O69 -> 4320 | S69: 1 | T69: 2.794312 | U69: =T69*R69 -> 12071.428 | V69: 0.59 | W69: =T69-T69*V69 -> 1.1456679 | X69: =U69*(1-V69) -> 4949.2854 | Y69: =X69*0.95 -> 4701.8211 | Z69: 74000 | AA69: =R69 -> 4320 | AB69: =X69/(AA69) -> 1.1456679 | AC69: =X69/(AA69)*1000 -> 1145.6679 | AD69: BI GROUP
B70: 24874 | C70: MG | D70: BELO HORIZONTE | E70: 3106200 | F70: DMIDIA | G70: 12.291.445/0001-57 | H70: Av. Cristiano Machado, 3411 - União | I70: PAINEL ELETRÔNICO | J70: MENSAL PROPORCIONAL | K70: VIAS DE ALTO FLUXO | L70: 10" | M70: 46219 | N70: =M70+O70-1 -> 46220 | O70: 2 | P70: 1 | Q70: =540*4 -> 2160 | R70: =Q70*P70*O70 -> 4320 | S70: 1 | T70: 2.794312 | U70: =T70*R70 -> 12071.428 | V70: 0.59 | W70: =T70-T70*V70 -> 1.1456679 | X70: =U70*(1-V70) -> 4949.2854 | Y70: =X70*0.95 -> 4701.8211 | Z70: 88500 | AA70: =R70 -> 4320 | AB70: =X70/(AA70) -> 1.1456679 | AC70: =X70/(AA70)*1000 -> 1145.6679 | AD70: BI GROUP
B71: 24874 | C71: MG | D71: BELO HORIZONTE | E71: 3106200 | F71: DMIDIA | G71: 12.291.445/0001-57 | H71: Av. Dom Pedro I, 1705 - Santa Branca | I71: PAINEL ELETRÔNICO | J71: MENSAL PROPORCIONAL | K71: VIAS DE ALTO FLUXO | L71: 10" | M71: 46219 | N71: =M71+O71-1 -> 46220 | O71: 2 | P71: 1 | Q71: =540*4 -> 2160 | R71: =Q71*P71*O71 -> 4320 | S71: 1 | T71: 2.794312 | U71: =T71*R71 -> 12071.428 | V71: 0.59 | W71: =T71-T71*V71 -> 1.1456679 | X71: =U71*(1-V71) -> 4949.2854 | Y71: =X71*0.95 -> 4701.8211 | Z71: 75000 | AA71: =R71 -> 4320 | AB71: =X71/(AA71) -> 1.1456679 | AC71: =X71/(AA71)*1000 -> 1145.6679 | AD71: BI GROUP
B72: 24874 | C72: MG | D72: BELO HORIZONTE | E72: 3106200 | F72: DMIDIA | G72: 12.291.445/0001-57 | H72: Av. Dom Pedro II, 3715 - Padre Eustaquio | I72: PAINEL ELETRÔNICO | J72: MENSAL PROPORCIONAL | K72: VIAS DE ALTO FLUXO | L72: 10" | M72: 46219 | N72: =M72+O72-1 -> 46220 | O72: 2 | P72: 1 | Q72: =540*4 -> 2160 | R72: =Q72*P72*O72 -> 4320 | S72: 1 | T72: 2.794312 | U72: =T72*R72 -> 12071.428 | V72: 0.59 | W72: =T72-T72*V72 -> 1.1456679 | X72: =U72*(1-V72) -> 4949.2854 | Y72: =X72*0.95 -> 4701.8211 | Z72: 46000 | AA72: =R72 -> 4320 | AB72: =X72/(AA72) -> 1.1456679 | AC72: =X72/(AA72)*1000 -> 1145.6679 | AD72: BI GROUP
B73: 71857 | C73: MG | D73: BELO HORIZONTE | E73: 3106200 | F73: DOORS | G73: 18.796.645/0001-48 | H73: Avenida Raja Gabáglia, 350 - Circulo Militar, próximo a avenida do contorno - Duplo sentido - Belo Horizonte - MG | I73: PAINEL ELETRÔNICO | J73: MENSAL PROPORCIONAL | K73: VIAS DE ALTO FLUXO | L73: 10" | M73: 46219 | N73: =M73+O73-1 -> 46220 | O73: 2 | P73: 1 | Q73: 800 | R73: =Q73*P73*O73 -> 1600 | S73: 1 | T73: 2.9 | U73: =T73*R73 -> 4640 | V73: 0.2 | W73: =T73-T73*V73 -> 2.32 | X73: =U73*(1-V73) -> 3712 | Y73: =X73*0.95 -> 3526.4 | Z73: 4700595 | AA73: =R73 -> 1600 | AB73: =X73/(AA73) -> 2.32 | AC73: =X73/(AA73)*1000 -> 2320 | AD73: DUE V
B74: 71857 | C74: MG | D74: BELO HORIZONTE | E74: 3106200 | F74: DOORS | G74: 18.796.645/0001-48 | H74: Avenida Raja Gabáglia, 1.201 - Proximo ao hospital Madre Tereza, Sentido Diamond Mall - Belo Horizonte - MG | I74: PAINEL ELETRÔNICO | J74: MENSAL PROPORCIONAL | K74: VIAS DE ALTO FLUXO | L74: 10" | M74: 46219 | N74: =M74+O74-1 -> 46220 | O74: 2 | P74: 1 | Q74: 800 | R74: =Q74*P74*O74 -> 1600 | S74: 1 | T74: 2.9 | U74: =T74*R74 -> 4640 | V74: 0.2 | W74: =T74-T74*V74 -> 2.32 | X74: =U74*(1-V74) -> 3712 | Y74: =X74*0.95 -> 3526.4 | Z74: 4700595 | AA74: =R74 -> 1600 | AB74: =X74/(AA74) -> 2.32 | AC74: =X74/(AA74)*1000 -> 2320 | AD74: DUE V
B75: 71857 | C75: MG | D75: BELO HORIZONTE | E75: 3106200 | F75: DOORS | G75: 18.796.645/0001-48 | H75: Av. Afonso Pena, 3.328 - Na Praça Milton Campos, Esq. Com Avenida do Contorno– Belo Horizonte - MG | I75: PAINEL ELETRÔNICO | J75: MENSAL PROPORCIONAL | K75: VIAS DE ALTO FLUXO | L75: 10" | M75: 46219 | N75: =M75+O75-1 -> 46220 | O75: 2 | P75: 1 | Q75: 800 | R75: =Q75*P75*O75 -> 1600 | S75: 1 | T75: 2.9 | U75: =T75*R75 -> 4640 | V75: 0.2 | W75: =T75-T75*V75 -> 2.32 | X75: =U75*(1-V75) -> 3712 | Y75: =X75*0.95 -> 3526.4 | Z75: 4700595 | AA75: =R75 -> 1600 | AB75: =X75/(AA75) -> 2.32 | AC75: =X75/(AA75)*1000 -> 2320 | AD75: DUE V
B76: 71857 | C76: MG | D76: BELO HORIZONTE | E76: 3106200 | F76: DOORS | G76: 18.796.645/0001-48 | H76: Avenida Prudente de Morais, 697 – Esq. com Rua Carlos Gomes, Sentido Bairro – Belo Horizonte - MG | I76: PAINEL ELETRÔNICO | J76: MENSAL PROPORCIONAL | K76: VIAS DE ALTO FLUXO | L76: 10" | M76: 46219 | N76: =M76+O76-1 -> 46220 | O76: 2 | P76: 1 | Q76: 800 | R76: =Q76*P76*O76 -> 1600 | S76: 1 | T76: 2.9 | U76: =T76*R76 -> 4640 | V76: 0.2 | W76: =T76-T76*V76 -> 2.32 | X76: =U76*(1-V76) -> 3712 | Y76: =X76*0.95 -> 3526.4 | Z76: 4700595 | AA76: =R76 -> 1600 | AB76: =X76/(AA76) -> 2.32 | AC76: =X76/(AA76)*1000 -> 2320 | AD76: DUE V
B77: 71857 | C77: MG | D77: BELO HORIZONTE | E77: 3106200 | F77: DOORS | G77: 18.796.645/0001-48 | H77: Avenida Cristiano Machado, 4101 – Em Frente ao Minas Shopping – Sentido Centro – Belo Horizonte - MG | I77: PAINEL ELETRÔNICO | J77: MENSAL PROPORCIONAL | K77: VIAS DE ALTO FLUXO | L77: 10" | M77: 46219 | N77: =M77+O77-1 -> 46220 | O77: 2 | P77: 1 | Q77: 800 | R77: =Q77*P77*O77 -> 1600 | S77: 1 | T77: 2.9 | U77: =T77*R77 -> 4640 | V77: 0.2 | W77: =T77-T77*V77 -> 2.32 | X77: =U77*(1-V77) -> 3712 | Y77: =X77*0.95 -> 3526.4 | Z77: 4700595 | AA77: =R77 -> 1600 | AB77: =X77/(AA77+AA82) -> 0.98723404 | AC77: =X77/(AA77+AA82)*1000 -> 987.23404 | AD77: DUE V
B78: 71857 | C78: MG | D78: BELO HORIZONTE | E78: 3106200 | F78: DOORS | G78: 18.796.645/0001-48 | H78: Avenida Presidente Carlos Luz, 4213 – Ao lado da Usiminas e em frente a UFMG, Sentido Pampulha – Belo Horizonte - MG | I78: PAINEL ELETRÔNICO | J78: MENSAL PROPORCIONAL | K78: VIAS DE ALTO FLUXO | L78: 10" | M78: 46219 | N78: =M78+O78-1 -> 46220 | O78: 2 | P78: 1 | Q78: 800 | R78: =Q78*P78*O78 -> 1600 | S78: 1 | T78: 2.9 | U78: =T78*R78 -> 4640 | V78: 0.2 | W78: =T78-T78*V78 -> 2.32 | X78: =U78*(1-V78) -> 3712 | Y78: =X78*0.95 -> 3526.4 | Z78: 4700595 | AA78: =R78 -> 1600 | AB78: =X78/(AA78+AA83) -> 0.98723404 | AC78: =X78/(AA78+AA83)*1000 -> 987.23404 | AD78: DUE V
B79: 71857 | C79: MG | D79: BELO HORIZONTE | E79: 3106200 | F79: DOORS | G79: 18.796.645/0001-48 | H79: Avenida dos Andradas, 3520 – Santa Efigênia, próximo ao Shopping Boulevard – Belo Horizonte - MG | I79: PAINEL ELETRÔNICO | J79: MENSAL PROPORCIONAL | K79: VIAS DE ALTO FLUXO | L79: 10" | M79: 46219 | N79: =M79+O79-1 -> 46220 | O79: 2 | P79: 1 | Q79: 800 | R79: =Q79*P79*O79 -> 1600 | S79: 1 | T79: 2.9 | U79: =T79*R79 -> 4640 | V79: 0.2 | W79: =T79-T79*V79 -> 2.32 | X79: =U79*(1-V79) -> 3712 | Y79: =X79*0.95 -> 3526.4 | Z79: 4700595 | AA79: =R79 -> 1600 | AB79: =X79/(AA79+AA84) -> 2.32 | AC79: =X79/(AA79+AA84)*1000 -> 2320 | AD79: DUE V
B80: 71857 | C80: MG | D80: BELO HORIZONTE | E80: 3106200 | F80: DOORS | G80: 18.796.645/0001-48 | H80: Avenida Presidente Carlos Luz, 1205 – Em frente ao Cemitério da Paz, Sentido Centro – Belo Horizonte - MG | I80: PAINEL ELETRÔNICO | J80: MENSAL PROPORCIONAL | K80: VIAS DE ALTO FLUXO | L80: 10" | M80: 46219 | N80: =M80+O80-1 -> 46220 | O80: 2 | P80: 1 | Q80: 800 | R80: =Q80*P80*O80 -> 1600 | S80: 1 | T80: 2.9 | U80: =T80*R80 -> 4640 | V80: 0.2 | W80: =T80-T80*V80 -> 2.32 | X80: =U80*(1-V80) -> 3712 | Y80: =X80*0.95 -> 3526.4 | Z80: 4700595 | AA80: =R80 -> 1600 | AB80: =X80/(AA80+AA85) -> 0.030392847 | AC80: =X80/(AA80+AA85)*1000 -> 30.392847 | AD80: DUE V
B81: 71857 | C81: MG | D81: BELO HORIZONTE | E81: 3106200 | F81: DOORS | G81: 18.796.645/0001-48 | H81: Avenida Antônio Carlos, 1694 – Próximo ao Hospital Belo Horizonte, Sentido Centro – Belo Horizonte - MG | I81: PAINEL ELETRÔNICO | J81: MENSAL PROPORCIONAL | K81: VIAS DE ALTO FLUXO | L81: 10" | M81: 46219 | N81: =M81+O81-1 -> 46220 | O81: 2 | P81: 1 | Q81: 800 | R81: =Q81*P81*O81 -> 1600 | S81: 1 | T81: 2.9 | U81: =T81*R81 -> 4640 | V81: 0.2 | W81: =T81-T81*V81 -> 2.32 | X81: =U81*(1-V81) -> 3712 | Y81: =X81*0.95 -> 3526.4 | Z81: 4700595 | AA81: =R81 -> 1600 | AB81: =X81/(AA81+AA86) -> 0.02473941 | AC81: =X81/(AA81+AA86)*1000 -> 24.73941 | AD81: DUE V
B82: 92163 | C82: MG | D82: BELO HORIZONTE | E82: 3106200 | F82: ALTERNAMIDIA | G82: 06.154.881/0001-81 | H82: AVENIDA DE MORAIS ESQUINA COM RUACARLOS GOMES SENTIDOBAIRRO COBETURA:CIDADE JARDIM,SANTOANTÔNIO, LUXEMBURGOE SANTALÚCIA | I82: PAINEL ELETRÔNICO | J82: MENSAL PROPORCIONAL | K82: VIAS DE ALTO FLUXO | L82: 10" | M82: 46219 | N82: =M82+O82-1 -> 46220 | O82: 2 | P82: 1 | Q82: 1080 | R82: =Q82*P82*O82 -> 2160 | S82: 1 | T82: 11485.71 | U82: =T82*S82 -> 11485.71 | V82: 0.26 | W82: =T82-T82*V82 -> 8499.4254 | X82: =U82*(1-V82) -> 8499.4254 | Y82: =X82*0.95 -> 8074.4541 | Z82: - | AA82: =R82 -> 2160 | AB82: - | AC82: - | AD82: DIRETO
B83: 92163 | C83: MG | D83: BELO HORIZONTE | E83: 3106200 | F83: ALTERNAMIDIA | G83: 06.154.881/0001-81 | H83: COBERTURA:PAMPULHA,OUROPRETOE CASTELO | I83: PAINEL ELETRÔNICO | J83: MENSAL PROPORCIONAL | K83: VIAS DE ALTO FLUXO | L83: 10" | M83: 46219 | N83: =M83+O83-1 -> 46220 | O83: 2 | P83: 1 | Q83: 1080 | R83: =Q83*P83*O83 -> 2160 | S83: 1 | T83: 11485.71 | U83: =T83*S83 -> 11485.71 | V83: 0.26 | W83: =T83-T83*V83 -> 8499.4254 | X83: =U83*(1-V83) -> 8499.4254 | Y83: =X83*0.95 -> 8074.4541 | Z83: - | AA83: =R83 -> 2160 | AB83: - | AC83: - | AD83: DIRETO
B84: TOTAL - MINAS GERAIS | P84: =SUBTOTAL(9,P66:P81) -> 16 | R84: =SUBTOTAL(9,R66:R81) -> 44640 | X84: =SUBTOTAL(9,X66:X81) -> 68052.998 | Y84: =SUBTOTAL(9,Y66:Y83) -> 80799.256 | AC84: =AVERAGE(AC66:AC81)*1.5 -> 2029.6196
B85: 85885 | C85: DF | D85: BRASÍLIA | E85: 5300108 | F85: TRAFFIC LED | G85: 48.306.123/0001-81 | H85: EPAR (DF047) SAIDA DO AEROPORTO, SENTIDO LAGO SUL E AREA CENTRAL DE BRASILIA, PROXIMO AO BALAO | I85: PAINEL ELETRÔNICO | J85: MENSAL PROPORCIONAL | K85: VIAS DE ALTO FLUXO | L85: 15" | M85: 46219 | N85: =M85+O85-1 -> 46220 | O85: 2 | P85: 1 | Q85: 420 | R85: =Q85*P85*O85 -> 840 | S85: 1 | T85: 1.69 | U85: =T85*R85 -> 1419.6 | V85: 0.35 | W85: =T85-T85*V85 -> 1.0985 | X85: =U85*(1-V85) -> 922.74 | Y85: =X85*0.95 -> 876.603 | Z85: 60267 | AA85: =Z85*O85 -> 120534 | AB85: =X85/(AA85) -> 0.0076554333 | AC85: =X85/(AA85)*1000 -> 7.6554333 | AD85: DIRETO
B86: 85885 | C86: DF | D86: BRASÍLIA | E86: 5300108 | F86: TRAFFIC LED | G86: 48.306.123/0001-81 | H86: VIA L4 SUL PRÓXIMO A UNIEURO SENTIDO PLANO PILOTO | I86: PAINEL ELETRÔNICO | J86: MENSAL PROPORCIONAL | K86: VIAS DE ALTO FLUXO | L86: 15" | M86: 46219 | N86: =M86+O86-1 -> 46220 | O86: 2 | P86: 1 | Q86: 420 | R86: =Q86*P86*O86 -> 840 | S86: 1 | T86: 1.69 | U86: =T86*R86 -> 1419.6 | V86: 0.35 | W86: =T86-T86*V86 -> 1.0985 | X86: =U86*(1-V86) -> 922.74 | Y86: =X86*0.95 -> 876.603 | Z86: 74222 | AA86: =Z86*O86 -> 148444 | AB86: =X86/(AA86) -> 0.0062160815 | AC86: =X86/(AA86)*1000 -> 6.2160815 | AD86: DIRETO
B87: 85885 | C87: DF | D87: BRASÍLIA | E87: 5300108 | F87: TRAFFIC LED | G87: 48.306.123/0001-81 | H87: DF 009, APÓS A PONTE DO BRAGUETO, ENTRADA PARA O LAGO NORTE | I87: PAINEL ELETRÔNICO | J87: MENSAL PROPORCIONAL | K87: VIAS DE ALTO FLUXO | L87: 15" | M87: 46219 | N87: =M87+O87-1 -> 46220 | O87: 2 | P87: 1 | Q87: 420 | R87: =Q87*P87*O87 -> 840 | S87: 1 | T87: 1.69 | U87: =T87*R87 -> 1419.6 | V87: 0.35 | W87: =T87-T87*V87 -> 1.0985 | X87: =U87*(1-V87) -> 922.74 | Y87: =X87*0.95 -> 876.603 | Z87: 113436 | AA87: =Z87*O87 -> 226872 | AB87: =X87/(AA87) -> 0.0040672273 | AC87: =X87/(AA87)*1000 -> 4.0672273 | AD87: DIRETO
B88: 85885 | C88: DF | D88: BRASÍLIA | E88: 5300108 | F88: TRAFFIC LED | G88: 48.306.123/0001-81 | H88: EPDB (DF025), PRÓXIMO AO GILBERTO SALOMÃO, SENTIDO HOSPITAL DAHER | I88: PAINEL ELETRÔNICO | J88: MENSAL PROPORCIONAL | K88: VIAS DE ALTO FLUXO | L88: 15" | M88: 46219 | N88: =M88+O88-1 -> 46220 | O88: 2 | P88: 1 | Q88: 420 | R88: =Q88*P88*O88 -> 840 | S88: 1 | T88: 1.69 | U88: =T88*R88 -> 1419.6 | V88: 0.35 | W88: =T88-T88*V88 -> 1.0985 | X88: =U88*(1-V88) -> 922.74 | Y88: =X88*0.95 -> 876.603 | Z88: 76199 | AA88: =Z88*O88 -> 152398 | AB88: =X88/(AA88) -> 0.0060548039 | AC88: =X88/(AA88)*1000 -> 6.0548039 | AD88: DIRETO
B89: 85885 | C89: DF | D89: BRASÍLIA | E89: 5300108 | F89: TRAFFIC LED | G89: 48.306.123/0001-81 | H89: EPAR (DF047) SENTIDO CHEGANDO AO AEROPORTO INTERNACIONAL DE BRASILIA | I89: PAINEL ELETRÔNICO | J89: MENSAL PROPORCIONAL | K89: VIAS DE ALTO FLUXO | L89: 15" | M89: 46219 | N89: =M89+O89-1 -> 46220 | O89: 2 | P89: 1 | Q89: 420 | R89: =Q89*P89*O89 -> 840 | S89: 1 | T89: 1.69 | U89: =T89*R89 -> 1419.6 | V89: 0.35 | W89: =T89-T89*V89 -> 1.0985 | X89: =U89*(1-V89) -> 922.74 | Y89: =X89*0.95 -> 876.603 | Z89: 56259 | AA89: =Z89*O89 -> 112518 | AB89: =X89/(AA89) -> 0.0082008212 | AC89: =X89/(AA89)*1000 -> 8.2008212 | AD89: DIRETO
B90: 85885 | C90: DF | D90: BRASÍLIA | E90: 5300108 | F90: TRAFFIC LED | G90: 48.306.123/0001-81 | H90: EPAR (DF047) SENTIDO AEROPORTO PARA AREA CENTRAL DE BRASILIA, ANTES DO ACESSO AO TUNEL | I90: PAINEL ELETRÔNICO | J90: MENSAL PROPORCIONAL | K90: VIAS DE ALTO FLUXO | L90: 15" | M90: 46219 | N90: =M90+O90-1 -> 46220 | O90: 2 | P90: 1 | Q90: 420 | R90: =Q90*P90*O90 -> 840 | S90: 1 | T90: 1.69 | U90: =T90*R90 -> 1419.6 | V90: 0.35 | W90: =T90-T90*V90 -> 1.0985 | X90: =U90*(1-V90) -> 922.74 | Y90: =X90*0.95 -> 876.603 | Z90: 56259 | AA90: =Z90*O90 -> 112518 | AB90: =X90/(AA90) -> 0.0082008212 | AC90: =X90/(AA90)*1000 -> 8.2008212 | AD90: DIRETO
B91: 85885 | C91: DF | D91: BRASÍLIA | E91: 5300108 | F91: TRAFFIC LED | G91: 48.306.123/0001-81 | H91: (DF051) SENTIDO GUARÁ PARA ASA SUL NO ACESSO AO ZOOLÓGICO | I91: PAINEL ELETRÔNICO | J91: MENSAL PROPORCIONAL | K91: VIAS DE ALTO FLUXO | L91: 15" | M91: 46219 | N91: =M91+O91-1 -> 46220 | O91: 2 | P91: 1 | Q91: 420 | R91: =Q91*P91*O91 -> 840 | S91: 1 | T91: 1.69 | U91: =T91*R91 -> 1419.6 | V91: 0.35 | W91: =T91-T91*V91 -> 1.0985 | X91: =U91*(1-V91) -> 922.74 | Y91: =X91*0.95 -> 876.603 | Z91: 95146 | AA91: =Z91*O91 -> 190292 | AB91: =X91/(AA91) -> 0.0048490741 | AC91: =X91/(AA91)*1000 -> 4.8490741 | AD91: DIRETO
B92: 85885 | C92: DF | D92: BRASÍLIA | E92: 5300108 | F92: TRAFFIC LED | G92: 48.306.123/0001-81 | H92: EPIA SUL (DF003) SENTIDO SIA PARA O PARKSHOPPING NA ENTRADA PARA O CARREFOUR E SHOPPING | I92: PAINEL ELETRÔNICO | J92: MENSAL PROPORCIONAL | K92: VIAS DE ALTO FLUXO | L92: 15" | M92: 46219 | N92: =M92+O92-1 -> 46220 | O92: 2 | P92: 1 | Q92: 420 | R92: =Q92*P92*O92 -> 840 | S92: 1 | T92: 1.69 | U92: =T92*R92 -> 1419.6 | V92: 0.35 | W92: =T92-T92*V92 -> 1.0985 | X92: =U92*(1-V92) -> 922.74 | Y92: =X92*0.95 -> 876.603 | Z92: 84598 | AA92: =Z92*O92 -> 169196 | AB92: =X92/(AA92) -> 0.005453675 | AC92: =X92/(AA92)*1000 -> 5.453675 | AD92: DIRETO
B93: 85885 | C93: DF | D93: BRASÍLIA | E93: 5300108 | F93: TRAFFIC LED | G93: 48.306.123/0001-81 | H93: EPIG SENTIDO SUDOESTE PARA O SAI, ALTURA DA OCTOGONAL ANTES DO VIADUTO DE ACESSO A EPIA | I93: PAINEL ELETRÔNICO | J93: MENSAL PROPORCIONAL | K93: VIAS DE ALTO FLUXO | L93: 15" | M93: 46219 | N93: =M93+O93-1 -> 46220 | O93: 2 | P93: 1 | Q93: 420 | R93: =Q93*P93*O93 -> 840 | S93: 1 | T93: 1.69 | U93: =T93*R93 -> 1419.6 | V93: 0.35 | W93: =T93-T93*V93 -> 1.0985 | X93: =U93*(1-V93) -> 922.74 | Y93: =X93*0.95 -> 876.603 | Z93: 86797 | AA93: =Z93*O93 -> 173594 | AB93: =X93/(AA93) -> 0.0053155063 | AC93: =X93/(AA93)*1000 -> 5.3155063 | AD93: DIRETO
B94: 85885 | C94: DF | D94: BRASÍLIA | E94: 5300108 | F94: TRAFFIC LED | G94: 48.306.123/0001-81 | H94: EPTG, SENTIDO SIA PARA TAGUATINGA, ANTES DA ENTRADA DO GUARÁ | I94: PAINEL ELETRÔNICO | J94: MENSAL PROPORCIONAL | K94: VIAS DE ALTO FLUXO | L94: 15" | M94: 46219 | N94: =M94+O94-1 -> 46220 | O94: 2 | P94: 1 | Q94: 420 | R94: =Q94*P94*O94 -> 840 | S94: 1 | T94: 1.69 | U94: =T94*R94 -> 1419.6 | V94: 0.35 | W94: =T94-T94*V94 -> 1.0985 | X94: =U94*(1-V94) -> 922.74 | Y94: =X94*0.95 -> 876.603 | Z94: 106471 | AA94: =Z94*O94 -> 212942 | AB94: =X94/(AA94) -> 0.0043332926 | AC94: =X94/(AA94)*1000 -> 4.3332926 | AD94: DIRETO
B95: 85885 | C95: DF | D95: BRASÍLIA | E95: 5300108 | F95: TRAFFIC LED | G95: 48.306.123/0001-81 | H95: PISTÃO SUL, SAÍDA DA EPTG FRENTE AO CONDOMÍNIO PENÍSULA | I95: PAINEL ELETRÔNICO | J95: MENSAL PROPORCIONAL | K95: VIAS DE ALTO FLUXO | L95: 15" | M95: 46219 | N95: =M95+O95-1 -> 46220 | O95: 2 | P95: 1 | Q95: 420 | R95: =Q95*P95*O95 -> 840 | S95: 1 | T95: 1.69 | U95: =T95*R95 -> 1419.6 | V95: 0.35 | W95: =T95-T95*V95 -> 1.0985 | X95: =U95*(1-V95) -> 922.74 | Y95: =X95*0.95 -> 876.603 | Z95: 127622 | AA95: =Z95*O95 -> 255244 | AB95: =X95/(AA95) -> 0.0036151291 | AC95: =X95/(AA95)*1000 -> 3.6151291 | AD95: DIRETO
B96: 85885 | C96: DF | D96: BRASÍLIA | E96: 5300108 | F96: TRAFFIC LED | G96: 48.306.123/0001-81 | H96: EPAA SENTIDO SETOR MILITAR URBANO PARA O AUTODROMO | I96: PAINEL ELETRÔNICO | J96: MENSAL PROPORCIONAL | K96: VIAS DE ALTO FLUXO | L96: 15" | M96: 46219 | N96: =M96+O96-1 -> 46220 | O96: 2 | P96: 1 | Q96: 420 | R96: =Q96*P96*O96 -> 840 | S96: 1 | T96: 1.69 | U96: =T96*R96 -> 1419.6 | V96: 0.35 | W96: =T96-T96*V96 -> 1.0985 | X96: =U96*(1-V96) -> 922.74 | Y96: =X96*0.95 -> 876.603 | Z96: 59502 | AA96: =Z96*O96 -> 119004 | AB96: =X96/(AA96) -> 0.007753857 | AC96: =X96/(AA96)*1000 -> 7.753857 | AD96: DIRETO
B97: 85885 | C97: DF | D97: BRASÍLIA | E97: 5300108 | F97: TRAFFIC LED | G97: 48.306.123/0001-81 | H97: (DF003) EPIA SUL FRENTE AO PARKSHOOPPING SENTIDO SIA | I97: PAINEL ELETRÔNICO | J97: MENSAL PROPORCIONAL | K97: VIAS DE ALTO FLUXO | L97: 15" | M97: 46219 | N97: =M97+O97-1 -> 46220 | O97: 2 | P97: 1 | Q97: 420 | R97: =Q97*P97*O97 -> 840 | S97: 1 | T97: 1.69 | U97: =T97*R97 -> 1419.6 | V97: 0.35 | W97: =T97-T97*V97 -> 1.0985 | X97: =U97*(1-V97) -> 922.74 | Y97: =X97*0.95 -> 876.603 | Z97: 65560 | AA97: =Z97*O97 -> 131120 | AB97: =X97/(AA97) -> 0.0070373703 | AC97: =X97/(AA97)*1000 -> 7.0373703 | AD97: DIRETO
B98: 74941 | C98: DF | D98: BRASÍLIA | E98: 5300108 | F98: LEDME | G98: 53.565.965/0001-98 | H98: DF-009 (Entrada do Lago Norte) | I98: PAINEL ELETRÔNICO | J98: MENSAL PROPORCIONAL | K98: VIAS DE ALTO FLUXO | L98: 10" | M98: 46219 | N98: =M98+O98-1 -> 46220 | O98: 2 | P98: 1 | Q98: 360 | R98: =Q98*P98*O98 -> 720 | S98: 2 | T98: =10548/10*O98*S98 -> 4219.2 | U98: =T98 -> 4219.2 | V98: 0.18 | W98: =T98-T98*V98 -> 3459.744 | X98: =U98*(1-V98) -> 3459.744 | Y98: =X98*0.95 -> 3286.7568 | Z98: 100000 | AA98: =Z98*O98 -> 200000 | AB98: =X98/(AA98+AA99) -> 0.0078630545 | AC98: =X98/(AA98+AA99)*1000 -> 7.8630545 | AD98: DIRETO
B99: 74941 | C99: DF | D99: BRASÍLIA | E99: 5300108 | F99: LEDME | G99: 53.565.965/0001-98 | H99: DF-075 (Saída principal EPNB) | I99: PAINEL ELETRÔNICO | J99: MENSAL PROPORCIONAL | K99: VIAS DE ALTO FLUXO | L99: 10" | M99: 46219 | N99: =M99+O99-1 -> 46220 | O99: 2 | P99: 1 | Q99: 420 | R99: =Q99*P99*O99 -> 840 | S99: 2 | T99: =20160/10*O99*S99 -> 8064 | U99: =T99 -> 8064 | V99: 0.18 | W99: =T99-T99*V99 -> 6612.48 | X99: =U99*(1-V99) -> 6612.48 | Y99: =X99*0.95 -> 6281.856 | Z99: 120000 | AA99: =Z99*O99 -> 240000 | AB99: =X99/(AA99+AA100) -> 0.013776 | AC99: =X99/(AA99+AA100)*1000 -> 13.776 | AD99: DIRETO
B100: 74941 | C100: DF | D100: BRASÍLIA | E100: 5300108 | F100: LEDME | G100: 53.565.965/0001-98 | H100: DF-011 (EPIG/EPTG) | I100: PAINEL ELETRÔNICO | J100: MENSAL PROPORCIONAL | K100: VIAS DE ALTO FLUXO | L100: 10" | M100: 46219 | N100: =M100+O100-1 -> 46220 | O100: 2 | P100: 1 | Q100: 420 | R100: =Q100*P100*O100 -> 840 | S100: 2 | T100: =20160/10*O100*S100 -> 8064 | U100: =T100 -> 8064 | V100: 0.18 | W100: =T100-T100*V100 -> 6612.48 | X100: =U100*(1-V100) -> 6612.48 | Y100: =X100*0.95 -> 6281.856 | Z100: 120000 | AA100: =Z100*O100 -> 240000 | AB100: =X100/(AA100+AA101) -> 0.017401263 | AC100: =X100/(AA100+AA101)*1000 -> 17.401263 | AD100: DIRETO
B101: 74941 | C101: DF | D101: BRASÍLIA | E101: 5300108 | F101: LEDME | G101: 53.565.965/0001-98 | H101: DF-047 (Acesso ao Eixão Sul) - The Curve 2D | I101: PAINEL ELETRÔNICO | J101: MENSAL PROPORCIONAL | K101: VIAS DE ALTO FLUXO | L101: 15" | M101: 46219 | N101: =M101+O101-1 -> 46220 | O101: 2 | P101: 1 | Q101: 720 | R101: =Q101*P101*O101 -> 1440 | S101: 2 | T101: =103572/10*O101*S101 -> 41428.8 | U101: =T101 -> 41428.8 | V101: 0.18 | W101: =T101-T101*V101 -> 33971.616 | X101: =U101*(1-V101) -> 33971.616 | Y101: =X101*0.95 -> 32273.035 | Z101: 70000 | AA101: =Z101*O101 -> 140000 | AB101: =X101/(AA101+AA102) -> 0.23856472 | AC101: =X101/(AA101+AA102)*1000 -> 238.56472 | AD101: DIRETO
B102: 87254 | C102: DF | D102: BRASÍLIA | E102: 5300108 | F102: LED MAIS | G102: 28.507.808/0001-89 | H102: QS 410 CONJUTNO L LOTE 1 LOJA 03 - SAMAMBAIA NORTE - DF | I102: PAINEL ELETRÔNICO | J102: MENSAL PROPORCIONAL | K102: VIAS DE ALTO FLUXO | L102: 10" | M102: 46219 | N102: =M102+O102-1 -> 46220 | O102: 2 | P102: 1 | Q102: 1200 | R102: =Q102*P102*O102 -> 2400 | S102: 1 | T102: 4.65 | U102: =T102*R102 -> 11160 | V102: 0.25 | W102: =T102-T102*V102 -> 3.4875 | X102: =U102*(1-V102) -> 8370 | Y102: =X102*0.95 -> 7951.5 | Z102: - | AA102: =R102 -> 2400 | AB102: - | AC102: - | AD102: G2
B103: 107541 | C103: DF | D103: BRASÍLIA | E103: 5300108 | F103: MLA MIDIA | G103: 52.008.394/0001-28 | H103: BRASILIA CEILÄNDIA SUL QNN 30 | I103: PAINEL ELETRÔNICO | J103: MENSAL PROPORCIONAL | K103: VIAS DE ALTO FLUXO | L103: 15" | M103: 46219 | N103: =M103+O103-1 -> 46220 | O103: 2 | P103: 1 | Q103: 2100 | R103: =Q103*P103*O103 -> 4200 | S103: 1 | T103: 5.4 | U103: =T103*R103 -> 22680 | V103: 0.66 | W103: =T103-T103*V103 -> 1.836 | X103: =U103*(1-V103) -> 7711.2 | Y103: =X103*0.95 -> 7325.64 | Z103: 70000 | AA103: =R103 -> 4200 | AB103: =X103/(AA103+AA112) -> 0.94039024 | AC103: =X103/(AA103+AA112)*1000 -> 940.39024 | AD103: DIRETO
B104: 107541 | C104: DF | D104: BRASÍLIA | E104: 5300108 | F104: MLA MIDIA | G104: 52.008.394/0001-28 | H104: BRASILIA EPTG KM 65 | I104: PAINEL ELETRÔNICO | J104: MENSAL PROPORCIONAL | K104: VIAS DE ALTO FLUXO | L104: 15" | M104: 46219 | N104: =M104+O104-1 -> 46220 | O104: 2 | P104: 1 | Q104: 2100 | R104: =Q104*P104*O104 -> 4200 | S104: 1 | T104: 5.4 | U104: =T104*R104 -> 22680 | V104: 0.66 | W104: =T104-T104*V104 -> 1.836 | X104: =U104*(1-V104) -> 7711.2 | Y104: =X104*0.95 -> 7325.64 | Z104: 70000 | AA104: =R104 -> 4200 | AB104: =X104/(AA104+AA113) -> 0.037762977 | AC104: =X104/(AA104+AA113)*1000 -> 37.762977 | AD104: DIRETO
...

Sheet DOOH - TERMINAL RODOVIÁRIO
B2: PROGRAMAÇÃO - DOOH TERMINAL RODOVIÁRIO
B4: =CAPA!D4 -> MINISTÉRIO DA EDUCAÇÃO
B5: =CAPA!D6 -> FIES 2026
B6: =CAPA!D8 -> JULHO DE 2026
B8: IDENTIFICADOR SISTEMA | C8: UF | D8: PRAÇA | E8: CÓD MUNICÍPIO | F8: VEÍCULO | G8: CNPJ | H8: LOCAL | I8: FORMATO | M8: PERÍODO DE VEICULAÇÃO | P8: QTD DE FACES | Q8: QTD. INS DIA | R8: TT. INS.PERÍODO | S8: QTD DE COTAS CONTRATADAS | T8: VALOR TABELA | V8: DESC. % | W8: VALOR NEGOCIADO | Y8: VALOR DESEMBOLSO 95% | Z8: COBERTURA (FLUXO) | AA8: PERÍODO | AB8: IMPACTO PERÍODO | AC8: FONTE | AD8: CPM | AE8: CPI | AF8: REPRESENTANTE
I9: TIPO | J9: TIPO DE COMPRA | K9: AMBIENTE | L9: MATERIAL | M9: INICIAL | N9: FINAL | O9: TOTAL DE DIAS | T9: UNITÁRIO | U9: TOTAL | W9: UNITÁRIO | X9: TOTAL 100%
B11: 39969 | C11: BA | D11: SALVADOR | E11: 2927408 | F11: MOBILAPA | G11: 63.697.907/0001-71 | H11: COMBO DIGITAL - Circuito Monitores, Circuito Totens, Circuito Relógios, Circuito Standart, Circuito Premium. | I11: MÍDIA EM TERMINAL DE ÔNIBUS/RODOVIÁRIA/TRÊM | J11: PERÍODO | K11: TERMINAL RODOVIÁRIO | L11: 10" | M11: 46219 | N11: =M11+O11-1 -> 46220 | O11: 2 | P11: 52 | Q11: 228 | R11: =Q11*P11*O11 -> 23712 | S11: 1 | T11: =117800/7*O11 -> 33657.143 | U11: =T11*S11 -> 33657.143 | V11: 0.13 | W11: =T11-T11*V11 -> 29281.714 | X11: =U11*(1-V11) -> 29281.714 | Y11: =X11*0.95 -> 27817.629 | Z11: =630000*O11 -> 1260000 | AA11: DIA | AB11: =R11 -> 23712 | AC11: PRÓPRIA | AD11: =X11/(AB11)*1000 -> 1234.8901 | AE11: =X11/(AB11) -> 1.2348901 | AF11: BIGROUP
B12: 90488 | C12: BA | D12: SALVADOR | E12: 2927408 | F12: ALL 7 MIDIA | G12: 48.754.566/0001-35 | H12: CIRCUITO DIGITAL - ACESSO NORTE | I12: MÍDIA EM TERMINAL DE ÔNIBUS/RODOVIÁRIA/TRÊM | J12: PERÍODO | K12: TERMINAL RODOVIÁRIO | L12: 15" | M12: 46219 | N12: =M12+O12-1 -> 46220 | O12: 2 | P12: 7 | Q12: 480 | R12: =Q12*P12*O12 -> 6720 | S12: 1 | T12: =51340*0.6/15*O12 -> 4107.2 | U12: =T12*S12 -> 4107.2 | V12: 0.1 | W12: =T12-T12*V12 -> 3696.48 | X12: =U12*(1-V12) -> 3696.48 | Y12: =X12*0.95 -> 3511.656 | Z12: - | AA12: DIA | AB12: =R12 -> 6720 | AC12: PRÓPRIA | AD12: =X12/(AB12+AB13)*1000 -> 256.7 | AE12: =X12/(AB12) -> 0.55007143 | AF12: MOSAICO
B13: 90488 | C13: BA | D13: SALVADOR | E13: 2927408 | F13: ALL 7 MIDIA | G13: 48.754.566/0001-35 | H13: CIRCUITO DIGITAL - PIRAJÁ | I13: MÍDIA EM TERMINAL DE ÔNIBUS/RODOVIÁRIA/TRÊM | J13: PERÍODO | K13: TERMINAL RODOVIÁRIO | L13: 15" | M13: 46219 | N13: =M13+O13-1 -> 46220 | O13: 2 | P13: 8 | Q13: 480 | R13: =Q13*P13*O13 -> 7680 | S13: 1 | T13: =30350*0.6/15*O13 -> 2428 | U13: =T13*S13 -> 2428 | V13: 0.1 | W13: =T13-T13*V13 -> 2185.2 | X13: =U13*(1-V13) -> 2185.2 | Y13: =X13*0.95 -> 2075.94 | Z13: - | AA13: DIA | AB13: =R13 -> 7680 | AC13: PRÓPRIA | AD13: =X13/(AB13+AB15)*1000 -> 103.46591 | AE13: =X13/(AB13) -> 0.28453125 | AF13: MOSAICO
B14: 90488 | C14: BA | D14: SALVADOR | E14: 2927408 | F14: ALL 7 MIDIA | G14: 48.754.566/0001-35 | H14: CIRCUITO DIGITAL - ÁGUAS CLARAS | I14: MÍDIA EM TERMINAL DE ÔNIBUS/RODOVIÁRIA/TRÊM | J14: PERÍODO | K14: TERMINAL RODOVIÁRIO | L14: 15" | M14: 46219 | N14: =M14+O14-1 -> 46220 | O14: 2 | P14: 20 | Q14: 480 | R14: =Q14*P14*O14 -> 19200 | S14: 1 | T14: =75700*0.6/15*O14 -> 6056 | U14: =T14*S14 -> 6056 | V14: 0.1 | W14: =T14-T14*V14 -> 5450.4 | X14: =U14*(1-V14) -> 5450.4 | Y14: =X14*0.95 -> 5177.88 | Z14: - | AA14: DIA | AB14: =R14 -> 19200 | AC14: PRÓPRIA | AD14: =X14/(AB14+AB15)*1000 -> 166.98529 | AE14: =X14/(AB14) -> 0.283875 | AF14: MOSAICO
B15: 90488 | C15: BA | D15: SALVADOR | E15: 2927408 | F15: ALL 7 MIDIA | G15: 48.754.566/0001-35 | H15: CIRCUITO DIGITAL - MUSSURUNGA | I15: MÍDIA EM TERMINAL DE ÔNIBUS/RODOVIÁRIA/TRÊM | J15: PERÍODO | K15: TERMINAL RODOVIÁRIO | L15: 15" | M15: 46219 | N15: =M15+O15-1 -> 46220 | O15: 2 | P15: 14 | Q15: 480 | R15: =Q15*P15*O15 -> 13440 | S15: 1 | T15: =52900*0.6/15*O15 -> 4232 | U15: =T15*S15 -> 4232 | V15: 0.1 | W15: =T15-T15*V15 -> 3808.8 | X15: =U15*(1-V15) -> 3808.8 | Y15: =X15*0.95 -> 3618.36 | Z15: - | AA15: DIA | AB15: =R15 -> 13440 | AC15: PRÓPRIA | AD15: =X15/(AB15+AB16)*1000 -> 132.25 | AE15: =X15/(AB15) -> 0.28339286 | AF15: MOSAICO
B16: 90488 | C16: BA | D16: SALVADOR | E16: 2927408 | F16: ALL 7 MIDIA | G16: 48.754.566/0001-35 | H16: CIRCUITO DIGITAL - AEROPORTO | I16: MÍDIA EM TERMINAL DE ÔNIBUS/RODOVIÁRIA/TRÊM | J16: PERÍODO | K16: TERMINAL RODOVIÁRIO | L16: 15" | M16: 46219 | N16: =M16+O16-1 -> 46220 | O16: 2 | P16: 16 | Q16: 480 | R16: =Q16*P16*O16 -> 15360 | S16: 1 | T16: =60700*0.6/15*O16 -> 4856 | U16: =T16*S16 -> 4856 | V16: 0.1 | W16: =T16-T16*V16 -> 4370.4 | X16: =U16*(1-V16) -> 4370.4 | Y16: =X16*0.95 -> 4151.88 | Z16: - | AA16: DIA | AB16: =R16 -> 15360 | AC16: PRÓPRIA | AD16: =X16/(AB16+AB17)*1000 -> 175.09615 | AE16: =X16/(AB16) -> 0.28453125 | AF16: MOSAICO
B17: 72799 | C17: BA | D17: SALVADOR | E17: 2927408 | F17: MIDI | G17: 35.798.903/0001-44 | H17: TERMINAL AEROPORTO | I17: MÍDIA EM TERMINAL DE ÔNIBUS/RODOVIÁRIA/TRÊM | J17: POR TELA | K17: TERMINAL RODOVIÁRIO | L17: 15" | M17: 46219 | N17: =M17+O17-1 -> 46220 | O17: 2 | P17: 4 | Q17: 1200 | R17: =Q17*P17*O17 -> 9600 | S17: 2 | T17: =140400*0.7/15*O17 -> 13104 | U17: =T17*S17 -> 26208 | V17: 0.1 | W17: =T17-T17*V17 -> 11793.6 | X17: =U17*(1-V17) -> 23587.2 | Y17: =X17*0.95 -> 22407.84 | Z17: =55000*O17 -> 110000 | AA17: DIA | AB17: =R17 -> 9600 | AC17: PRÓPRIA | AD17: =X17/(AB17+AB18)*1000 -> 1638 | AE17: =X17/(AB17) -> 2.457 | AF17: BIGROUP
B18: 72799 | C18: BA | D18: SALVADOR | E18: 2927408 | F18: MIDI | G18: 35.798.903/0001-44 | H18: TERMINAL RETIRO | I18: MÍDIA EM TERMINAL DE ÔNIBUS/RODOVIÁRIA/TRÊM | J18: POR TELA | K18: TERMINAL RODOVIÁRIO | L18: 15" | M18: 46219 | N18: =M18+O18-1 -> 46220 | O18: 2 | P18: 4 | Q18: 600 | R18: =Q18*P18*O18 -> 4800 | S18: 1 | T18: =140400*0.7/15*O18 -> 13104 | U18: =T18*S18 -> 13104 | V18: 0.1 | W18: =T18-T18*V18 -> 11793.6 | X18: =U18*(1-V18) -> 11793.6 | Y18: =X18*0.95 -> 11203.92 | Z18: =52000*O18 -> 104000 | AA18: DIA | AB18: =R18 -> 4800 | AC18: PRÓPRIA | AD18: =X18/(AB18+AB19)*1000 -> 1228.5 | AE18: =X18/(AB18) -> 2.457 | AF18: BIGROUP
B19: 72799 | C19: BA | D19: SALVADOR | E19: 2927408 | F19: MIDI | G19: 35.798.903/0001-44 | H19: TERMINAL ACESSO NORTE | I19: MÍDIA EM TERMINAL DE ÔNIBUS/RODOVIÁRIA/TRÊM | J19: POR TELA | K19: TERMINAL RODOVIÁRIO | L19: 15" | M19: 46219 | N19: 46223 | O19: 2 | P19: 2 | Q19: 1200 | R19: =Q19*P19*O19 -> 4800 | S19: 2 | T19: =140400*0.7/15*O19 -> 13104 | U19: =T19*S19 -> 26208 | V19: 0.1 | W19: =T19-T19*V19 -> 11793.6 | X19: =U19*(1-V19) -> 23587.2 | Y19: =X19*0.95 -> 22407.84 | Z19: =70000*O19 -> 140000 | AA19: DIA | AB19: =R19 -> 4800 | AC19: PRÓPRIA | AD19: =X19/(AB19+AB20)*1000 -> 2457 | AE19: =X19/(AB19) -> 4.914 | AF19: BIGROUP
B20: 72799 | C20: BA | D20: SALVADOR | E20: 2927408 | F20: MIDI | G20: 35.798.903/0001-44 | H20: TERMINAL PIRAJÁ | I20: MÍDIA EM TERMINAL DE ÔNIBUS/RODOVIÁRIA/TRÊM | J20: POR TELA | K20: TERMINAL RODOVIÁRIO | L20: 15" | M20: 46219 | N20: =M20+O20-1 -> 46220 | O20: 2 | P20: 4 | Q20: 600 | R20: =Q20*P20*O20 -> 4800 | S20: 1 | T20: =140400*0.7/15*O20 -> 13104 | U20: =T20*S20 -> 13104 | V20: 0.1 | W20: =T20-T20*V20 -> 11793.6 | X20: =U20*(1-V20) -> 11793.6 | Y20: =X20*0.95 -> 11203.92 | Z20: =140000*O20 -> 280000 | AA20: DIA | AB20: =R20 -> 4800 | AC20: PRÓPRIA | AD20: =X20/(AB20+AB21)*1000 -> 2457 | AE20: =X20/(AB20) -> 2.457 | AF20: BIGROUP
B21: TOTAL -BAHIA | R21: =SUBTOTAL(9,R11:R20) -> 110112 | X21: =SUBTOTAL(9,X11:X20) -> 119554.59 | Y21: =SUBTOTAL(9,Y11:Y20) -> 113576.86 | AD21: =AVERAGE(AD11:AD20)*1.5 -> 1477.4831
B22: 11699 | C22: RJ | D22: RIO DE JANEIRO | E22: 3304557 | F22: ONBUS | G22: 10.491.859/0001-02 | H22: TERMINAL ALVORADA - CIRCUITO SEQUENCIAL ALVORADA - 6 PICOLES / 1 AEREO | I22: MÍDIA EM TERMINAL DE ÔNIBUS/RODOVIÁRIA/TRÊM | J22: POR INSERÇÃO | K22: TERMINAL RODOVIÁRIO | L22: 15" | M22: 46219 | N22: 46223 | O22: 2 | P22: 1 | Q22: 1080 | R22: =Q22*P22*O22 -> 2160 | S22: 1 | T22: 3.53 | U22: =T22*R22 -> 7624.8 | V22: 0.25 | W22: =T22-T22*V22 -> 2.6475 | X22: =U22*(1-V22) -> 5718.6 | Y22: =X22*0.95 -> 5432.67 | Z22: =70000*O22 -> 140000 | AA22: DIA | AB22: =R22 -> 2160 | AC22: PRÓPRIA | AD22: =X22/(AB22+AB23)*1000 -> 1323.75 | AE22: =X22/(AB22) -> 2.6475 | AF22: MOSAICO
B23: 11699 | C23: RJ | D23: RIO DE JANEIRO | E23: 3304557 | F23: ONBUS | G23: 10.491.859/0001-02 | H23: TERMINAL PAULO PORTELA - TESTEIRA | I23: MÍDIA EM TERMINAL DE ÔNIBUS/RODOVIÁRIA/TRÊM | J23: POR INSERÇÃO | K23: TERMINAL RODOVIÁRIO | L23: 15" | M23: 46219 | N23: 46223 | O23: 2 | P23: 1 | Q23: 1080 | R23: =Q23*P23*O23 -> 2160 | S23: 1 | T23: 3.17 | U23: =T23*R23 -> 6847.2 | V23: 0.25 | W23: =T23-T23*V23 -> 2.3775 | X23: =U23*(1-V23) -> 5135.4 | Y23: =X23*0.945 -> 4852.953 | Z23: =70000*O23 -> 140000 | AA23: DIA | AB23: =R23 -> 2160 | AC23: PRÓPRIA | AD23: =X23/(AB23+AB24)*1000 -> 1188.75 | AE23: =X23/(AB23) -> 2.3775 | AF23: MOSAICO
B24: 11699 | C24: RJ | D24: RIO DE JANEIRO | E24: 3304557 | F24: ONBUS | G24: 10.491.859/0001-02 | H24: TERMINAL CAMPO GRANDE - TESTEIRA DUPLA DIGITAL | I24: MÍDIA EM TERMINAL DE ÔNIBUS/RODOVIÁRIA/TRÊM | J24: POR INSERÇÃO | K24: TERMINAL RODOVIÁRIO | L24: 15" | M24: 46219 | N24: =M24+O24-1 -> 46220 | O24: 2 | P24: 1 | Q24: 1080 | R24: =Q24*P24*O24 -> 2160 | S24: 1 | T24: 1.38 | U24: =T24*R24 -> 2980.8 | V24: 0.25 | W24: =T24-T24*V24 -> 1.035 | X24: =U24*(1-V24) -> 2235.6 | Y24: =X24*0.95 -> 2123.82 | Z24: =140000*O24 -> 280000 | AA24: DIA | AB24: =R24 -> 2160 | AC24: PRÓPRIA | AD24: =X24/(AB24+AB25)*1000 -> 517.5 | AE24: =X24/(AB24) -> 1.035 | AF24: MOSAICO
B25: 11699 | C25: RJ | D25: RIO DE JANEIRO | E25: 3304557 | F25: ONBUS | G25: 10.491.859/0001-02 | H25: TERMINAL CAMPO GRANDE - MEGA AEREA | I25: MÍDIA EM TERMINAL DE ÔNIBUS/RODOVIÁRIA/TRÊM | J25: POR INSERÇÃO | K25: TERMINAL RODOVIÁRIO | L25: 15" | M25: 46219 | N25: =M25+O25-1 -> 46220 | O25: 2 | P25: 1 | Q25: 1080 | R25: =Q25*P25*O25 -> 2160 | S25: 1 | T25: 1.84 | U25: =T25*R25 -> 3974.4 | V25: 0.25 | W25: =T25-T25*V25 -> 1.38 | X25: =U25*(1-V25) -> 2980.8 | Y25: =X25*0.945 -> 2816.856 | Z25: =140000*O25 -> 280000 | AA25: DIA | AB25: =R25 -> 2160 | AC25: PRÓPRIA | AD25: =X25/(AB25+AB26)*1000 -> 1380 | AE25: =X25/(AB25) -> 1.38 | AF25: MOSAICO
B26: TOTAL - RIO DE JANEIRO | R26: =SUBTOTAL(9,R22:R25) -> 8640 | X26: =SUBTOTAL(9,X22:X25) -> 16070.4 | Y26: =SUBTOTAL(9,Y22:Y25) -> 15226.299 | AD26: =AVERAGE(AD22:AD25)*1.5 -> 1653.75
B27: TOTAL GERAL | R27: =SUBTOTAL(9,R11:R26) -> 118752 | U27: =SUM(U11:U26) -> 155387.54 | X27: =SUBTOTAL(9,X11:X26) -> 135624.99 | Y27: =SUBTOTAL(9,Y11:Y26) -> 128803.16 | AB27: =SUM(AB11:AB26) -> 118752
B28: OBSERVAÇÃO:
B31: VEÍCULO | D31: QTD DE INSERÇÕES | E31: DADOS DE IMPACTO | F31: VALOR TABELA | G31: VALOR NEGOCIADO 100% | H31: VALOR DESEMBOLSO 95% | I31: RENTABILIDADE %
B32: MOBILAPA | D32: =SUMIF($F$11:$F$26,B32,$R$11:$R$26) -> 23712 | E32: =SUMIF($F$11:$F$26,B32,$AB$11:$AB$26) -> 23712 | F32: =SUMIF($F$11:$F$26,B32,$U$11:$U$26) -> 33657.143 | G32: =SUMIF($F$11:$F$26,B32,$X$11:$X$26) -> 29281.714 | H32: =G32*0.95 -> 27817.629 | I32: =1-H32/F32 -> 0.1735
B33: ALL 7 MIDIA | D33: =SUMIF($F$11:$F$26,B33,$R$11:$R$26) -> 62400 | E33: =SUMIF($F$11:$F$26,B33,$AB$11:$AB$26) -> 62400 | F33: =SUMIF($F$11:$F$26,B33,$U$11:$U$26) -> 21679.2 | G33: =SUMIF($F$11:$F$26,B33,$X$11:$X$26) -> 19511.28 | H33: =G33*0.95 -> 18535.716 | I33: =1-H33/F33 -> 0.145
B34: MIDI | D34: =SUMIF($F$11:$F$26,B34,$R$11:$R$26) -> 24000 | E34: =SUMIF($F$11:$F$26,B34,$AB$11:$AB$26) -> 24000 | F34: =SUMIF($F$11:$F$26,B34,$U$11:$U$26) -> 78624 | G34: =SUMIF($F$11:$F$26,B34,$X$11:$X$26) -> 70761.6 | H34: =G34*0.95 -> 67223.52 | I34: =1-H34/F34 -> 0.145
B35: ONBUS | D35: =SUMIF($F$11:$F$26,B35,$R$11:$R$26) -> 8640 | E35: =SUMIF($F$11:$F$26,B35,$AB$11:$AB$26) -> 8640 | F35: =SUMIF($F$11:$F$26,B35,$U$11:$U$26) -> 21427.2 | G35: =SUMIF($F$11:$F$26,B35,$X$11:$X$26) -> 16070.4 | H35: =G35*0.95 -> 15266.88 | I35: =1-H35/F35 -> 0.2875
D36: =SUM(D32:D35) -> 118752 | E36: =SUM(E32:E35) -> 118752 | F36: =SUM(F32:F35) -> 155387.54 | G36: =SUM(G32:G35) -> 135624.99 | H36: =SUM(H32:H35) -> 128843.74
B38: AGENCIA | D38: VALOR 100% | E38: VALOR 95%
B39: CALIA | D39: =SUMIF($A$11:$A$26,B39,$X$11:$X$26) -> 0 | E39: =D39*0.95 -> 0
B40: SA | D40: =SUMIF($A$11:$A$26,B40,$X$11:$X$26) -> 0 | E40: =D40*0.95 -> 0
B41: DE BRITO | D41: =SUMIF($A$11:$A$26,B41,$X$11:$X$26) -> 0 | E41: =D41*0.95 -> 0

Sheet INTERNET
B2: PROGRAMAÇÃO - INTERNET
B4: =RESUMO!C5 -> MINISTÉRIO DA EDUCAÇÃO
B5: =RESUMO!C6 -> FIES 2026
B6: =RESUMO!C7 -> JULHO DE 2026
B9: VEÍCULO | C9: CNPJ | D9: ID VEÍCULO | E9: SITUAÇÃO | F9: PI | G9: AÇÃO | H9: UF | I9: PRAÇA | J9: CATEGORIA | K9: CANAL/ SEGMENTAÇÃO | L9: FORMATO | M9: DIMENSÃO | N9: OBJETIVO | O9: KPIS | P9: ADSERVER | Q9: TIPO DE TAGUEAMENTO | R9: SECUNDAGEM COMPRADA | S9: AUDITORIA DE TERCEIROS | T9: PERÍODO | U9: QTD. | V9: TOTAL EXECUTADO | W9: TIPO DE COMPRA | X9: IMPRESSÕES ESTIMADAS POR DIÁRIA | Y9: VISIBILIDADE % | Z9: INVENTÁRIO PERÍODO | AA9: VALOR TABELA | AC9: NEG. % | AD9: ABATIMENTO | AF9: VALOR NEGOCIADO | AI9: HONORÁRIO (13%) | AJ9: VALOR DESEMBOLSO | AK9: LÍQUIDO PLATAFORMA (SEM IMPOSTO) | AL9: Impostos (ISS 2,9% + 9,25% Pis/Cofins) | AM9: % VEÍCULO | AN9: OBSERVAÇÕES | AO9: CONTATO
AA10: UNITÁRIO | AB10: TOTAL | AD10: VIEWABILITY % | AE10: VIEWABILITY/ BRAND SAFETY | AF10: UNITÁRIO | AG10: ABATIMENTO | AH10: TOTAL
B11: META | C11: 13.347.016/0001-17 | D11: 9424 | E11: EM APROVAÇÃO | H11: BR | I11: NACIONAL | J11: INOVADOR DIGITAL | K11: FACEBOOK/INSTAGRAM AS 25+ | L11: POST | N11: TRAFÉGO | O11: CLIQUES NO LINK | P11: Não | Q11: N/A | R11: N/A | S11: N/A | T11: 16/07 A 17/07/2026 | U11: 128000 | V11: =U11+AE11 -> 128000 | W11: CPC | AA11: 2 | AB11: =U11*AA11 -> 256000 | AC11: 0 | AF11: =AA11*(1-AC11) -> 2 | AH11: =U11*AF11 -> 256000 | AI11: =IF(OR(B11="META",B11="GOOGLE BRASIL"),AH11*13%,0) -> 33280 | AJ11: =IF(OR(B11="META",B11="GOOGLE BRASIL"),AH11+AI11,AH11*0.95) -> 289280 | AK11: =IF(OR(B11="META",B11="FACEBOOK",B11="INSTAGRAN"),AH11*0.8785,0) -> 224896 | AL11: =IF(OR(B11="META",B11="FACEBOOK",B11="INSTAGRAN"),AH11*0.1215,0) -> 31104
U12: =SUBTOTAL(9,U10:U11) -> 128000 | V12: =SUBTOTAL(9,V10:V11) -> 128000 | AB12: =SUBTOTAL(9,AB10:AB11) -> 256000 | AH12: =SUBTOTAL(9,AH10:AH11) -> 256000 | AJ12: =SUBTOTAL(9,AJ10:AJ11) -> 289280 | AM12: =AH12/$AH$32 -> 0.13960858
B13: TIK TOK | C13: 27.415.911/0001-36 | D13: 73732 | E13: EM APROVAÇÃO | H13: BR | I13: NACIONAL | J13: REDE SOCIAL | K13: AS 25+ | L13: INFEED AD | N13: TRAFÉGO | O13: CLIQUES NO LINK | P13: Não | Q13: N/A | R13: N/A | S13: N/A | T13: 16/07 A 17/07/2026 | U13: 171875 | V13: =U13+AE13 -> 171875 | W13: CPC | AA13: 1.2 | AB13: =U13*AA13 -> 206250 | AC13: 0 | AF13: =AA13*(1-AC13) -> 1.2 | AH13: =U13*AF13 -> 206250 | AI13: =IF(OR(B13="META",B13="GOOGLE BRASIL"),AH13*13%,0) -> 0 | AJ13: =IF(OR(B13="META",B13="GOOGLE BRASIL"),AH13+AI13,AH13*0.95) -> 195937.5 | AK13: =IF(OR(B13="META",B13="FACEBOOK",B13="INSTAGRAN"),AH13*0.8785,0) -> 0 | AL13: =IF(OR(B13="META",B13="FACEBOOK",B13="INSTAGRAN"),AH13*0.1215,0) -> 0
B14: TOTAL REDES SOCIAIS | U14: =SUBTOTAL(9,U13:U13) -> 171875 | V14: =SUBTOTAL(9,V13:V13) -> 171875 | AB14: =SUBTOTAL(9,AB13:AB13) -> 206250 | AH14: =SUBTOTAL(9,AH13:AH13) -> 206250 | AJ14: =SUBTOTAL(9,AJ13:AJ13) -> 195937.5 | AM14: =AH14/$AH$32 -> 0.11247762
B15: NEWCOM | C15: 46.698.419/0001-60 | D15: 82904 | E15: EM APROVAÇÃO | H15: BR | I15: NACIONAL | J15: REDE DE CONTEÚDO | K15: AS 18+ | L15: Display IAB | M15: 300x250 320x50 320x480 | N15: ALCANCE | O15: CPMA | ALCANCE | P15: Sim | Q15: N/A | R15: N/A | S15: N/A | T15: 16/07 A 17/07/2026 | U15: 2002561 | V15: =U15+AE15 -> 2002561 | W15: CPM | AA15: 110 | AB15: =U15*AA15/1000 -> 220281.71 | AC15: 0.2 | AF15: =AA15*(1-AC15) -> 88 | AH15: =AF15*U15/1000+(AG15) -> 176225.37 | AI15: =IF(OR(B15="META",B15="GOOGLE BRASIL"),AH15*13%,0) -> 0 | AJ15: =IF(OR(B15="META",B15="GOOGLE BRASIL"),AH15+AI15,AH15*0.95) -> 167414.1 | AK15: =IF(OR(B15="META",B15="FACEBOOK",B15="INSTAGRAN"),AH15*0.8785,0) -> 0 | AL15: =IF(OR(B15="META",B15="FACEBOOK",B15="INSTAGRAN"),AH15*0.1215,0) -> 0
B16: BAIHIVE | C16: 63.529.585/0001-51 | D16: 105049 | E16: EM APROVAÇÃO | H16: BR | I16: NACIONAL | J16: REDE DE CONTEÚDO | K16: AS 18+ | L16: Display IAB | M16: 728x90 300x250 320x100 300x600 | N16: ALCANCE | O16: CPMA | ALCANCE | P16: Sim | Q16: N/A | R16: N/A | S16: N/A | T16: 16/07 A 17/07/2026 | U16: 2351617 | V16: =U16+AE16 -> 2351617 | W16: CPM | AA16: 137.12 | AB16: =U16*AA16/1000 -> 322453.72 | AC16: 0.55 | AF16: =AA16*(1-AC16) -> 61.704 | AH16: =AF16*U16/1000+(AG16) -> 145104.18 | AI16: =IF(OR(B16="META",B16="GOOGLE BRASIL"),AH16*13%,0) -> 0 | AJ16: =IF(OR(B16="META",B16="GOOGLE BRASIL"),AH16+AI16,AH16*0.95) -> 137848.97 | AK16: =IF(OR(B16="META",B16="FACEBOOK",B16="INSTAGRAN"),AH16*0.8785,0) -> 0 | AL16: =IF(OR(B16="META",B16="FACEBOOK",B16="INSTAGRAN"),AH16*0.1215,0) -> 0
B17: MÍDIA MINDS | C17: 62.378.681/0001-83 | D17: 103498 | E17: EM APROVAÇÃO | H17: BR | I17: NACIONAL | J17: REDE DE CONTEÚDO | K17: AS 18+ | L17: Display IAB | M17: 300x250 300x600 728x90 320x480 | N17: ALCANCE | O17: CPMA | ALCANCE | P17: Sim | Q17: N/A | R17: N/A | S17: N/A | T17: 16/07 A 17/07/2026 | U17: 750546 | V17: =U17+AE17 -> 750546 | W17: CPM | AA17: 302.08 | AB17: 249.62 | AC17: 0.36 | AF17: =AA17*(1-AC17) -> 193.3312 | AH17: =AF17*U17/1000+(AG17) -> 145103.96 | AI17: =IF(OR(B17="META",B17="GOOGLE BRASIL"),AH17*13%,0) -> 0 | AJ17: =IF(OR(B17="META",B17="GOOGLE BRASIL"),AH17+AI17,AH17*0.95) -> 137848.76 | AK17: =IF(OR(B17="META",B17="FACEBOOK",B17="INSTAGRAN"),AH17*0.8785,0) -> 0 | AL17: =IF(OR(B17="META",B17="FACEBOOK",B17="INSTAGRAN"),AH17*0.1215,0) -> 0
B18: ADZEP | C18: 33.401.925/0001-01 | D18: 89383 | E18: EM APROVAÇÃO | H18: BR | I18: NACIONAL | J18: REDE DE CONTEÚDO | K18: AS 18+ | L18: Display IAB | M18: 970X90 728X90 320X100 320X50 | N18: ALCANCE | O18: CPMA | ALCANCE | P18: Sim | Q18: N/A | R18: N/A | S18: N/A | T18: 16/07 A 17/07/2026 | U18: 3903975 | V18: =U18+AE18 -> 3903975 | W18: CPM | AA18: 74 | AB18: 249.62 | AC18: 0.39 | AF18: =AA18*(1-AC18) -> 45.14 | AH18: =AF18*U18/1000+(AG18) -> 176225.43 | AI18: =IF(OR(B18="META",B18="GOOGLE BRASIL"),AH18*13%,0) -> 0 | AJ18: =IF(OR(B18="META",B18="GOOGLE BRASIL"),AH18+AI18,AH18*0.95) -> 167414.16 | AK18: =IF(OR(B18="META",B18="FACEBOOK",B18="INSTAGRAN"),AH18*0.8785,0) -> 0 | AL18: =IF(OR(B18="META",B18="FACEBOOK",B18="INSTAGRAN"),AH18*0.1215,0) -> 0
B19: ="TOTAL "&J17 -> TOTAL REDE DE CONTEÚDO | U19: =SUM(U15:U18) -> 9008699 | V19: =SUM(V15:V18) -> 9008699 | AB19: =SUM(AB15:AB18) -> 543234.67 | AH19: =SUM(AH15:AH18) -> 642658.93 | AJ19: =SUM(AJ15:AJ18) -> 610525.99 | AM19: =AH19/$AH$32 -> 0.35047149
B20: RANGE | C20: 44.579.378/0001-67 | D20: 79468 | E20: EM APROVAÇÃO | H20: BR | I20: NACIONAL | J20: REDE DE VÍDEO | K20: AS 18+ | L20: VÍDEO | M20: 640x480 480x640 | N20: RECONHECIMENTO | O20: VIEW COMPLETO | P20: Sim | Q20: N/A | R20: N/A | S20: N/A | T20: 16/07 A 17/07/2026 | U20: 180000 | V20: =U20+AE20 -> 180000 | W20: CPV | AA20: 1.2 | AB20: =U20*AA20 -> 216000 | AC20: 0.5 | AF20: =AA20*(1-AC20) -> 0.6 | AH20: =AF20*U20+(AG20) -> 108000 | AI20: =IF(OR(B20="META",B20="GOOGLE BRASIL"),AH20*13%,0) -> 0 | AJ20: =IF(OR(B20="META",B20="GOOGLE BRASIL"),AH20+AI20,AH20*0.95) -> 102600 | AK20: =IF(OR(B20="META",B20="FACEBOOK",B20="INSTAGRAN"),AH20*0.8785,0) -> 0 | AL20: =IF(OR(B20="META",B20="FACEBOOK",B20="INSTAGRAN"),AH20*0.1215,0) -> 0
B21: SIMPLEADS | C21: 26.775.512/0001-13 | D21: 44052 | E21: EM APROVAÇÃO | H21: BR | I21: NACIONAL | J21: REDE DE VÍDEO | K21: AS 18+ | Brasil Estudantes, Ensino Médio, ENEM, Ensino Superior Privado, Universidades e Faculdades, Financiamento Estudantil, FIES, Sem diploma de ensino superior, Renda familiar de até 3 salários mínimos per capita, Notícias e atualidades. | L21: BannerSimpleAds - Vídeo até 30" | M21: 1920x1080 | N21: RECONHECIMENTO | O21: VIEWABILITY - BRANDSAFETY - CTR - FREQUENCIA | P21: Sim | Q21: N/A | R21: N/A | S21: N/A | T21: 16/07 A 17/07/2026 | V21: =U21+AE21 -> 0 | W21: CPM | AA21: 125 | AB21: =U21*AA21/1000 -> 0 | AC21: 0.64 | AF21: =AA21*(1-AC21) -> 45 | AH21: =AF21*U21/1000+(AG21) -> 0 | AI21: =IF(OR(B21="META",B21="GOOGLE BRASIL"),AH21*13%,0) -> 0 | AJ21: =IF(OR(B21="META",B21="GOOGLE BRASIL"),AH21+AI21,AH21*0.95) -> 0 | AK21: =IF(OR(B21="META",B21="FACEBOOK",B21="INSTAGRAN"),AH21*0.8785,0) -> 0 | AL21: =IF(OR(B21="META",B21="FACEBOOK",B21="INSTAGRAN"),AH21*0.1215,0) -> 0
B22: ="TOTAL "&J20 -> TOTAL REDE DE VÍDEO | U22: =SUBTOTAL(9,U20:U21) -> 180000 | V22: =SUBTOTAL(9,V20:V21) -> 180000 | AB22: =SUBTOTAL(9,AB20:AB21) -> 216000 | AH22: =SUBTOTAL(9,AH20:AH21) -> 108000 | AJ22: =SUBTOTAL(9,AJ20:AJ21) -> 102600 | AM22: =AH22/$AH$32 -> 0.05889737
B23: CITTAMOBI | C23: 46.868.302/0001-87 | D23: 51260 | E23: EM APROVAÇÃO | H23: BR | I23: NACIONAL | J23: WI-FI | K23: AS 18+ | L23: Banner Previsão | M23: 320 x 50 | N23: ALCANCE | O23: CPMA | ALCANCE | P23: Sim | Q23: N/A | R23: N/A | S23: N/A | T23: 16/07 A 17/07/2026 | U23: 7395407 | V23: =U23+AE23 -> 7395407 | W23: CPM | AA23: 126.57 | AB23: =U23*AA23/1000 -> 936036.66 | AC23: 0.87 | AF23: =AA23*(1-AC23) -> 16.4541 | AH23: =AF23*U23/1000+(AG23) -> 121684.77 | AI23: =IF(OR(B23="META",B23="GOOGLE BRASIL"),AH23*13%,0) -> 0 | AJ23: =IF(OR(B23="META",B23="GOOGLE BRASIL"),AH23+AI23,AH23*0.95) -> 115600.53 | AK23: =IF(OR(B23="META",B23="FACEBOOK",B23="INSTAGRAN"),AH23*0.8785,0) -> 0 | AL23: =IF(OR(B23="META",B23="FACEBOOK",B23="INSTAGRAN"),AH23*0.1215,0) -> 0
B24: TOTAL APP MOBILIDADE | U24: =SUBTOTAL(9,U23:U23) -> 7395407 | V24: =SUBTOTAL(9,V23:V23) -> 7395407 | AB24: =SUM(AB23:AB23) -> 936036.66 | AH24: =SUBTOTAL(9,AH23:AH23) -> 121684.77 | AJ24: =SUBTOTAL(9,AJ23:AJ23) -> 115600.53 | AM24: =AH24/$AH$32 -> 0.066360302
B25: YOU TARGET | C25: 35.373.693/0001-42 | D25: 82344 | E25: EM APROVAÇÃO | H25: BR | I25: NACIONAL | J25: WI-FI | K25: AS 18+ | L25: Vídeo até 30" | M25: 1920x1080 | N25: RECONHECIMENTO | O25: VIEW COMPLETO | P25: Sim | Q25: N/A | R25: N/A | S25: N/A | T25: 16/07 A 17/07/2026 | U25: 20709 | V25: =U25+AE25 -> 20709 | W25: CPV | AA25: 14 | AB25: =U25*AA25 -> 289926 | AC25: 0.486 | AF25: =AA25*(1-AC25) -> 7.196 | AH25: =AF25*U25+(AG25) -> 149021.96 | AI25: =IF(OR(B25="META",B25="GOOGLE BRASIL"),AH25*13%,0) -> 0 | AJ25: =IF(OR(B25="META",B25="GOOGLE BRASIL"),AH25+AI25,AH25*0.95) -> 141570.87 | AK25: =IF(OR(B25="META",B25="FACEBOOK",B25="INSTAGRAN"),AH25*0.8785,0) -> 0 | AL25: =IF(OR(B25="META",B25="FACEBOOK",B25="INSTAGRAN"),AH25*0.1215,0) -> 0
B26: CONECTA BRASIL | C26: 22.295.219/0001-06 | D26: 104464 | E26: EM APROVAÇÃO | H26: BR | I26: NACIONAL | J26: WI-FI | K26: AS 18+ | L26: Infeed / Vídeos de até 60 segundos | M26: 1080x1550 | N26: RECONHECIMENTO | O26: VIEW COMPLETO | P26: Sim | Q26: N/A | R26: N/A | S26: N/A | T26: 16/07 A 17/07/2026 | U26: 12600 | V26: =U26+AE26 -> 12600 | W26: CPV | AA26: 9 | AB26: =U26*AA26 -> 113400 | AC26: 0.15 | AF26: =AA26*(1-AC26) -> 7.65 | AH26: =AF26*U26+(AG26) -> 96390 | AI26: =IF(OR(B26="META",B26="GOOGLE BRASIL"),AH26*13%,0) -> 0 | AJ26: =IF(OR(B26="META",B26="GOOGLE BRASIL"),AH26+AI26,AH26*0.95) -> 91570.5 | AK26: =IF(OR(B26="META",B26="FACEBOOK",B26="INSTAGRAN"),AH26*0.8785,0) -> 0 | AL26: =IF(OR(B26="META",B26="FACEBOOK",B26="INSTAGRAN"),AH26*0.1215,0) -> 0
B27: MFAY WI-FI | C27: 34.866.355/0001-80 | D27: 75166 | E27: EM APROVAÇÃO | H27: BR | I27: NACIONAL | J27: WI-FI | K27: AS 18+ | L27: Vídeo até 30" | M27: 1920x1080 | N27: RECONHECIMENTO | O27: VIEW COMPLETO | P27: Sim | Q27: N/A | R27: N/A | S27: N/A | T27: 16/07 A 17/07/2026 | U27: 23285 | V27: =U27+AE27 -> 23285 | W27: CPV | AA27: 8 | AB27: =U27*AA27 -> 186280 | AC27: 0.2 | AF27: =AA27*(1-AC27) -> 6.4 | AH27: =AF27*U27+(AG27) -> 149024 | AI27: =IF(OR(B27="META",B27="GOOGLE BRASIL"),AH27*13%,0) -> 0 | AJ27: =IF(OR(B27="META",B27="GOOGLE BRASIL"),AH27+AI27,AH27*0.95) -> 141572.8 | AK27: =IF(OR(B27="META",B27="FACEBOOK",B27="INSTAGRAN"),AH27*0.8785,0) -> 0 | AL27: =IF(OR(B27="META",B27="FACEBOOK",B27="INSTAGRAN"),AH27*0.1215,0) -> 0
B28: ="TOTAL "&#REF! -> #REF! | U28: =SUM(U25:U27) -> 56594 | V28: =SUM(V25:V27) -> 56594 | AB28: =SUM(AB25:AB27) -> 589606 | AH28: =SUM(AH25:AH27) -> 394435.96 | AI28: =SUM(AI25:AI26) -> 0 | AJ28: =SUM(AJ25:AJ27) -> 374714.17 | AM28: =AH28/$AH$32 -> 0.21510408
B29: TRIPLE A GAMES | C29: 44.292.443/0001-79 | D29: 91434 | E29: EM APROVAÇÃO | H29: BR | I29: NACIONAL | J29: GAMES | K29: AS 18+ | L29: Gamer ads | M29: 320x50 320x480 | N29: ALCANCE | O29: CPMA | ALCANCE | P29: Sim | Q29: N/A | R29: N/A | S29: N/A | T29: 16/07 A 17/07/2026 | U29: 5814918 | V29: =U29+AE29 -> 5814918 | W29: CPM | AA29: 30 | AB29: =U29*AA29/1000 -> 174447.54 | AC29: 0.4 | AF29: =AA29*(1-AC29) -> 18 | AH29: =AF29*U29/1000+(AG29) -> 104668.52 | AI29: =IF(OR(B29="META",B29="GOOGLE BRASIL"),AH29*13%,0) -> 0 | AJ29: =IF(OR(B29="META",B29="GOOGLE BRASIL"),AH29+AI29,AH29*0.95) -> 99435.098 | AK29: =IF(OR(B29="META",B29="FACEBOOK",B29="INSTAGRAN"),AH29*0.8785,0) -> 0 | AL29: =IF(OR(B29="META",B29="FACEBOOK",B29="INSTAGRAN"),AH29*0.1215,0) -> 0
B30: ="TOTAL "&J29 -> TOTAL GAMES | U30: =SUBTOTAL(9,U29:U29) -> 5814918 | V30: =SUBTOTAL(9,V29:V29) -> 5814918 | AB30: =SUBTOTAL(9,AB29:AB29) -> 174447.54 | AH30: =SUBTOTAL(9,AH29:AH29) -> 104668.52 | AJ30: =SUBTOTAL(9,AJ29:AJ29) -> 99435.098 | AM30: =AH30/$AH$32 -> 0.057080562
U32: =SUM(U30,U28,U24,U22,U19,U14,U12,) -> 22755493 | V32: =SUM(V30,V28,V24,V22,V19,V14,V12,) -> 22755493 | AB32: =SUM(AB30,AB28,AB24,AB22,AB19,AB14,AB12,) -> 2921574.9 | AH32: =SUM(AH30,AH28,AH24,AH22,AH19,AH14,AH12,) -> 1833698.2 | AJ32: =SUM(AJ30,AJ28,AJ24,AJ22,AJ19,AJ14,AJ12,) -> 1788093.3 | AM32: =SUBTOTAL(9,$AM$10:$AM$31) -> 1
B35: VEÍCULO | D35: VALOR 100% | E35: DESEMBOLSO 95%
B36: META | D36: =SUMIF($B$11:$B$30,B36,$AH$11:$AH$30) -> 256000 | E36: =SUMIF($B$11:$B$30,B36,$AJ$11:$AJ$30) -> 289280
B37: TIK TOK | D37: =SUMIF($B$11:$B$30,B37,$AH$11:$AH$30) -> 206250 | E37: =SUMIF($B$11:$B$30,B37,$AJ$11:$AJ$30) -> 195937.5
B38: NEWCOM | D38: =SUMIF($B$11:$B$30,B38,$AH$11:$AH$30) -> 176225.37 | E38: =SUMIF($B$11:$B$30,B38,$AJ$11:$AJ$30) -> 167414.1
B39: BAIHIVE | D39: =SUMIF($B$11:$B$30,B39,$AH$11:$AH$30) -> 145104.18 | E39: =SUMIF($B$11:$B$30,B39,$AJ$11:$AJ$30) -> 137848.97
B40: ZAP MEDIA | D40: =SUMIF($B$11:$B$30,B40,$AH$11:$AH$30) -> 0 | E40: =SUMIF($B$11:$B$30,B40,$AJ$11:$AJ$30) -> 0
B41: ADZEP | D41: =SUMIF($B$11:$B$30,B41,$AH$11:$AH$30) -> 176225.43 | E41: =SUMIF($B$11:$B$30,B41,$AJ$11:$AJ$30) -> 167414.16
B42: RANGE | D42: =SUMIF($B$11:$B$30,B42,$AH$11:$AH$30) -> 108000 | E42: =SUMIF($B$11:$B$30,B42,$AJ$11:$AJ$30) -> 102600
B43: SIMPLEADS | D43: =SUMIF($B$11:$B$30,B43,$AH$11:$AH$30) -> 0 | E43: =SUMIF($B$11:$B$30,B43,$AJ$11:$AJ$30) -> 0
B44: CITTAMOBI | D44: =SUMIF($B$11:$B$30,B44,$AH$11:$AH$30) -> 121684.77 | E44: =SUMIF($B$11:$B$30,B44,$AJ$11:$AJ$30) -> 115600.53
B45: MOOVIT | D45: =SUMIF($B$11:$B$30,B45,$AH$11:$AH$30) -> 0 | E45: =SUMIF($B$11:$B$30,B45,$AJ$11:$AJ$30) -> 0
B46: YOU TARGET | D46: =SUMIF($B$11:$B$30,B46,$AH$11:$AH$30) -> 149021.96 | E46: =SUMIF($B$11:$B$30,B46,$AJ$11:$AJ$30) -> 141570.87
B47: MITCH SMART | D47: =SUMIF($B$11:$B$30,B47,$AH$11:$AH$30) -> 0 | E47: =SUMIF($B$11:$B$30,B47,$AJ$11:$AJ$30) -> 0
... B50: TRIPLE A GAMES | D50: =SUMIF($B$11:$B$30,B50,$AH$11:$AH$30) -> 104668.52 | E50: =SUMIF($B$11:$B$30,B50,$AJ$11:$AJ$30) -> 99435.098
B51: TOTAL GERAL | D51: =SUM(D36:D50) -> 1688594.2 | E51: =SUM(E36:E50) -> 1650244.5
B53: AGENCIA | E53: VALOR 100% | F53: VALOR 95%
B54: CALIA | E54: =SUMIF($A$11:$A$30,B54,$AH$11:$AH$30) -> 0 | F54: =SUMIF($A$11:$A$30,B54,$AJ$11:$AJ$30) -> 0
B55: SA | E55: =SUMIF($A$11:$A$179,B55,$W$11:$W$179) -> 0 | F55: =SUMIF($A$11:$A$30,B55,$AJ$11:$AJ$30) -> 0
B56: DE BRITO | E56: =SUMIF($A$11:$A$179,B56,$W$11:$W$179) -> 0 | F56: =SUMIF($A$11:$A$30,B56,$AJ$11:$AJ$30) -> 0

Sheet RKG - Social Media
A1: Row | B1: Entity Type | C1: Status | D1: Social Media Measurement | E1: Entity | F1: Total Digital Population | H1: Social | J1: Desktop and Mobile | N1: Desktop | R1: Mobile
F2: Total Unique Visitors/Viewers (000) | G2: % Reach | H2: Total Unique Visitors/Viewers (000) | I2: % Reach | J2: Total Unique Visitors/Viewers (000) | K2: % Reach | L2: Total Views (MM) | M2: Total Visits (000) | N2: Total Unique Visitors/Viewers (000) | O2: % Reach | P2: Total Views (MM) | Q2: Total Visits (000) | R2: Total Unique Visitors/Viewers (000) | S2: % Reach | T2: Total Views (MM) | U2: Total Visits (000) | V2: Data Alerts
E3: Total Internet : Total Audience | F3: 131081.49 | G3: 100 | H3: 101649.46 | I3: 100 | J3: 131081.49 | K3: 100 | L3: 103108.18 | M3: 8183427.4 | N3: 41522.645 | O3: 100 | P3: 66137.255 | Q3: 1978862.3 | R3: 122421.29 | S3: 100 | T3: 36970.923 | U3: 6204565.1
B4: Subcategory | E4: Social Media - Social Networking | F4: 109291.2 | G4: 83.376536 | H4: n/a | I4: n/a | J4: 109291.2 | K4: 83.376536 | L4: 5409.6856 | M4: 614017.89 | N4: 24069.159 | O4: 57.966344 | P4: 3825.7104 | Q4: 262713.29 | R4: 98584.152 | S4: 80.528601 | T4: 1583.9752 | U4: 351304.61
A5: 1 | B5: [M] | C5: 0 | D5: 0 | E5: INSTAGRAM.COM | F5: 94618.165 | G5: 72.182705 | H5: n/a | I5: n/a | J5: 94618.165 | K5: 72.182705 | L5: 857.01188 | M5: 185287.29 | N5: 13767.065 | O5: 33.15556 | P5: 548.9762 | Q5: 120365.95 | R5: 88210.134 | S5: 72.05457 | T5: 308.03567 | U5: 64921.344
A6: 2 | B6: [M] | C6: 0 | D6: 0 | E6: Facebook And Messenger | F6: 84661.884 | G6: 64.587215 | H6: n/a | I6: n/a | J6: 84661.884 | K6: 64.587215 | L6: 1328.4549 | M6: 197462.41 | N6: 10579.813 | O6: 25.479621 | P6: 530.10904 | Q6: 60942.74 | R6: 79453.681 | S6: 64.901849 | T6: 798.34583 | U6: 136519.66
A7: 3 | B7: [P] | C7: 0 | D7: 0 | E7: Bytedance Inc. | F7: 83557.316 | G7: 63.744558 | H7: n/a | I7: n/a | J7: 83557.316 | K7: 63.744558 | L7: 2587.385 | M7: 98637.07 | N7: 7431.0452 | O7: 17.896368 | P7: 2496.3061 | Q7: 46337.334 | R7: 79811.893 | S7: 65.194455 | T7: 91.078904 | U7: 52299.736
A8: 4 | B8: [P] | C8: 0 | D8: 0 | E8: Pinterest | F8: 36338.408 | G8: 27.721998 | H8: n/a | I8: n/a | J8: 36338.408 | K8: 27.721998 | L8: 121.54484 | M8: 54873.438 | N8: 7159.8891 | O8: 17.243336 | P8: 67.104249 | Q8: 37176.698 | R8: 30722.358 | S8: 25.0956 | T8: 54.44059 | U8: 17696.74
A9: 5 | B9: [P] | C9: 0 | D9: 0 | E9: Kuaishou Technology | F9: 32933.478 | G9: 25.124431 | H9: n/a | I9: n/a | J9: 32933.478 | K9: 25.124431 | L9: 15.221607 | M9: 9312.4626 | N9: 263.11661 | O9: 0.63367016 | P9: 4.1862459 | Q9: 469.37314 | R9: 32734.556 | S9: 26.739267 | T9: 11.035361 | U9: 8843.0894
A10: 6 | B10: [P] | C10: 0 | D10: 0 | E10: X (formerly Twitter) | F10: 22003.239 | G10: 16.785924 | H10: n/a | I10: n/a | J10: 22003.239 | K10: 16.785924 | L10: 247.71845 | M10: 44224.363 | N10: 2462.424 | O10: 5.9303158 | P10: 87.607436 | Q10: 17681.998 | R10: 19913.611 | S10: 16.266461 | T10: 160.11102 | U10: 26542.365
A11: 7 | B11: [C] | C11: 0 | D11: 0 | E11: Google Meet (Google Duo) (Mobile App) | F11: 17656.752 | G11: 13.470058 | H11: n/a | I11: n/a | J11: 17656.752 | K11: 13.470058 | L11: 0 | M11: 0 | N11: n/a | O11: n/a | P11: n/a | Q11: n/a | R11: 17656.752 | S11: 14.422943 | T11: 0 | U11: 0
A12: 8 | B12: [P] | C12: 0 | D12: 0 | E12: Reddit | F12: 17335.482 | G12: 13.224965 | H12: n/a | I12: n/a | J12: 17335.482 | K12: 13.224965 | L12: 84.896641 | M12: 33587.147 | N12: 3558.2299 | O12: 8.5693721 | P12: 26.069834 | Q12: 9526.2906 | R12: 14160.509 | S12: 11.567031 | T12: 58.826808 | U12: 24060.856
A13: 9 | B13: [P] | C13: 0 | D13: 0 | E13: Linkedin | F13: 14780.045 | G13: 11.275463 | H13: n/a | I13: n/a | J13: 14780.045 | K13: 11.275463 | L13: 90.727146 | M13: 29567.741 | N13: 2669.8368 | O13: 6.4298332 | P13: 33.513825 | Q13: 9736.2421 | R13: 12360.03 | S13: 10.096308 | T13: 57.213322 | U13: 19831.499
A14: 10 | B14: [P] | C14: 0 | D14: 0 | E14: Snapchat, Inc | F14: 5485.3016 | G14: 4.1846501 | H14: n/a | I14: n/a | J14: 5485.3016 | K14: 4.1846501 | L14: 0.99702207 | M14: 655.20936 | N14: 31.789546 | O14: 0.076559541 | P14: 0.20362469 | Q14: 46.46624 | R14: 5454.8311 | S14: 4.4557863 | T14: 0.79339738 | U14: 608.74312
A15: 11 | B15: [P] | C15: 0 | D15: 0 | E15: Kwai Lite - mais simples (Mobile App) | F15: 3292.8399 | G15: 2.5120556 | H15: n/a | I15: n/a | J15: 3292.8399 | K15: 2.5120556 | L15: 0 | M15: 0 | N15: n/a | O15: n/a | P15: n/a | Q15: n/a | R15: 3292.8399 | S15: 2.6897608 | T15: 0 | U15: 0
A16: 12 | B16: [P] | C16: 0 | D16: 0 | E16: LIFE360.COM | F16: 2444.3866 | G16: 1.864784 | H16: n/a | I16: n/a | J16: 2444.3866 | K16: 1.864784 | L16: 0.0086333533 | M16: 6.535509 | N16: 6.2857486 | O16: 0.015138122 | P16: 0.0086333533 | Q16: 6.535509 | R16: 2438.2174 | S16: 1.9916613 | T16: 0 | U16: 0
A17: 13 | B17: [M] | C17: 0 | D17: 0 | E17: Zangi Messenger (Mobile App) | F17: 1460.7825 | G17: 1.1144079 | H17: n/a | I17: n/a | J17: 1460.7825 | K17: 1.1144079 | L17: 0 | M17: 0 | N17: n/a | O17: n/a | P17: n/a | Q17: n/a | R17: 1460.7825 | S17: 1.1932422 | T17: 0 | U17: 0
A18: 14 | B18: [P] | C18: 0 | D18: 0 | E18: BADOO.COM | F18: 1280.4023 | G18: 0.97679872 | H18: n/a | I18: n/a | J18: 1280.4023 | K18: 0.97679872 | L18: 0.54248495 | M18: 174.31472 | N18: 23.562944 | O18: 0.056747214 | P18: 0.54248495 | Q18: 174.31472 | R18: 1257.0647 | S18: 1.026835 | T18: 0 | U18: 0
A19: 15 | B19: [M] | C19: 1 | D19: 0 | E19: TUMBLR.COM* | F19: 1106.9016 | G19: 0.84443777 | H19: n/a | I19: n/a | J19: 1106.9016 | K19: 0.84443777 | L19: 13.132976 | M19: 2216.5215 | N19: 477.07565 | O19: 1.1489529 | P19: 6.0942948 | Q19: 968.85038 | R19: 632.11981 | S19: 0.51634794 | T19: 7.0386813 | U19: 1247.6711
A20: 16 | B20: [M] | C20: 0 | D20: 0 | E20: VAKINHA.COM.BR | F20: 1091.5422 | G20: 0.83272034 | H20: n/a | I20: n/a | J20: 1091.5422 | K20: 0.83272034 | L20: 4.997806 | M20: 2359.0882 | N20: 17.942471 | O20: 0.043211291 | P20: 0.1147589 | Q20: 21.562571 | R20: 1073.7463 | S20: 0.87709114 | T20: 4.8830471 | U20: 2337.5256
A21: 17 | B21: [M] | C21: 0 | D21: 0 | E21: ODNOKLASSNIKI.RU | F21: 861.96196 | G21: 0.65757718 | H21: n/a | I21: n/a | J21: 861.96196 | K21: 0.65757718 | L21: 5.0756521 | M21: 2307.2574 | N21: 131.52592 | O21: 0.3167571 | P21: 1.0980866 | Q21: 273.69768 | R21: 731.16752 | S21: 0.5972552 | T21: 3.9775656 | U21: 2033.5597
A22: 18 | B22: [M] | C22: 0 | D22: 0 | E22: DEVIANTART.COM | F22: 706.98104 | G22: 0.53934468 | H22: n/a | I22: n/a | J22: 706.98104 | K22: 0.53934468 | L22: 14.663746 | M22: 2482.4585 | N22: 150.83727 | O22: 0.36326507 | P22: 3.7592275 | Q22: 592.45118 | R22: 556.78259 | S22: 0.45480862 | T22: 10.904518 | U22: 1890.0073
A23: 19 | B23: [M] | C23: 0 | D23: 0 | E23: VK.COM | F23: 596.13453 | G23: 0.45478163 | H23: n/a | I23: n/a | J23: 596.13453 | K23: 0.45478163 | L23: 16.716305 | M23: 3832.1905 | N23: 102.27384 | O23: 0.24630858 | P23: 0.68794426 | Q23: 225.81499 | R23: 494.24518 | S23: 0.40372486 | T23: 16.02836 | U23: 3606.3755
A24: 20 | B24: [P] | C24: 0 | D24: 0 | E24: CHANGE.ORG | F24: 467.12181 | G24: 0.35635986 | H24: n/a | I24: n/a | J24: 467.12181 | K24: 0.35635986 | L24: 1.1016565 | M24: 511.01134 | N24: 25.148169 | O24: 0.060564949 | P24: 0.078329778 | Q24: 35.352579 | R24: 442.05821 | S24: 0.36109586 | T24: 1.0233267 | U24: 475.65876
A25: 21 | B25: [C] | C25: 0 | D25: 0 | E25: Google+ | F25: 437.58621 | G25: 0.33382761 | H25: n/a | I25: n/a | J25: 437.58621 | K25: 0.33382761 | L25: 0 | M25: 0 | N25: n/a | O25: n/a | P25: n/a | Q25: n/a | R25: 437.58621 | S25: 0.3574429 | T25: 0 | U25: 0
A26: 22 | B26: [C] | C26: 0 | D26: 0 | E26: LETTERBOXD.COM | F26: 350.16924 | G26: 0.26713859 | H26: n/a | I26: n/a | J26: 350.16924 | K26: 0.26713859 | L26: 1.9552902 | M26: 278.2369 | N26: 67.530906 | O26: 0.16263633 | P26: 1.9552902 | Q26: 278.2369 | R26: 282.78359 | S26: 0.23099217 | T26: 0 | U26: 0
A27: 23 | B27: [P] | C27: 0 | D27: 0 | E27: BEHANCE.NET | F27: 255.37513 | G27: 0.19482166 | H27: n/a | I27: n/a | J27: 255.37513 | K27: 0.19482166 | L27: 1.7481978 | M27: 653.63644 | N27: 255.37513 | O27: 0.61502617 | P27: 1.7481978 | Q27: 653.63644 | R27: n/a | S27: n/a | T27: n/a | U27: n/a
A28: 24 | B28: [P] | C28: 1 | D28: 0 | E28: VerticalScope | F28: 115.79962 | G28: 0.088341702 | H28: n/a | I28: n/a | J28: 115.79962 | K28: 0.088341702 | L28: 2.1235533 | M28: 429.17798 | N28: 70.576864 | O28: 0.16997198 | P28: 1.2348963 | Q28: 192.03831 | R28: 45.247045 | S28: 0.036960111 | T28: 0.88865697 | U28: 237.13967
A29: 25 | B29: [P] | C29: 0 | D29: 0 | E29: UNSPLASH.COM | F29: 97.778599 | G29: 0.07459375 | H29: n/a | I29: n/a | J29: 97.778599 | K29: 0.07459375 | L29: 0.19150337 | M29: 124.36047 | N29: 97.778599 | O29: 0.23548259 | P29: 0.19150337 | Q29: 124.36047 | R29: n/a | S29: n/a | T29: n/a | U29: n/a
A30: 26 | B30: [P] | C30: 0 | D30: 0 | E30: GRAPHCOMMENT.COM | F30: 69.436397 | G30: 0.052971932 | H30: n/a | I30: n/a | J30: 69.436397 | K30: 0.052971932 | L30: 1.7435659 | M30: 418.72865 | N30: 69.436397 | O30: 0.16722537 | P30: 1.7435659 | Q30: 418.72865 | R30: n/a | S30: n/a | T30: n/a | U30: n/a
A31: 27 | B31: [P] | C31: 0 | D31: 0 | E31: BEBEE.COM | F31: 28.177069 | G31: 0.021495842 | H31: n/a | I31: n/a | J31: 28.177069 | K31: 0.021495842 | L31: 0.40141655 | M31: 51.117667 | N31: 28.177069 | O31: 0.067859524 | P31: 0.40141655 | Q31: 51.117667 | R31: n/a | S31: n/a | T31: n/a | U31: n/a
A32: 28 | B32: [P] | C32: 0 | D32: 0 | E32: PIXIESET.COM | F32: 26.605999 | G32: 0.020297297 | H32: n/a | I32: n/a | J32: 26.605999 | K32: 0.020297297 | L32: 0.24144289 | M32: 66.757771 | N32: 26.605999 | O32: 0.064075876 | P32: 0.24144289 | Q32: 66.757771 | R32: n/a | S32: n/a | T32: n/a | U32: n/a
A33: 29 | B33: [C] | C33: 0 | D33: 0 | E33: GOODREADS.COM | F33: 20.154695 | G33: 0.015375699 | H33: n/a | I33: n/a | J33: 20.154695 | K33: 0.015375699 | L33: 0.16896825 | M33: 34.132052 | N33: 20.154695 | O33: 0.048539043 | P33: 0.16896825 | Q33: 34.132052 | R33: n/a | S33: n/a | T33: n/a | U33: n/a
A34: 30 | B34: [P] | C34: 0 | D34: 0 | E34: 500PX.COM | F34: 15.917773 | G34: 0.012143418 | H34: n/a | I34: n/a | J34: 15.917773 | K34: 0.012143418 | L34: 0.028715456 | M34: 16.942085 | N34: 15.917773 | O34: 0.038335162 | P34: 0.028715456 | Q34: 16.942085 | R34: n/a | S34: n/a | T34: n/a | U34: n/a
A35: 31 | B35: [M] | C35: 0 | D35: 0 | E35: PIXIV.NET | F35: 13.855406 | G35: 0.010570071 | H35: n/a | I35: n/a | J35: 13.855406 | K35: 0.010570071 | L35: 0.32592109 | M35: 119.06881 | N35: 13.855406 | O35: 0.033368313 | P35: 0.32592109 | Q35: 119.06881 | R35: n/a | S35: n/a | T35: n/a | U35: n/a
A36: 32 | B36: [M] | C36: 0 | D36: 0 | E36: Orkut | F36: 10.168563 | G36: 0.0077574366 | H36: n/a | I36: n/a | J36: 10.168563 | K36: 0.0077574366 | L36: 0.013456435 | M36: 10.737054 | N36: 10.168563 | O36: 0.0244892 | P36: 0.013456435 | Q36: 10.737054 | R36: n/a | S36: n/a | T36: n/a | U36: n/a
A37: 33 | B37: [P] | C37: 0 | D37: 0 | E37: BADOOCDN.COM | F37: 6.2103643 | G37: 0.0047377889 | H37: n/a | I37: n/a | J37: 6.2103643 | K37: 0.0047377889 | L37: 0.084334254 | M37: 33.041367 | N37: 6.2103643 | O37: 0.014956572 | P37: 0.084334254 | Q37: 33.041367 | R37: n/a | S37: n/a | T37: n/a | U37: n/a

Sheet CONTRA PARTIDA CARRO SOM
B2: PROGRAMAÇÃO - CARRO SOM - PROJETO
B4: =#REF! -> #REF!
B5: =#REF! -> #REF!
B6: =#REF! -> #REF!
B8: TOTAL - TOCANTINS | M8: =SUM(#REF!) -> #REF! | O8: =SUM(#REF!) -> #REF! | R8: =SUBTOTAL(9,#REF!) -> #REF! | S8: =R8*0.95 -> #REF!
B9: CÓDIGO MIDIACAD | C9: UF | D9: PRAÇA | E9: CÓD MUNICIPIO | F9: VEÍCULO | G9: COMUNIDADE | H9: FORMATO | J9: PERÍODO DE VEICULAÇÃO | M9: QUANTIDADE DE CARROS | N9: QTD. HORAS CARRO/DIA | O9: TT. HORAS | P9: VALOR TABELA | R9: DESC. % | S9: VALOR NEGOCIADO | U9: VALOR DESEMBOLSO 95% | V9: POPULAÇÃO | W9: PERÍODO | X9: IMPACTO PERÍODO | Y9: FONTE | Z9: CPI | AA9: CPM | AB9: RENTABILIDADE | AC9: REPRESENTANTE
H10: TIPO | I10: AMBIENTE | J10: INÍCIO | K10: FIM | L10: TOTAL DE DIAS | P10: UNITÁRIO | Q10: TOTAL | S10: UNITÁRIO | T10: TOTAL 100%
B12: 47612 | C12: MA | D12: MARANHÃO | F12: COMUNIDADE DOOR | G12: A DEFINIR | H12: CARRO DE SOM | I12: RUA | J12: 44669 | K12: =J12+L12-1 -> 44683 | L12: 15 | M12: 1 | N12: 1 | O12: =N12*M12*L12 -> 15 | P12: 450 | Q12: =P12*O12 -> 6750 | R12: 1 | S12: =P12-P12*R12 -> 0 | T12: =S12*O12 -> 0 | U12: =T12*0.95 -> 0 | V12: 7285 | W12: DIA | X12: =V12*L12 -> 109275 | Y12: VEÍCULO/IBGE | AA12: =(T12/X12)*1000 -> 0 | AB12: 1 | AC12: MOSAICO
B13: 47612 | C13: BA | D13: SALVADOR | F13: COMUNIDADE DOOR | G13: A DEFINIR | H13: CARRO DE SOM | I13: RUA | J13: 44669 | K13: =J13+L13-1 -> 44683 | L13: 15 | M13: 1 | N13: 1 | O13: =N13*M13*L13 -> 15 | P13: 450 | Q13: =P13*O13 -> 6750 | R13: 1 | S13: =P13-P13*R13 -> 0 | T13: =S13*O13 -> 0 | U13: =T13*0.95 -> 0 | V13: 4150 | W13: DIA | X13: =V13*L13 -> 62250 | Y13: VEÍCULO/IBGE | Z13: =T13/X13 -> 0 | AA13: =(T13/X13)*1000 -> 0 | AB13: 1 | AC13: MOSAICO
B14: 47612 | C14: AC | D14: RIO BRANCO | F14: COMUNIDADE DOOR | G14: A DEFINIR | H14: CARRO DE SOM | I14: RUA | J14: 44669 | K14: =J14+L14-1 -> 44683 | L14: 15 | M14: 1 | N14: 1 | O14: =N14*M14*L14 -> 15 | P14: 450 | Q14: =P14*O14 -> 6750 | R14: 1 | S14: =P14-P14*R14 -> 0 | T14: =S14*O14 -> 0 | U14: =T14*0.95 -> 0 | V14: 4150 | W14: DIA | X14: =V14*L14 -> 62250 | Y14: VEÍCULO/IBGE | Z14: =T14/X14 -> 0 | AA14: =(T14/X14)*1000 -> 0 | AB14: 1 | AC14: MOSAICO
G15: A DEFINIR | H15: CARRO DE SOM | I15: RUA | J15: 44669 | K15: =J15+L15-1 -> 44683 | L15: 15 | M15: 1 | N15: 1 | O15: =N15*M15*L15 -> 15 | P15: 450 | Q15: =P15*O15 -> 6750 | R15: 1 | S15: =P15-P15*R15 -> 0 | T15: =S15*O15 -> 0 | U15: =T15*0.95 -> 0 | V15: 4150 | W15: DIA | X15: =V15*L15 -> 62250 | Y15: VEÍCULO/IBGE | Z15: =T15/X15 -> 0 | AA15: =(T15/X15)*1000 -> 0 | AB15: 1 | AC15: MOSAICO
G16: A DEFINIR | H16: CARRO DE SOM | I16: RUA | J16: 44669 | K16: =J16+L16-1 -> 44683 | L16: 15 | M16: 1 | N16: 1 | O16: =N16*M16*L16 -> 15 | P16: 450 | Q16: =P16*O16 -> 6750 | R16: 1 | S16: =P16-P16*R16 -> 0 | T16: =S16*O16 -> 0 | U16: =T16*0.95 -> 0 | V16: 4150 | W16: DIA | X16: =V16*L16 -> 62250 | Y16: VEÍCULO/IBGE | Z16: =T16/X16 -> 0 | AA16: =(T16/X16)*1000 -> 0 | AB16: 1 | AC16: MOSAICO
B17: 35984 | C17: CE | D17: FORTALEZA | F17: GESTÃO PUBLICIDADE | G17: A DEFINIR | H17: CARRO DE SOM | I17: RUA | J17: 44669 | K17: =J17+L17-1 -> 44683 | L17: 15 | M17: 1 | N17: 1 | O17: =N17*M17*L17 -> 15 | P17: 450 | Q17: =P17*O17 -> 6750 | R17: 1 | S17: =P17-P17*R17 -> 0 | T17: =S17*O17 -> 0 | U17: =T17*0.95 -> 0 | V17: 3711 | W17: DIA | X17: =V17*L17 -> 55665 | Y17: VEÍCULO/IBGE | Z17: =T17/X17 -> 0 | AA17: =(T17/X17)*1000 -> 0 | AB17: 1 | AC17: GESTÃO
B18: TOTAL CARRO SOM | O18: =SUM(O10:O17) -> 90 | Q18: =SUM(Q10:Q17) -> 40500 | T18: =SUM(T10:T17) -> 0 | U18: =T18*0.95 -> 0 | AA18: =AVERAGE(AA10:AA17)*1.5 -> 0
B21: OBSERVAÇÃO:
B22: CARRO SOM NAS COMUNIDADES
B23: 1 HORA POR 15 DIAS
D54: =SUBTOTAL(9,D19:D53) -> 0

Sheet CONTRA PARTIDA RÁDIO COM. 
B2: PROGRAMAÇÃO - RÁDIOS COMUNITÁRIAS - PROJETO
B4: =#REF! -> #REF!
B5: =#REF! -> #REF!
B6: =#REF! -> #REF!
B8: ID. SECOM | C8: UF | D8: MUNICÍPIO VEICULAÇÃO | E8: CÓD. MUNICÍPIO | F8: POPULAÇÃO | G8: COMUNIDADE | H8: NOME FANTASIA | I8: PRX | J8: FAIXA HORÁRIA | L8: ABRIL 2022 | AM8: MAIO 2022 | AT8: TT. INS. | AU8: CUSTO TABELA | AW8: % DESC. PUP. | AX8: CUSTO NEGOCIADO | AZ8: CUSTO DESEMBOLSO 95% | BA8: IA % IBOPE | BB8: IA # IBOPE | BC8: REPRESENTANTE
J9: INÍCIO | K9: FIM | L9: S | M9: T | N9: Q | O9: Q | P9: S | Q9: S | R9: D | S9: S | T9: T | U9: Q | V9: Q | W9: S | X9: S | Y9: D | Z9: S | AA9: T | AB9: Q | AC9: Q | AD9: S | AE9: S | AF9: D | AG9: S | AH9: T | AI9: Q | AJ9: Q | AK9: S | AL9: S | AM9: D | AN9: S | AO9: T | AP9: Q | AQ9: Q | AR9: S | AS9: S | AU9: UNITÁRIO 30" | AV9: TOTAL | AX9: UNITÁRIO | AY9: TOTAL
L10: 4 | M10: =L10+1 -> 5 | N10: =M10+1 -> 6 | O10: =N10+1 -> 7 | P10: =O10+1 -> 8 | Q10: =P10+1 -> 9 | R10: =Q10+1 -> 10 | S10: =R10+1 -> 11 | T10: =S10+1 -> 12 | ... AL10: =AK10+1 -> 30 | AM10: 1 | AN10: =AM10+1 -> 2 | AO10: =AN10+1 -> 3 | AP10: =AO10+1 -> 4 | AQ10: =AP10+1 -> 5 | AR10: =AQ10+1 -> 6 | AS10: =AR10+1 -> 7
B11: 47612 | C11: MA | D11: MARANHÃO | F11: COMUNIDADE DOOR | G11: A DEFINIR | H11: RÁDIO COMUNITÁRIA | J11: 0.29166667 | K11: 0.79166667 | Z11: 10 | AA11: 10 | AB11: 10 | AC11: 10 | AD11: 10 | AG11: 10 | AH11: 10 | AI11: 10 | AJ11: 10 | AK11: 10 | AT11: =SUM(L11:AS11) -> 100 | AU11: 30 | AV11: =AU11*AT11 -> 3000 | AW11: 1 | AX11: =AU11-AU11*AW11 -> 0 | AY11: =AX11*AT11 -> 0 | AZ11: =AY11*0.95 -> 0 | BC11: MOSAICO
B12: 47612 | C12: BA | D12: SALVADOR | F12: COMUNIDADE DOOR | G12: A DEFINIR | H12: RÁDIO COMUNITÁRIA | J12: 0.29166667 | K12: 0.79166667 | Z12: 10 | AA12: 10 | AB12: 10 | AC12: 10 | AD12: 10 | AG12: 10 | AH12: 10 | AI12: 10 | AJ12: 10 | AK12: 10 | AT12: =SUM(L12:AS12) -> 100 | AU12: 30 | AV12: =AU12*AT12 -> 3000 | AW12: 1 | AX12: =AU12-AU12*AW12 -> 0 | AY12: =AX12*AT12 -> 0 | AZ12: =AY12*0.95 -> 0 | BC12: MOSAICO
B13: 47612 | C13: AC | D13: RIO BRANCO | F13: COMUNIDADE DOOR | G13: A DEFINIR | H13: RÁDIO COMUNITÁRIA | J13: 0.29166667 | K13: 0.79166667 | Z13: 10 | AA13: 10 | AB13: 10 | AC13: 10 | AD13: 10 | AG13: 10 | AH13: 10 | AI13: 10 | AJ13: 10 | AK13: 10 | AT13: =SUM(L13:AS13) -> 100 | AU13: 30 | AV13: =AU13*AT13 -> 3000 | AW13: 1 | AX13: =AU13-AU13*AW13 -> 0 | AY13: =AX13*AT13 -> 0 | AZ13: =AY13*0.95 -> 0 | BC13: MOSAICO
B14: 35984 | C14: CE | D14: FORTALEZA | F14: GESTÃO PUBLICIDADE | G14: A DEFINIR | H14: RÁDIO COMUNITÁRIA | J14: 0.29166667 | K14: 0.79166667 | Z14: 10 | AA14: 10 | AB14: 10 | AC14: 10 | AD14: 10 | AG14: 10 | AH14: 10 | AI14: 10 | AJ14: 10 | AK14: 10 | AT14: =SUM(L14:AS14) -> 100 | AU14: 30 | AV14: =AU14*AT14 -> 3000 | AW14: 1 | AX14: =AU14-AU14*AW14 -> 0 | AY14: =AX14*AT14 -> 0 | AZ14: =AY14*0.95 -> 0 | BC14: GESTÃO
AT15: =SUM(AT11:AT14) -> 400 | AV15: =SUM(AV11:AV14) -> 12000 | AY15: =SUM(AY11:AY14) -> 0 | AZ15: =AY15*0.95 -> 0
B17: OBSERVAÇÃO:
B18: RÁDIOS COMUNITÁRIAS BONIFICADAS
B19: 10 INSERÇÕES/DIA
